Workbook

Sheet BASE_PAGAMENTOS
A1: Tipo/NroDocto | B1: Tipo/NroCartão | C1: Embarque | D1: Pagamento | E1: Tipo | F1: Valor Transação | G1: Status | H1: Nome do Favorecido | I1: Documento do Favorecido | J1: Placa do veículo | K1: ID Viagem | L1: Filial | M1: Contrato de Frete | N1: Carga | O1: CT´es | P1: UF Filial | Q1: UF Destino | R1: Situação da CF | S1: Situação da carga | T1: Status Financeiro | U1: Prazo | V1: DT de pagamento | W1: Cont_caracter | X1: DEF_PRESTADOR | Y1: REFERENCIA | Z1: PRESTADOR | AA1: Email_transp
A2: CON:277 | B2: 4417812014686304 | C2: 45833 | D2: 45833 | E2: ADT | F2: 300 | G2: EFETIVADA | H2: SILVERIO DA SILVEIRA | I2: 17250059000130 | J2: ATL5J69 | K2: 100902598 | L2: SP | M2: 144264 | N2: 262876 | O2: 277 | P2: RS | Q2: RS | R2: Finalizado | S2: Finalizada | T2: EFETIVADA | U2: Quinta feira | V2: Quinta feira | W2: =LEN(I2) -> 14 | X2: =IF(W2=14,"CNPJ",IF(W2=12,"CNPJ_INCOMPLETO_2",IF(W2=13,"CNPJ_INCOMPLETO_1",IF(W2=10,"CPF_Incompleto","CPF")))) -> CNPJ | Y2: =IF(X2="CNPJ_INCOMPLETO_1",("0"&LEFT(I2,1)&"."&MID(I2,2,3)&"."&MID(I2,5,3)&"/"&MID(I2,8,4)&"-"&MID(I2,12,2)),IF(X2="CNPJ_INCOMPLETO_2",("00."&LEFT(I2,3)&"."&MID(I2,4,3)&"/"&MID(I2,7,4)&"-"&MID(I2,11,2)),IF(X2="CNPJ",(LEFT(I2,2)&"."&MID(I2,3,3)&"."&MID(I2,6,3)&"/"&MID(I2,9,4)&"-"&MID(I2,13,2)),IF(X2="CPF_Incompleto",("0"&LEFT(I2,2)&"."&MID(I2,3,3)&"."&MID(I2,6,3)&"-"&MID(I2,9,2)),(LEFT(I2,3)&"."&MID(I2,4,3)&"."&MID(I2,7,3)&"-"&MID(I2,10,2)))))) -> 17.250.059/0001-30 | Z2: =VLOOKUP(Y2,FORNECEDORES!$A$2:$G$9043,3,0) -> SILVERIO DA SILVEIRA ME | AA2: =VLOOKUP(Y2,FORNECEDORES!$A$2:$G$9041,7,0) -> silveriosilveira86@hotmail.com;
A3: CON:277 | B3: 4417812014686304 | C3: 45833 | D3: 45834 | E3: SDO | F3: 200 | G3: EFETIVADA | H3: SILVERIO DA SILVEIRA | I3: 17250059000130 | J3: ATL5J69 | K3: 100902598 | L3: SP | M3: 144264 | N3: 262876 | O3: 277 | P3: RS | Q3: RS | R3: Finalizado | S3: Finalizada | T3: EFETIVADA | U3: Quinta feira | V3: Quinta feira | W3: =LEN(I3) -> 14 | X3: =IF(W3=14,"CNPJ",IF(W3=12,"CNPJ_INCOMPLETO_2",IF(W3=13,"CNPJ_INCOMPLETO_1",IF(W3=10,"CPF_Incompleto","CPF")))) -> CNPJ | Y3: =IF(X3="CNPJ_INCOMPLETO_1",("0"&LEFT(I3,1)&"."&MID(I3,2,3)&"."&MID(I3,5,3)&"/"&MID(I3,8,4)&"-"&MID(I3,12,2)),IF(X3="CNPJ_INCOMPLETO_2",("00."&LEFT(I3,3)&"."&MID(I3,4,3)&"/"&MID(I3,7,4)&"-"&MID(I3,11,2)),IF(X3="CNPJ",(LEFT(I3,2)&"."&MID(I3,3,3)&"."&MID(I3,6,3)&"/"&MID(I3,9,4)&"-"&MID(I3,13,2)),IF(X3="CPF_Incompleto",("0"&LEFT(I3,2)&"."&MID(I3,3,3)&"."&MID(I3,6,3)&"-"&MID(I3,9,2)),(LEFT(I3,3)&"."&MID(I3,4,3)&"."&MID(I3,7,3)&"-"&MID(I3,10,2)))))) -> 17.250.059/0001-30 | Z3: =VLOOKUP(Y3,FORNECEDORES!$A$2:$G$9043,3,0) -> SILVERIO DA SILVEIRA ME | AA3: =VLOOKUP(Y3,FORNECEDORES!$A$2:$G$9041,7,0) -> silveriosilveira86@hotmail.com;
A4: CON:3464 | B4: 4417812010875943 | C4: 45833 | D4: 45863 | E4: DES | F4: 540 | G4: EFETIVADA | H4: ANDRE L.A. ENDRES - ME | I4: 92309194000120 | J4: AFK2804 | K4: 100904258 | L4: SP | M4: 144268 | N4: 262898 | O4: 3464 | P4: RS | Q4: RS | R4: Finalizado | S4: Finalizada | T4: EFETIVADA | U4: 30 | V4: 45868 | W4: =LEN(I4) -> 14 | X4: =IF(W4=14,"CNPJ",IF(W4=12,"CNPJ_INCOMPLETO_2",IF(W4=13,"CNPJ_INCOMPLETO_1",IF(W4=10,"CPF_Incompleto","CPF")))) -> CNPJ | Y4: =IF(X4="CNPJ_INCOMPLETO_1",("0"&LEFT(I4,1)&"."&MID(I4,2,3)&"."&MID(I4,5,3)&"/"&MID(I4,8,4)&"-"&MID(I4,12,2)),IF(X4="CNPJ_INCOMPLETO_2",("00."&LEFT(I4,3)&"."&MID(I4,4,3)&"/"&MID(I4,7,4)&"-"&MID(I4,11,2)),IF(X4="CNPJ",(LEFT(I4,2)&"."&MID(I4,3,3)&"."&MID(I4,6,3)&"/"&MID(I4,9,4)&"-"&MID(I4,13,2)),IF(X4="CPF_Incompleto",("0"&LEFT(I4,2)&"."&MID(I4,3,3)&"."&MID(I4,6,3)&"-"&MID(I4,9,2)),(LEFT(I4,3)&"."&MID(I4,4,3)&"."&MID(I4,7,3)&"-"&MID(I4,10,2)))))) -> 92.309.194/0001-20 | Z4: =VLOOKUP(Y4,FORNECEDORES!$A$2:$G$9043,3,0) -> ANDRE L.A. ENDRES - ME | AA4: =VLOOKUP(Y4,FORNECEDORES!$A$2:$G$9041,7,0) -> endrestransportes@outlook.com
A5: CON:3466 | B5: 4417812013265605 | C5: 45833 | D5: 45834 | E5: ADT | F5: 1693.02 | G5: EFETIVADA | H5: VANDERLI DASSOLER | I5: 58751050030 | J5: MKS4A50 | K5: 100923624 | L5: SP | M5: 144295 | N5: 262986 | O5: 3466 | P5: RS | Q5: RS | R5: Finalizado | S5: Finalizada | T5: EFETIVADA | U5: Quinta feira | V5: Quinta feira | W5: =LEN(I5) -> 11 | X5: =IF(W5=14,"CNPJ",IF(W5=12,"CNPJ_INCOMPLETO_2",IF(W5=13,"CNPJ_INCOMPLETO_1",IF(W5=10,"CPF_Incompleto","CPF")))) -> CPF | Y5: =IF(X5="CNPJ_INCOMPLETO_1",("0"&LEFT(I5,1)&"."&MID(I5,2,3)&"."&MID(I5,5,3)&"/"&MID(I5,8,4)&"-"&MID(I5,12,2)),IF(X5="CNPJ_INCOMPLETO_2",("00."&LEFT(I5,3)&"."&MID(I5,4,3)&"/"&MID(I5,7,4)&"-"&MID(I5,11,2)),IF(X5="CNPJ",(LEFT(I5,2)&"."&MID(I5,3,3)&"."&MID(I5,6,3)&"/"&MID(I5,9,4)&"-"&MID(I5,13,2)),IF(X5="CPF_Incompleto",("0"&LEFT(I5,2)&"."&MID(I5,3,3)&"."&MID(I5,6,3)&"-"&MID(I5,9,2)),(LEFT(I5,3)&"."&MID(I5,4,3)&"."&MID(I5,7,3)&"-"&MID(I5,10,2)))))) -> 587.510.500-30 | Z5: =VLOOKUP(Y5,FORNECEDORES!$A$2:$G$9043,3,0) -> VANDERLI DASSOLER | AA5: =VLOOKUP(Y5,FORNECEDORES!$A$2:$G$9041,7,0) -> vanderliegv@gmail.com;
A6: CON:3466 | B6: 4417812013265605 | C6: 45833 | D6: 45834 | E6: SDO | F6: 1128.68 | G6: EFETIVADA | H6: VANDERLI DASSOLER | I6: 58751050030 | J6: MKS4A50 | K6: 100923624 | L6: SP | M6: 144295 | N6: 262986 | O6: 3466 | P6: RS | Q6: RS | R6: Finalizado | S6: Finalizada | T6: EFETIVADA | U6: Quinta feira | V6: Quinta feira | W6: =LEN(I6) -> 11 | X6: =IF(W6=14,"CNPJ",IF(W6=12,"CNPJ_INCOMPLETO_2",IF(W6=13,"CNPJ_INCOMPLETO_1",IF(W6=10,"CPF_Incompleto","CPF")))) -> CPF | Y6: =IF(X6="CNPJ_INCOMPLETO_1",("0"&LEFT(I6,1)&"."&MID(I6,2,3)&"."&MID(I6,5,3)&"/"&MID(I6,8,4)&"-"&MID(I6,12,2)),IF(X6="CNPJ_INCOMPLETO_2",("00."&LEFT(I6,3)&"."&MID(I6,4,3)&"/"&MID(I6,7,4)&"-"&MID(I6,11,2)),IF(X6="CNPJ",(LEFT(I6,2)&"."&MID(I6,3,3)&"."&MID(I6,6,3)&"/"&MID(I6,9,4)&"-"&MID(I6,13,2)),IF(X6="CPF_Incompleto",("0"&LEFT(I6,2)&"."&MID(I6,3,3)&"."&MID(I6,6,3)&"-"&MID(I6,9,2)),(LEFT(I6,3)&"."&MID(I6,4,3)&"."&MID(I6,7,3)&"-"&MID(I6,10,2)))))) -> 587.510.500-30 | Z6: =VLOOKUP(Y6,FORNECEDORES!$A$2:$G$9043,3,0) -> VANDERLI DASSOLER | AA6: =VLOOKUP(Y6,FORNECEDORES!$A$2:$G$9041,7,0) -> vanderliegv@gmail.com;
A7: CON:3467 | B7: 4417812010875943 | C7: 45833 | D7: 45863 | E7: DES | F7: 2700 | G7: EFETIVADA | H7: ANDRE L.A. ENDRES - ME | I7: 92309194000120 | J7: AFK2804 | K7: 100928877 | L7: SP | M7: 144301 | N7: 262997 | O7: 3467 | P7: RS | Q7: RS | R7: Finalizado | S7: Finalizada | T7: EFETIVADA | U7: 30 | V7: 45868 | W7: =LEN(I7) -> 14 | X7: =IF(W7=14,"CNPJ",IF(W7=12,"CNPJ_INCOMPLETO_2",IF(W7=13,"CNPJ_INCOMPLETO_1",IF(W7=10,"CPF_Incompleto","CPF")))) -> CNPJ | Y7: =IF(X7="CNPJ_INCOMPLETO_1",("0"&LEFT(I7,1)&"."&MID(I7,2,3)&"."&MID(I7,5,3)&"/"&MID(I7,8,4)&"-"&MID(I7,12,2)),IF(X7="CNPJ_INCOMPLETO_2",("00."&LEFT(I7,3)&"."&MID(I7,4,3)&"/"&MID(I7,7,4)&"-"&MID(I7,11,2)),IF(X7="CNPJ",(LEFT(I7,2)&"."&MID(I7,3,3)&"."&MID(I7,6,3)&"/"&MID(I7,9,4)&"-"&MID(I7,13,2)),IF(X7="CPF_Incompleto",("0"&LEFT(I7,2)&"."&MID(I7,3,3)&"."&MID(I7,6,3)&"-"&MID(I7,9,2)),(LEFT(I7,3)&"."&MID(I7,4,3)&"."&MID(I7,7,3)&"-"&MID(I7,10,2)))))) -> 92.309.194/0001-20 | Z7: =VLOOKUP(Y7,FORNECEDORES!$A$2:$G$9043,3,0) -> ANDRE L.A. ENDRES - ME | AA7: =VLOOKUP(Y7,FORNECEDORES!$A$2:$G$9041,7,0) -> endrestransportes@outlook.com
A8: CON:3468 | B8: 4417812015511030 | C8: 45834 | D8: 45834 | E8: ADT | F8: 992.46 | G8: EFETIVADA | H8: Denis Camillo Da Silva | I8: 96685697091 | J8: IQM9933 | K8: 100946382 | L8: SP | M8: 144327 | N8: 263038 | O8: 3468, 3469 | P8: RS | Q8: RS | R8: Finalizado | S8: Finalizada | T8: EFETIVADA | U8: Quinta feira | V8: Quinta feira | W8: =LEN(I8) -> 11 | X8: =IF(W8=14,"CNPJ",IF(W8=12,"CNPJ_INCOMPLETO_2",IF(W8=13,"CNPJ_INCOMPLETO_1",IF(W8=10,"CPF_Incompleto","CPF")))) -> CPF | Y8: =IF(X8="CNPJ_INCOMPLETO_1",("0"&LEFT(I8,1)&"."&MID(I8,2,3)&"."&MID(I8,5,3)&"/"&MID(I8,8,4)&"-"&MID(I8,12,2)),IF(X8="CNPJ_INCOMPLETO_2",("00."&LEFT(I8,3)&"."&MID(I8,4,3)&"/"&MID(I8,7,4)&"-"&MID(I8,11,2)),IF(X8="CNPJ",(LEFT(I8,2)&"."&MID(I8,3,3)&"."&MID(I8,6,3)&"/"&MID(I8,9,4)&"-"&MID(I8,13,2)),IF(X8="CPF_Incompleto",("0"&LEFT(I8,2)&"."&MID(I8,3,3)&"."&MID(I8,6,3)&"-"&MID(I8,9,2)),(LEFT(I8,3)&"."&MID(I8,4,3)&"."&MID(I8,7,3)&"-"&MID(I8,10,2)))))) -> 966.856.970-91 | Z8: =VLOOKUP(Y8,FORNECEDORES!$A$2:$G$9043,3,0) -> DENIS CAMILLO DA SILVA | AA8: =VLOOKUP(Y8,FORNECEDORES!$A$2:$G$9041,7,0) -> deniscamillo29@gmail.com;
A9: CON:3468 | B9: 4417812015511030 | C9: 45834 | D9: 45841 | E9: SDO | F9: 661.64 | G9: EFETIVADA | H9: Denis Camillo Da Silva | I9: 96685697091 | J9: IQM9933 | K9: 100946382 | L9: SP | M9: 144327 | N9: 263038 | O9: 3468, 3469 | P9: RS | Q9: RS | R9: Finalizado | S9: Finalizada | T9: EFETIVADA | U9: Quinta feira | V9: Quinta feira | W9: =LEN(I9) -> 11 | X9: =IF(W9=14,"CNPJ",IF(W9=12,"CNPJ_INCOMPLETO_2",IF(W9=13,"CNPJ_INCOMPLETO_1",IF(W9=10,"CPF_Incompleto","CPF")))) -> CPF | Y9: =IF(X9="CNPJ_INCOMPLETO_1",("0"&LEFT(I9,1)&"."&MID(I9,2,3)&"."&MID(I9,5,3)&"/"&MID(I9,8,4)&"-"&MID(I9,12,2)),IF(X9="CNPJ_INCOMPLETO_2",("00."&LEFT(I9,3)&"."&MID(I9,4,3)&"/"&MID(I9,7,4)&"-"&MID(I9,11,2)),IF(X9="CNPJ",(LEFT(I9,2)&"."&MID(I9,3,3)&"."&MID(I9,6,3)&"/"&MID(I9,9,4)&"-"&MID(I9,13,2)),IF(X9="CPF_Incompleto",("0"&LEFT(I9,2)&"."&MID(I9,3,3)&"."&MID(I9,6,3)&"-"&MID(I9,9,2)),(LEFT(I9,3)&"."&MID(I9,4,3)&"."&MID(I9,7,3)&"-"&MID(I9,10,2)))))) -> 966.856.970-91 | Z9: =VLOOKUP(Y9,FORNECEDORES!$A$2:$G$9043,3,0) -> DENIS CAMILLO DA SILVA | AA9: =VLOOKUP(Y9,FORNECEDORES!$A$2:$G$9041,7,0) -> deniscamillo29@gmail.com;
A10: CON:3470 | B10: 4417812022858440 | C10: 45834 | D10: 45834 | E10: ADT | F10: 1693.02 | G10: EFETIVADA | H10: JOSE DAGOBERTO MACHADO | I10: 40573680000 | J10: IKV8F25 | K10: 100951395 | L10: SP | M10: 144330 | N10: 263046 | O10: 3470 | P10: RS | Q10: RS | R10: Finalizado | S10: Finalizada | T10: EFETIVADA | U10: Quinta feira | V10: Quinta feira | W10: =LEN(I10) -> 11 | X10: =IF(W10=14,"CNPJ",IF(W10=12,"CNPJ_INCOMPLETO_2",IF(W10=13,"CNPJ_INCOMPLETO_1",IF(W10=10,"CPF_Incompleto","CPF")))) -> CPF | Y10: =IF(X10="CNPJ_INCOMPLETO_1",("0"&LEFT(I10,1)&"."&MID(I10,2,3)&"."&MID(I10,5,3)&"/"&MID(I10,8,4)&"-"&MID(I10,12,2)),IF(X10="CNPJ_INCOMPLETO_2",("00."&LEFT(I10,3)&"."&MID(I10,4,3)&"/"&MID(I10,7,4)&"-"&MID(I10,11,2)),IF(X10="CNPJ",(LEFT(I10,2)&"."&MID(I10,3,3)&"."&MID(I10,6,3)&"/"&MID(I10,9,4)&"-"&MID(I10,13,2)),IF(X10="CPF_Incompleto",("0"&LEFT(I10,2)&"."&MID(I10,3,3)&"."&MID(I10,6,3)&"-"&MID(I10,9,2)),(LEFT(I10,3)&"."&MID(I10,4,3)&"."&MID(I10,7,3)&"-"&MID(I10,10,2)))))) -> 405.736.800-00 | Z10: =VLOOKUP(Y10,FORNECEDORES!$A$2:$G$9043,3,0) -> JOSÉ DAGOBERTO MACHADO | AA10: =VLOOKUP(Y10,FORNECEDORES!$A$2:$G$9041,7,0) -> jdmdago@gmail.com;
A11: CON:3470 | B11: 4417812022858440 | C11: 45834 | D11: 45841 | E11: SDO | F11: 1128.68 | G11: EFETIVADA | H11: JOSE DAGOBERTO MACHADO | I11: 40573680000 | J11: IKV8F25 | K11: 100951395 | L11: SP | M11: 144330 | N11: 263046 | O11: 3470 | P11: RS | Q11: RS | R11: Finalizado | S11: Finalizada | T11: EFETIVADA | U11: Quinta feira | V11: Quinta feira | W11: =LEN(I11) -> 11 | X11: =IF(W11=14,"CNPJ",IF(W11=12,"CNPJ_INCOMPLETO_2",IF(W11=13,"CNPJ_INCOMPLETO_1",IF(W11=10,"CPF_Incompleto","CPF")))) -> CPF | Y11: =IF(X11="CNPJ_INCOMPLETO_1",("0"&LEFT(I11,1)&"."&MID(I11,2,3)&"."&MID(I11,5,3)&"/"&MID(I11,8,4)&"-"&MID(I11,12,2)),IF(X11="CNPJ_INCOMPLETO_2",("00."&LEFT(I11,3)&"."&MID(I11,4,3)&"/"&MID(I11,7,4)&"-"&MID(I11,11,2)),IF(X11="CNPJ",(LEFT(I11,2)&"."&MID(I11,3,3)&"."&MID(I11,6,3)&"/"&MID(I11,9,4)&"-"&MID(I11,13,2)),IF(X11="CPF_Incompleto",("0"&LEFT(I11,2)&"."&MID(I11,3,3)&"."&MID(I11,6,3)&"-"&MID(I11,9,2)),(LEFT(I11,3)&"."&MID(I11,4,3)&"."&MID(I11,7,3)&"-"&MID(I11,10,2)))))) -> 405.736.800-00 | Z11: =VLOOKUP(Y11,FORNECEDORES!$A$2:$G$9043,3,0) -> JOSÉ DAGOBERTO MACHADO | AA11: =VLOOKUP(Y11,FORNECEDORES!$A$2:$G$9041,7,0) -> jdmdago@gmail.com;
A12: CON:3472 | B12: 4417812013265605 | C12: 45835 | D12: 45835 | E12: ADT | F12: 1576.26 | G12: EFETIVADA | H12: VANDERLI DASSOLER | I12: 58751050030 | J12: MKS4A50 | K12: 100980043 | L12: SP | M12: 144379 | N12: 263152 | O12: 3472 | P12: RS | Q12: RS | R12: Finalizado | S12: Finalizada | T12: EFETIVADA | U12: Quinta feira | V12: Quinta feira | W12: =LEN(I12) -> 11 | X12: =IF(W12=14,"CNPJ",IF(W12=12,"CNPJ_INCOMPLETO_2",IF(W12=13,"CNPJ_INCOMPLETO_1",IF(W12=10,"CPF_Incompleto","CPF")))) -> CPF | Y12: =IF(X12="CNPJ_INCOMPLETO_1",("0"&LEFT(I12,1)&"."&MID(I12,2,3)&"."&MID(I12,5,3)&"/"&MID(I12,8,4)&"-"&MID(I12,12,2)),IF(X12="CNPJ_INCOMPLETO_2",("00."&LEFT(I12,3)&"."&MID(I12,4,3)&"/"&MID(I12,7,4)&"-"&MID(I12,11,2)),IF(X12="CNPJ",(LEFT(I12,2)&"."&MID(I12,3,3)&"."&MID(I12,6,3)&"/"&MID(I12,9,4)&"-"&MID(I12,13,2)),IF(X12="CPF_Incompleto",("0"&LEFT(I12,2)&"."&MID(I12,3,3)&"."&MID(I12,6,3)&"-"&MID(I12,9,2)),(LEFT(I12,3)&"."&MID(I12,4,3)&"."&MID(I12,7,3)&"-"&MID(I12,10,2)))))) -> 587.510.500-30 | Z12: =VLOOKUP(Y12,FORNECEDORES!$A$2:$G$9043,3,0) -> VANDERLI DASSOLER | AA12: =VLOOKUP(Y12,FORNECEDORES!$A$2:$G$9041,7,0) -> vanderliegv@gmail.com;
A13: CON:3472 | B13: 4417812013265605 | C13: 45835 | D13: 45841 | E13: SDO | F13: 1050.84 | G13: EFETIVADA | H13: VANDERLI DASSOLER | I13: 58751050030 | J13: MKS4A50 | K13: 100980043 | L13: SP | M13: 144379 | N13: 263152 | O13: 3472 | P13: RS | Q13: RS | R13: Finalizado | S13: Finalizada | T13: EFETIVADA | U13: Quinta feira | V13: Quinta feira | W13: =LEN(I13) -> 11 | X13: =IF(W13=14,"CNPJ",IF(W13=12,"CNPJ_INCOMPLETO_2",IF(W13=13,"CNPJ_INCOMPLETO_1",IF(W13=10,"CPF_Incompleto","CPF")))) -> CPF | Y13: =IF(X13="CNPJ_INCOMPLETO_1",("0"&LEFT(I13,1)&"."&MID(I13,2,3)&"."&MID(I13,5,3)&"/"&MID(I13,8,4)&"-"&MID(I13,12,2)),IF(X13="CNPJ_INCOMPLETO_2",("00."&LEFT(I13,3)&"."&MID(I13,4,3)&"/"&MID(I13,7,4)&"-"&MID(I13,11,2)),IF(X13="CNPJ",(LEFT(I13,2)&"."&MID(I13,3,3)&"."&MID(I13,6,3)&"/"&MID(I13,9,4)&"-"&MID(I13,13,2)),IF(X13="CPF_Incompleto",("0"&LEFT(I13,2)&"."&MID(I13,3,3)&"."&MID(I13,6,3)&"-"&MID(I13,9,2)),(LEFT(I13,3)&"."&MID(I13,4,3)&"."&MID(I13,7,3)&"-"&MID(I13,10,2)))))) -> 587.510.500-30 | Z13: =VLOOKUP(Y13,FORNECEDORES!$A$2:$G$9043,3,0) -> VANDERLI DASSOLER | AA13: =VLOOKUP(Y13,FORNECEDORES!$A$2:$G$9041,7,0) -> vanderliegv@gmail.com;
A14: CON:3473 | B14: 4417812010875943 | C14: 45835 | D14: 45866 | E14: DES | F14: 1800 | G14: EFETIVADA | H14: ANDRE L.A. ENDRES - ME | I14: 92309194000120 | J14: AFK2804 | K14: 100981423 | L14: SP | M14: 144380 | N14: 263153 | O14: 3473 | P14: RS | Q14: RS | R14: Finalizado | S14: Finalizada | T14: EFETIVADA | U14: 30 | V14: 45868 | W14: =LEN(I14) -> 14 | X14: =IF(W14=14,"CNPJ",IF(W14=12,"CNPJ_INCOMPLETO_2",IF(W14=13,"CNPJ_INCOMPLETO_1",IF(W14=10,"CPF_Incompleto","CPF")))) -> CNPJ | Y14: =IF(X14="CNPJ_INCOMPLETO_1",("0"&LEFT(I14,1)&"."&MID(I14,2,3)&"."&MID(I14,5,3)&"/"&MID(I14,8,4)&"-"&MID(I14,12,2)),IF(X14="CNPJ_INCOMPLETO_2",("00."&LEFT(I14,3)&"."&MID(I14,4,3)&"/"&MID(I14,7,4)&"-"&MID(I14,11,2)),IF(X14="CNPJ",(LEFT(I14,2)&"."&MID(I14,3,3)&"."&MID(I14,6,3)&"/"&MID(I14,9,4)&"-"&MID(I14,13,2)),IF(X14="CPF_Incompleto",("0"&LEFT(I14,2)&"."&MID(I14,3,3)&"."&MID(I14,6,3)&"-"&MID(I14,9,2)),(LEFT(I14,3)&"."&MID(I14,4,3)&"."&MID(I14,7,3)&"-"&MID(I14,10,2)))))) -> 92.309.194/0001-20 | Z14: =VLOOKUP(Y14,FORNECEDORES!$A$2:$G$9043,3,0) -> ANDRE L.A. ENDRES - ME | AA14: =VLOOKUP(Y14,FORNECEDORES!$A$2:$G$9041,7,0) -> endrestransportes@outlook.com
A15: CON:3475 | B15: 4417812013265605 | C15: 45838 | D15: 45839 | E15: ADT | F15: 1693.02 | G15: EFETIVADA | H15: VANDERLI DASSOLER | I15: 58751050030 | J15: MKS4A50 | K15: 101072217 | L15: SP | M15: 144516 | N15: 263407 | O15: 3475 | P15: RS | Q15: RS | R15: Finalizado | S15: Finalizada | T15: EFETIVADA | U15: Quinta feira | V15: Quinta feira | W15: =LEN(I15) -> 11 | X15: =IF(W15=14,"CNPJ",IF(W15=12,"CNPJ_INCOMPLETO_2",IF(W15=13,"CNPJ_INCOMPLETO_1",IF(W15=10,"CPF_Incompleto","CPF")))) -> CPF | Y15: =IF(X15="CNPJ_INCOMPLETO_1",("0"&LEFT(I15,1)&"."&MID(I15,2,3)&"."&MID(I15,5,3)&"/"&MID(I15,8,4)&"-"&MID(I15,12,2)),IF(X15="CNPJ_INCOMPLETO_2",("00."&LEFT(I15,3)&"."&MID(I15,4,3)&"/"&MID(I15,7,4)&"-"&MID(I15,11,2)),IF(X15="CNPJ",(LEFT(I15,2)&"."&MID(I15,3,3)&"."&MID(I15,6,3)&"/"&MID(I15,9,4)&"-"&MID(I15,13,2)),IF(X15="CPF_Incompleto",("0"&LEFT(I15,2)&"."&MID(I15,3,3)&"."&MID(I15,6,3)&"-"&MID(I15,9,2)),(LEFT(I15,3)&"."&MID(I15,4,3)&"."&MID(I15,7,3)&"-"&MID(I15,10,2)))))) -> 587.510.500-30 | Z15: =VLOOKUP(Y15,FORNECEDORES!$A$2:$G$9043,3,0) -> VANDERLI DASSOLER | AA15: =VLOOKUP(Y15,FORNECEDORES!$A$2:$G$9041,7,0) -> vanderliegv@gmail.com;
A16: CON:3475 | B16: 4417812013265605 | C16: 45838 | D16: 45841 | E16: SDO | F16: 1128.68 | G16: EFETIVADA | H16: VANDERLI DASSOLER | I16: 58751050030 | J16: MKS4A50 | K16: 101072217 | L16: SP | M16: 144516 | N16: 263407 | O16: 3475 | P16: RS | Q16: RS | R16: Finalizado | S16: Finalizada | T16: EFETIVADA | U16: Quinta feira | V16: Quinta feira | W16: =LEN(I16) -> 11 | X16: =IF(W16=14,"CNPJ",IF(W16=12,"CNPJ_INCOMPLETO_2",IF(W16=13,"CNPJ_INCOMPLETO_1",IF(W16=10,"CPF_Incompleto","CPF")))) -> CPF | Y16: =IF(X16="CNPJ_INCOMPLETO_1",("0"&LEFT(I16,1)&"."&MID(I16,2,3)&"."&MID(I16,5,3)&"/"&MID(I16,8,4)&"-"&MID(I16,12,2)),IF(X16="CNPJ_INCOMPLETO_2",("00."&LEFT(I16,3)&"."&MID(I16,4,3)&"/"&MID(I16,7,4)&"-"&MID(I16,11,2)),IF(X16="CNPJ",(LEFT(I16,2)&"."&MID(I16,3,3)&"."&MID(I16,6,3)&"/"&MID(I16,9,4)&"-"&MID(I16,13,2)),IF(X16="CPF_Incompleto",("0"&LEFT(I16,2)&"."&MID(I16,3,3)&"."&MID(I16,6,3)&"-"&MID(I16,9,2)),(LEFT(I16,3)&"."&MID(I16,4,3)&"."&MID(I16,7,3)&"-"&MID(I16,10,2)))))) -> 587.510.500-30 | Z16: =VLOOKUP(Y16,FORNECEDORES!$A$2:$G$9043,3,0) -> VANDERLI DASSOLER | AA16: =VLOOKUP(Y16,FORNECEDORES!$A$2:$G$9041,7,0) -> vanderliegv@gmail.com;
A17: CON:3476 | B17: 4417812010875943 | C17: 45838 | D17: 45868 | E17: DES | F17: 1800 | G17: EFETIVADA | H17: ANDRE L.A. ENDRES - ME | I17: 92309194000120 | J17: AFK2804 | K17: 101072261 | L17: SP | M17: 144517 | N17: 263408 | O17: 3476 | P17: RS | Q17: RS | R17: Finalizado | S17: Finalizada | T17: EFETIVADA | U17: 30 | V17: 45868 | W17: =LEN(I17) -> 14 | X17: =IF(W17=14,"CNPJ",IF(W17=12,"CNPJ_INCOMPLETO_2",IF(W17=13,"CNPJ_INCOMPLETO_1",IF(W17=10,"CPF_Incompleto","CPF")))) -> CNPJ | Y17: =IF(X17="CNPJ_INCOMPLETO_1",("0"&LEFT(I17,1)&"."&MID(I17,2,3)&"."&MID(I17,5,3)&"/"&MID(I17,8,4)&"-"&MID(I17,12,2)),IF(X17="CNPJ_INCOMPLETO_2",("00."&LEFT(I17,3)&"."&MID(I17,4,3)&"/"&MID(I17,7,4)&"-"&MID(I17,11,2)),IF(X17="CNPJ",(LEFT(I17,2)&"."&MID(I17,3,3)&"."&MID(I17,6,3)&"/"&MID(I17,9,4)&"-"&MID(I17,13,2)),IF(X17="CPF_Incompleto",("0"&LEFT(I17,2)&"."&MID(I17,3,3)&"."&MID(I17,6,3)&"-"&MID(I17,9,2)),(LEFT(I17,3)&"."&MID(I17,4,3)&"."&MID(I17,7,3)&"-"&MID(I17,10,2)))))) -> 92.309.194/0001-20 | Z17: =VLOOKUP(Y17,FORNECEDORES!$A$2:$G$9043,3,0) -> ANDRE L.A. ENDRES - ME | AA17: =VLOOKUP(Y17,FORNECEDORES!$A$2:$G$9041,7,0) -> endrestransportes@outlook.com
A18: CON:3477 | B18: 4417812014686304 | C18: 45838 | D18: 45839 | E18: ADT | F18: 1740 | G18: EFETIVADA | H18: SILVERIO DA SILVEIRA | I18: 17250059000130 | J18: ATL5J69 | K18: 101080661 | L18: SP | M18: 144520 | N18: 263428 | O18: 3477 | P18: RS | Q18: RS | R18: Finalizado | S18: Finalizada | T18: EFETIVADA | U18: Quinta feira | V18: Quinta feira | W18: =LEN(I18) -> 14 | X18: =IF(W18=14,"CNPJ",IF(W18=12,"CNPJ_INCOMPLETO_2",IF(W18=13,"CNPJ_INCOMPLETO_1",IF(W18=10,"CPF_Incompleto","CPF")))) -> CNPJ | Y18: =IF(X18="CNPJ_INCOMPLETO_1",("0"&LEFT(I18,1)&"."&MID(I18,2,3)&"."&MID(I18,5,3)&"/"&MID(I18,8,4)&"-"&MID(I18,12,2)),IF(X18="CNPJ_INCOMPLETO_2",("00."&LEFT(I18,3)&"."&MID(I18,4,3)&"/"&MID(I18,7,4)&"-"&MID(I18,11,2)),IF(X18="CNPJ",(LEFT(I18,2)&"."&MID(I18,3,3)&"."&MID(I18,6,3)&"/"&MID(I18,9,4)&"-"&MID(I18,13,2)),IF(X18="CPF_Incompleto",("0"&LEFT(I18,2)&"."&MID(I18,3,3)&"."&MID(I18,6,3)&"-"&MID(I18,9,2)),(LEFT(I18,3)&"."&MID(I18,4,3)&"."&MID(I18,7,3)&"-"&MID(I18,10,2)))))) -> 17.250.059/0001-30 | Z18: =VLOOKUP(Y18,FORNECEDORES!$A$2:$G$9043,3,0) -> SILVERIO DA SILVEIRA ME | AA18: =VLOOKUP(Y18,FORNECEDORES!$A$2:$G$9041,7,0) -> silveriosilveira86@hotmail.com;
A19: CON:3477 | B19: 4417812014686304 | C19: 45838 | D19: 45841 | E19: SDO | F19: 1160 | G19: EFETIVADA | H19: SILVERIO DA SILVEIRA | I19: 17250059000130 | J19: ATL5J69 | K19: 101080661 | L19: SP | M19: 144520 | N19: 263428 | O19: 3477 | P19: RS | Q19: RS | R19: Finalizado | S19: Finalizada | T19: EFETIVADA | U19: Quinta feira | V19: Quinta feira | W19: =LEN(I19) -> 14 | X19: =IF(W19=14,"CNPJ",IF(W19=12,"CNPJ_INCOMPLETO_2",IF(W19=13,"CNPJ_INCOMPLETO_1",IF(W19=10,"CPF_Incompleto","CPF")))) -> CNPJ | Y19: =IF(X19="CNPJ_INCOMPLETO_1",("0"&LEFT(I19,1)&"."&MID(I19,2,3)&"."&MID(I19,5,3)&"/"&MID(I19,8,4)&"-"&MID(I19,12,2)),IF(X19="CNPJ_INCOMPLETO_2",("00."&LEFT(I19,3)&"."&MID(I19,4,3)&"/"&MID(I19,7,4)&"-"&MID(I19,11,2)),IF(X19="CNPJ",(LEFT(I19,2)&"."&MID(I19,3,3)&"."&MID(I19,6,3)&"/"&MID(I19,9,4)&"-"&MID(I19,13,2)),IF(X19="CPF_Incompleto",("0"&LEFT(I19,2)&"."&MID(I19,3,3)&"."&MID(I19,6,3)&"-"&MID(I19,9,2)),(LEFT(I19,3)&"."&MID(I19,4,3)&"."&MID(I19,7,3)&"-"&MID(I19,10,2)))))) -> 17.250.059/0001-30 | Z19: =VLOOKUP(Y19,FORNECEDORES!$A$2:$G$9043,3,0) -> SILVERIO DA SILVEIRA ME | AA19: =VLOOKUP(Y19,FORNECEDORES!$A$2:$G$9041,7,0) -> silveriosilveira86@hotmail.com;
A20: CON:3478 | B20: 4417812022858440 | C20: 45838 | D20: 45839 | E20: ADT | F20: 1576.26 | G20: EFETIVADA | H20: JOSE DAGOBERTO MACHADO | I20: 40573680000 | J20: IKV8F25 | K20: 101081771 | L20: SP | M20: 144523 | N20: 263434 | O20: 3478 | P20: RS | Q20: RS | R20: Finalizado | S20: Finalizada | T20: EFETIVADA | U20: Quinta feira | V20: Quinta feira | W20: =LEN(I20) -> 11 | X20: =IF(W20=14,"CNPJ",IF(W20=12,"CNPJ_INCOMPLETO_2",IF(W20=13,"CNPJ_INCOMPLETO_1",IF(W20=10,"CPF_Incompleto","CPF")))) -> CPF | Y20: =IF(X20="CNPJ_INCOMPLETO_1",("0"&LEFT(I20,1)&"."&MID(I20,2,3)&"."&MID(I20,5,3)&"/"&MID(I20,8,4)&"-"&MID(I20,12,2)),IF(X20="CNPJ_INCOMPLETO_2",("00."&LEFT(I20,3)&"."&MID(I20,4,3)&"/"&MID(I20,7,4)&"-"&MID(I20,11,2)),IF(X20="CNPJ",(LEFT(I20,2)&"."&MID(I20,3,3)&"."&MID(I20,6,3)&"/"&MID(I20,9,4)&"-"&MID(I20,13,2)),IF(X20="CPF_Incompleto",("0"&LEFT(I20,2)&"."&MID(I20,3,3)&"."&MID(I20,6,3)&"-"&MID(I20,9,2)),(LEFT(I20,3)&"."&MID(I20,4,3)&"."&MID(I20,7,3)&"-"&MID(I20,10,2)))))) -> 405.736.800-00 | Z20: =VLOOKUP(Y20,FORNECEDORES!$A$2:$G$9043,3,0) -> JOSÉ DAGOBERTO MACHADO | AA20: =VLOOKUP(Y20,FORNECEDORES!$A$2:$G$9041,7,0) -> jdmdago@gmail.com;
A21: CON:3478 | B21: 4417812022858440 | C21: 45838 | D21: 45841 | E21: SDO | F21: 1050.84 | G21: EFETIVADA | H21: JOSE DAGOBERTO MACHADO | I21: 40573680000 | J21: IKV8F25 | K21: 101081771 | L21: SP | M21: 144523 | N21: 263434 | O21: 3478 | P21: RS | Q21: RS | R21: Finalizado | S21: Finalizada | T21: EFETIVADA | U21: Quinta feira | V21: Quinta feira | W21: =LEN(I21) -> 11 | X21: =IF(W21=14,"CNPJ",IF(W21=12,"CNPJ_INCOMPLETO_2",IF(W21=13,"CNPJ_INCOMPLETO_1",IF(W21=10,"CPF_Incompleto","CPF")))) -> CPF | Y21: =IF(X21="CNPJ_INCOMPLETO_1",("0"&LEFT(I21,1)&"."&MID(I21,2,3)&"."&MID(I21,5,3)&"/"&MID(I21,8,4)&"-"&MID(I21,12,2)),IF(X21="CNPJ_INCOMPLETO_2",("00."&LEFT(I21,3)&"."&MID(I21,4,3)&"/"&MID(I21,7,4)&"-"&MID(I21,11,2)),IF(X21="CNPJ",(LEFT(I21,2)&"."&MID(I21,3,3)&"."&MID(I21,6,3)&"/"&MID(I21,9,4)&"-"&MID(I21,13,2)),IF(X21="CPF_Incompleto",("0"&LEFT(I21,2)&"."&MID(I21,3,3)&"."&MID(I21,6,3)&"-"&MID(I21,9,2)),(LEFT(I21,3)&"."&MID(I21,4,3)&"."&MID(I21,7,3)&"-"&MID(I21,10,2)))))) -> 405.736.800-00 | Z21: =VLOOKUP(Y21,FORNECEDORES!$A$2:$G$9043,3,0) -> JOSÉ DAGOBERTO MACHADO | AA21: =VLOOKUP(Y21,FORNECEDORES!$A$2:$G$9041,7,0) -> jdmdago@gmail.com;
A22: CON:3479 | B22: 4417812010875943 | C22: 45839 | D22: 45869 | E22: DES | F22: 540 | G22: EFETIVADA | H22: ANDRE L.A. ENDRES - ME | I22: 92309194000120 | J22: AFK2804 | K22: 101098131 | L22: SP | M22: 144544 | N22: 263466 | O22: 3479 | P22: RS | Q22: RS | R22: Finalizado | S22: Finalizada | T22: EFETIVADA | U22: 30 | V22: 45868 | W22: =LEN(I22) -> 14 | X22: =IF(W22=14,"CNPJ",IF(W22=12,"CNPJ_INCOMPLETO_2",IF(W22=13,"CNPJ_INCOMPLETO_1",IF(W22=10,"CPF_Incompleto","CPF")))) -> CNPJ | Y22: =IF(X22="CNPJ_INCOMPLETO_1",("0"&LEFT(I22,1)&"."&MID(I22,2,3)&"."&MID(I22,5,3)&"/"&MID(I22,8,4)&"-"&MID(I22,12,2)),IF(X22="CNPJ_INCOMPLETO_2",("00."&LEFT(I22,3)&"."&MID(I22,4,3)&"/"&MID(I22,7,4)&"-"&MID(I22,11,2)),IF(X22="CNPJ",(LEFT(I22,2)&"."&MID(I22,3,3)&"."&MID(I22,6,3)&"/"&MID(I22,9,4)&"-"&MID(I22,13,2)),IF(X22="CPF_Incompleto",("0"&LEFT(I22,2)&"."&MID(I22,3,3)&"."&MID(I22,6,3)&"-"&MID(I22,9,2)),(LEFT(I22,3)&"."&MID(I22,4,3)&"."&MID(I22,7,3)&"-"&MID(I22,10,2)))))) -> 92.309.194/0001-20 | Z22: =VLOOKUP(Y22,FORNECEDORES!$A$2:$G$9043,3,0) -> ANDRE L.A. ENDRES - ME | AA22: =VLOOKUP(Y22,FORNECEDORES!$A$2:$G$9041,7,0) -> endrestransportes@outlook.com
A23: CON:3481 | B23: 4417812015511030 | C23: 45839 | D23: 45839 | E23: ADT | F23: 992.46 | G23: EFETIVADA | H23: Denis Camillo Da Silva | I23: 96685697091 | J23: IQM9933 | K23: 101106138 | L23: SP | M23: 144558 | N23: 263557 | O23: 3481, 3482, 3483 | P23: RS | Q23: RS | R23: Finalizado | S23: Finalizada | T23: EFETIVADA | U23: Quinta feira | V23: Quinta feira | W23: =LEN(I23) -> 11 | X23: =IF(W23=14,"CNPJ",IF(W23=12,"CNPJ_INCOMPLETO_2",IF(W23=13,"CNPJ_INCOMPLETO_1",IF(W23=10,"CPF_Incompleto","CPF")))) -> CPF | Y23: =IF(X23="CNPJ_INCOMPLETO_1",("0"&LEFT(I23,1)&"."&MID(I23,2,3)&"."&MID(I23,5,3)&"/"&MID(I23,8,4)&"-"&MID(I23,12,2)),IF(X23="CNPJ_INCOMPLETO_2",("00."&LEFT(I23,3)&"."&MID(I23,4,3)&"/"&MID(I23,7,4)&"-"&MID(I23,11,2)),IF(X23="CNPJ",(LEFT(I23,2)&"."&MID(I23,3,3)&"."&MID(I23,6,3)&"/"&MID(I23,9,4)&"-"&MID(I23,13,2)),IF(X23="CPF_Incompleto",("0"&LEFT(I23,2)&"."&MID(I23,3,3)&"."&MID(I23,6,3)&"-"&MID(I23,9,2)),(LEFT(I23,3)&"."&MID(I23,4,3)&"."&MID(I23,7,3)&"-"&MID(I23,10,2)))))) -> 966.856.970-91 | Z23: =VLOOKUP(Y23,FORNECEDORES!$A$2:$G$9043,3,0) -> DENIS CAMILLO DA SILVA | AA23: =VLOOKUP(Y23,FORNECEDORES!$A$2:$G$9041,7,0) -> deniscamillo29@gmail.com;
A24: CON:3481 | B24: 4417812015511030 | C24: 45839 | D24: 45841 | E24: SDO | F24: 661.64 | G24: EFETIVADA | H24: Denis Camillo Da Silva | I24: 96685697091 | J24: IQM9933 | K24: 101106138 | L24: SP | M24: 144558 | N24: 263557 | O24: 3481, 3482, 3483 | P24: RS | Q24: RS | R24: Finalizado | S24: Finalizada | T24: EFETIVADA | U24: Quinta feira | V24: Quinta feira | W24: =LEN(I24) -> 11 | X24: =IF(W24=14,"CNPJ",IF(W24=12,"CNPJ_INCOMPLETO_2",IF(W24=13,"CNPJ_INCOMPLETO_1",IF(W24=10,"CPF_Incompleto","CPF")))) -> CPF | Y24: =IF(X24="CNPJ_INCOMPLETO_1",("0"&LEFT(I24,1)&"."&MID(I24,2,3)&"."&MID(I24,5,3)&"/"&MID(I24,8,4)&"-"&MID(I24,12,2)),IF(X24="CNPJ_INCOMPLETO_2",("00."&LEFT(I24,3)&"."&MID(I24,4,3)&"/"&MID(I24,7,4)&"-"&MID(I24,11,2)),IF(X24="CNPJ",(LEFT(I24,2)&"."&MID(I24,3,3)&"."&MID(I24,6,3)&"/"&MID(I24,9,4)&"-"&MID(I24,13,2)),IF(X24="CPF_Incompleto",("0"&LEFT(I24,2)&"."&MID(I24,3,3)&"."&MID(I24,6,3)&"-"&MID(I24,9,2)),(LEFT(I24,3)&"."&MID(I24,4,3)&"."&MID(I24,7,3)&"-"&MID(I24,10,2)))))) -> 966.856.970-91 | Z24: =VLOOKUP(Y24,FORNECEDORES!$A$2:$G$9043,3,0) -> DENIS CAMILLO DA SILVA | AA24: =VLOOKUP(Y24,FORNECEDORES!$A$2:$G$9041,7,0) -> deniscamillo29@gmail.com;
A25: CON:3485 | B25: 4417812022858440 | C25: 45839 | D25: 45839 | E25: ADT | F25: 437.85 | G25: EFETIVADA | H25: JOSE DAGOBERTO MACHADO | I25: 40573680000 | J25: IKV8F25 | K25: 101116326 | L25: SP | M25: 144588 | N25: 263602 | O25: 3485 | P25: RS | Q25: RS | R25: Finalizado | S25: Finalizada | T25: EFETIVADA | U25: Quinta feira | V25: Quinta feira | W25: =LEN(I25) -> 11 | X25: =IF(W25=14,"CNPJ",IF(W25=12,"CNPJ_INCOMPLETO_2",IF(W25=13,"CNPJ_INCOMPLETO_1",IF(W25=10,"CPF_Incompleto","CPF")))) -> CPF | Y25: =IF(X25="CNPJ_INCOMPLETO_1",("0"&LEFT(I25,1)&"."&MID(I25,2,3)&"."&MID(I25,5,3)&"/"&MID(I25,8,4)&"-"&MID(I25,12,2)),IF(X25="CNPJ_INCOMPLETO_2",("00."&LEFT(I25,3)&"."&MID(I25,4,3)&"/"&MID(I25,7,4)&"-"&MID(I25,11,2)),IF(X25="CNPJ",(LEFT(I25,2)&"."&MID(I25,3,3)&"."&MID(I25,6,3)&"/"&MID(I25,9,4)&"-"&MID(I25,13,2)),IF(X25="CPF_Incompleto",("0"&LEFT(I25,2)&"."&MID(I25,3,3)&"."&MID(I25,6,3)&"-"&MID(I25,9,2)),(LEFT(I25,3)&"."&MID(I25,4,3)&"."&MID(I25,7,3)&"-"&MID(I25,10,2)))))) -> 405.736.800-00 | Z25: =VLOOKUP(Y25,FORNECEDORES!$A$2:$G$9043,3,0) -> JOSÉ DAGOBERTO MACHADO | AA25: =VLOOKUP(Y25,FORNECEDORES!$A$2:$G$9041,7,0) -> jdmdago@gmail.com;
A26: CON:3485 | B26: 4417812022858440 | C26: 45839 | D26: 45841 | E26: SDO | F26: 291.9 | G26: EFETIVADA | H26: JOSE DAGOBERTO MACHADO | I26: 40573680000 | J26: IKV8F25 | K26: 101116326 | L26: SP | M26: 144588 | N26: 263602 | O26: 3485 | P26: RS | Q26: RS | R26: Finalizado | S26: Finalizada | T26: EFETIVADA | U26: Quinta feira | V26: Quinta feira | W26: =LEN(I26) -> 11 | X26: =IF(W26=14,"CNPJ",IF(W26=12,"CNPJ_INCOMPLETO_2",IF(W26=13,"CNPJ_INCOMPLETO_1",IF(W26=10,"CPF_Incompleto","CPF")))) -> CPF | Y26: =IF(X26="CNPJ_INCOMPLETO_1",("0"&LEFT(I26,1)&"."&MID(I26,2,3)&"."&MID(I26,5,3)&"/"&MID(I26,8,4)&"-"&MID(I26,12,2)),IF(X26="CNPJ_INCOMPLETO_2",("00."&LEFT(I26,3)&"."&MID(I26,4,3)&"/"&MID(I26,7,4)&"-"&MID(I26,11,2)),IF(X26="CNPJ",(LEFT(I26,2)&"."&MID(I26,3,3)&"."&MID(I26,6,3)&"/"&MID(I26,9,4)&"-"&MID(I26,13,2)),IF(X26="CPF_Incompleto",("0"&LEFT(I26,2)&"."&MID(I26,3,3)&"."&MID(I26,6,3)&"-"&MID(I26,9,2)),(LEFT(I26,3)&"."&MID(I26,4,3)&"."&MID(I26,7,3)&"-"&MID(I26,10,2)))))) -> 405.736.800-00 | Z26: =VLOOKUP(Y26,FORNECEDORES!$A$2:$G$9043,3,0) -> JOSÉ DAGOBERTO MACHADO | AA26: =VLOOKUP(Y26,FORNECEDORES!$A$2:$G$9041,7,0) -> jdmdago@gmail.com;
A27: CON:3487 | B27: 4417812010875943 | C27: 45840 | D27: 45870 | E27: DES | F27: 1800 | G27: EFETIVADA | H27: ANDRE L.A. ENDRES - ME | I27: 92309194000120 | J27: AFK2804 | K27: 101141168 | L27: SP | M27: 144630 | N27: 263674 | O27: 3487 | P27: RS | Q27: RS | R27: Aprovado | S27: Em Transporte | T27: EFETIVADA | U27: 30 | V27: 45879 | W27: =LEN(I27) -> 14 | X27: =IF(W27=14,"CNPJ",IF(W27=12,"CNPJ_INCOMPLETO_2",IF(W27=13,"CNPJ_INCOMPLETO_1",IF(W27=10,"CPF_Incompleto","CPF")))) -> CNPJ | Y27: =IF(X27="CNPJ_INCOMPLETO_1",("0"&LEFT(I27,1)&"."&MID(I27,2,3)&"."&MID(I27,5,3)&"/"&MID(I27,8,4)&"-"&MID(I27,12,2)),IF(X27="CNPJ_INCOMPLETO_2",("00."&LEFT(I27,3)&"."&MID(I27,4,3)&"/"&MID(I27,7,4)&"-"&MID(I27,11,2)),IF(X27="CNPJ",(LEFT(I27,2)&"."&MID(I27,3,3)&"."&MID(I27,6,3)&"/"&MID(I27,9,4)&"-"&MID(I27,13,2)),IF(X27="CPF_Incompleto",("0"&LEFT(I27,2)&"."&MID(I27,3,3)&"."&MID(I27,6,3)&"-"&MID(I27,9,2)),(LEFT(I27,3)&"."&MID(I27,4,3)&"."&MID(I27,7,3)&"-"&MID(I27,10,2)))))) -> 92.309.194/0001-20 | Z27: =VLOOKUP(Y27,FORNECEDORES!$A$2:$G$9043,3,0) -> ANDRE L.A. ENDRES - ME | AA27: =VLOOKUP(Y27,FORNECEDORES!$A$2:$G$9041,7,0) -> endrestransportes@outlook.com
A28: CON:3489 | B28: 4417812013265605 | C28: 45840 | D28: 45841 | E28: ADT | F28: 1050.84 | G28: EFETIVADA | H28: VANDERLI DASSOLER | I28: 58751050030 | J28: MKS4A50 | K28: 101163718 | L28: SP | M28: 144665 | N28: 263744 | O28: 3489 | P28: RS | Q28: RS | R28: Finalizado | S28: Finalizada | T28: EFETIVADA | U28: Quinta feira | V28: Quinta feira | W28: =LEN(I28) -> 11 | X28: =IF(W28=14,"CNPJ",IF(W28=12,"CNPJ_INCOMPLETO_2",IF(W28=13,"CNPJ_INCOMPLETO_1",IF(W28=10,"CPF_Incompleto","CPF")))) -> CPF | Y28: =IF(X28="CNPJ_INCOMPLETO_1",("0"&LEFT(I28,1)&"."&MID(I28,2,3)&"."&MID(I28,5,3)&"/"&MID(I28,8,4)&"-"&MID(I28,12,2)),IF(X28="CNPJ_INCOMPLETO_2",("00."&LEFT(I28,3)&"."&MID(I28,4,3)&"/"&MID(I28,7,4)&"-"&MID(I28,11,2)),IF(X28="CNPJ",(LEFT(I28,2)&"."&MID(I28,3,3)&"."&MID(I28,6,3)&"/"&MID(I28,9,4)&"-"&MID(I28,13,2)),IF(X28="CPF_Incompleto",("0"&LEFT(I28,2)&"."&MID(I28,3,3)&"."&MID(I28,6,3)&"-"&MID(I28,9,2)),(LEFT(I28,3)&"."&MID(I28,4,3)&"."&MID(I28,7,3)&"-"&MID(I28,10,2)))))) -> 587.510.500-30 | Z28: =VLOOKUP(Y28,FORNECEDORES!$A$2:$G$9043,3,0) -> VANDERLI DASSOLER | AA28: =VLOOKUP(Y28,FORNECEDORES!$A$2:$G$9041,7,0) -> vanderliegv@gmail.com;
A29: CON:3489 | B29: 4417812013265605 | C29: 45840 | D29: 45841 | E29: SDO | F29: 700.56 | G29: EFETIVADA | H29: VANDERLI DASSOLER | I29: 58751050030 | J29: MKS4A50 | K29: 101163718 | L29: SP | M29: 144665 | N29: 263744 | O29: 3489 | P29: RS | Q29: RS | R29: Finalizado | S29: Finalizada | T29: EFETIVADA | U29: Quinta feira | V29: Quinta feira | W29: =LEN(I29) -> 11 | X29: =IF(W29=14,"CNPJ",IF(W29=12,"CNPJ_INCOMPLETO_2",IF(W29=13,"CNPJ_INCOMPLETO_1",IF(W29=10,"CPF_Incompleto","CPF")))) -> CPF | Y29: =IF(X29="CNPJ_INCOMPLETO_1",("0"&LEFT(I29,1)&"."&MID(I29,2,3)&"."&MID(I29,5,3)&"/"&MID(I29,8,4)&"-"&MID(I29,12,2)),IF(X29="CNPJ_INCOMPLETO_2",("00."&LEFT(I29,3)&"."&MID(I29,4,3)&"/"&MID(I29,7,4)&"-"&MID(I29,11,2)),IF(X29="CNPJ",(LEFT(I29,2)&"."&MID(I29,3,3)&"."&MID(I29,6,3)&"/"&MID(I29,9,4)&"-"&MID(I29,13,2)),IF(X29="CPF_Incompleto",("0"&LEFT(I29,2)&"."&MID(I29,3,3)&"."&MID(I29,6,3)&"-"&MID(I29,9,2)),(LEFT(I29,3)&"."&MID(I29,4,3)&"."&MID(I29,7,3)&"-"&MID(I29,10,2)))))) -> 587.510.500-30 | Z29: =VLOOKUP(Y29,FORNECEDORES!$A$2:$G$9043,3,0) -> VANDERLI DASSOLER | AA29: =VLOOKUP(Y29,FORNECEDORES!$A$2:$G$9041,7,0) -> vanderliegv@gmail.com;
A30: CON:3490 | B30: 4417812022858440 | C30: 45841 | D30: 45841 | E30: ADT | F30: 1576.26 | G30: EFETIVADA | H30: JOSE DAGOBERTO MACHADO | I30: 40573680000 | J30: IKV8F25 | K30: 101180167 | L30: SP | M30: 144691 | N30: 263792 | O30: 3490 | P30: RS | Q30: RS | R30: Finalizado | S30: Finalizada | T30: EFETIVADA | U30: Quinta feira | V30: Quinta feira | W30: =LEN(I30) -> 11 | X30: =IF(W30=14,"CNPJ",IF(W30=12,"CNPJ_INCOMPLETO_2",IF(W30=13,"CNPJ_INCOMPLETO_1",IF(W30=10,"CPF_Incompleto","CPF")))) -> CPF | Y30: =IF(X30="CNPJ_INCOMPLETO_1",("0"&LEFT(I30,1)&"."&MID(I30,2,3)&"."&MID(I30,5,3)&"/"&MID(I30,8,4)&"-"&MID(I30,12,2)),IF(X30="CNPJ_INCOMPLETO_2",("00."&LEFT(I30,3)&"."&MID(I30,4,3)&"/"&MID(I30,7,4)&"-"&MID(I30,11,2)),IF(X30="CNPJ",(LEFT(I30,2)&"."&MID(I30,3,3)&"."&MID(I30,6,3)&"/"&MID(I30,9,4)&"-"&MID(I30,13,2)),IF(X30="CPF_Incompleto",("0"&LEFT(I30,2)&"."&MID(I30,3,3)&"."&MID(I30,6,3)&"-"&MID(I30,9,2)),(LEFT(I30,3)&"."&MID(I30,4,3)&"."&MID(I30,7,3)&"-"&MID(I30,10,2)))))) -> 405.736.800-00 | Z30: =VLOOKUP(Y30,FORNECEDORES!$A$2:$G$9043,3,0) -> JOSÉ DAGOBERTO MACHADO | AA30: =VLOOKUP(Y30,FORNECEDORES!$A$2:$G$9041,7,0) -> jdmdago@gmail.com;
A31: CON:3490 | B31: 4417812022858440 | C31: 45841 | D31: 45841 | E31: SDO | F31: 1050.84 | G31: EFETIVADA | H31: JOSE DAGOBERTO MACHADO | I31: 40573680000 | J31: IKV8F25 | K31: 101180167 | L31: SP | M31: 144691 | N31: 263792 | O31: 3490 | P31: RS | Q31: RS | R31: Finalizado | S31: Finalizada | T31: EFETIVADA | U31: Quinta feira | V31: Quinta feira | W31: =LEN(I31) -> 11 | X31: =IF(W31=14,"CNPJ",IF(W31=12,"CNPJ_INCOMPLETO_2",IF(W31=13,"CNPJ_INCOMPLETO_1",IF(W31=10,"CPF_Incompleto","CPF")))) -> CPF | Y31: =IF(X31="CNPJ_INCOMPLETO_1",("0"&LEFT(I31,1)&"."&MID(I31,2,3)&"."&MID(I31,5,3)&"/"&MID(I31,8,4)&"-"&MID(I31,12,2)),IF(X31="CNPJ_INCOMPLETO_2",("00."&LEFT(I31,3)&"."&MID(I31,4,3)&"/"&MID(I31,7,4)&"-"&MID(I31,11,2)),IF(X31="CNPJ",(LEFT(I31,2)&"."&MID(I31,3,3)&"."&MID(I31,6,3)&"/"&MID(I31,9,4)&"-"&MID(I31,13,2)),IF(X31="CPF_Incompleto",("0"&LEFT(I31,2)&"."&MID(I31,3,3)&"."&MID(I31,6,3)&"-"&MID(I31,9,2)),(LEFT(I31,3)&"."&MID(I31,4,3)&"."&MID(I31,7,3)&"-"&MID(I31,10,2)))))) -> 405.736.800-00 | Z31: =VLOOKUP(Y31,FORNECEDORES!$A$2:$G$9043,3,0) -> JOSÉ DAGOBERTO MACHADO | AA31: =VLOOKUP(Y31,FORNECEDORES!$A$2:$G$9041,7,0) -> jdmdago@gmail.com;
A32: CON:1680 | B32: 4417812010875943 | C32: 45841 | D32: 45870 | E32: DES | F32: 660 | G32: EFETIVADA | H32: ANDRE L.A. ENDRES - ME | I32: 92309194000120 | J32: AFK2804 | K32: 101184547 | L32: SP | M32: 144699 | N32: 263820 | O32: 1680 | P32: RS | Q32: RS | R32: Finalizado | S32: Finalizada | T32: EFETIVADA | U32: 30 | V32: 45879 | W32: =LEN(I32) -> 14 | X32: =IF(W32=14,"CNPJ",IF(W32=12,"CNPJ_INCOMPLETO_2",IF(W32=13,"CNPJ_INCOMPLETO_1",IF(W32=10,"CPF_Incompleto","CPF")))) -> CNPJ | Y32: =IF(X32="CNPJ_INCOMPLETO_1",("0"&LEFT(I32,1)&"."&MID(I32,2,3)&"."&MID(I32,5,3)&"/"&MID(I32,8,4)&"-"&MID(I32,12,2)),IF(X32="CNPJ_INCOMPLETO_2",("00."&LEFT(I32,3)&"."&MID(I32,4,3)&"/"&MID(I32,7,4)&"-"&MID(I32,11,2)),IF(X32="CNPJ",(LEFT(I32,2)&"."&MID(I32,3,3)&"."&MID(I32,6,3)&"/"&MID(I32,9,4)&"-"&MID(I32,13,2)),IF(X32="CPF_Incompleto",("0"&LEFT(I32,2)&"."&MID(I32,3,3)&"."&MID(I32,6,3)&"-"&MID(I32,9,2)),(LEFT(I32,3)&"."&MID(I32,4,3)&"."&MID(I32,7,3)&"-"&MID(I32,10,2)))))) -> 92.309.194/0001-20 | Z32: =VLOOKUP(Y32,FORNECEDORES!$A$2:$G$9043,3,0) -> ANDRE L.A. ENDRES - ME | AA32: =VLOOKUP(Y32,FORNECEDORES!$A$2:$G$9041,7,0) -> endrestransportes@outlook.com
A33: CON:3494 | B33: 4417812010875943 | C33: 45841 | D33: 45870 | E33: DES | F33: 1800 | G33: EFETIVADA | H33: ANDRE L.A. ENDRES - ME | I33: 92309194000120 | J33: AFK2804 | K33: 101197051 | L33: SP | M33: 144717 | N33: 263893 | O33: 3494 | P33: RS | Q33: RS | R33: Finalizado | S33: Finalizada | T33: EFETIVADA | U33: 30 | V33: 45879 | W33: =LEN(I33) -> 14 | X33: =IF(W33=14,"CNPJ",IF(W33=12,"CNPJ_INCOMPLETO_2",IF(W33=13,"CNPJ_INCOMPLETO_1",IF(W33=10,"CPF_Incompleto","CPF")))) -> CNPJ | Y33: =IF(X33="CNPJ_INCOMPLETO_1",("0"&LEFT(I33,1)&"."&MID(I33,2,3)&"."&MID(I33,5,3)&"/"&MID(I33,8,4)&"-"&MID(I33,12,2)),IF(X33="CNPJ_INCOMPLETO_2",("00."&LEFT(I33,3)&"."&MID(I33,4,3)&"/"&MID(I33,7,4)&"-"&MID(I33,11,2)),IF(X33="CNPJ",(LEFT(I33,2)&"."&MID(I33,3,3)&"."&MID(I33,6,3)&"/"&MID(I33,9,4)&"-"&MID(I33,13,2)),IF(X33="CPF_Incompleto",("0"&LEFT(I33,2)&"."&MID(I33,3,3)&"."&MID(I33,6,3)&"-"&MID(I33,9,2)),(LEFT(I33,3)&"."&MID(I33,4,3)&"."&MID(I33,7,3)&"-"&MID(I33,10,2)))))) -> 92.309.194/0001-20 | Z33: =VLOOKUP(Y33,FORNECEDORES!$A$2:$G$9043,3,0) -> ANDRE L.A. ENDRES - ME | AA33: =VLOOKUP(Y33,FORNECEDORES!$A$2:$G$9041,7,0) -> endrestransportes@outlook.com
A34: CON:3495 | B34: 4417812014686304 | C34: 45841 | D34: 45842 | E34: ADT | F34: 342 | G34: EFETIVADA | H34: SILVERIO DA SILVEIRA | I34: 17250059000130 | J34: ATL5J69 | K34: 101200614 | L34: SP | M34: 144722 | N34: 263902 | O34: 3495 | P34: RS | Q34: RS | R34: Finalizado | S34: Finalizada | T34: EFETIVADA | U34: Quinta feira | V34: Quinta feira | W34: =LEN(I34) -> 14 | X34: =IF(W34=14,"CNPJ",IF(W34=12,"CNPJ_INCOMPLETO_2",IF(W34=13,"CNPJ_INCOMPLETO_1",IF(W34=10,"CPF_Incompleto","CPF")))) -> CNPJ | Y34: =IF(X34="CNPJ_INCOMPLETO_1",("0"&LEFT(I34,1)&"."&MID(I34,2,3)&"."&MID(I34,5,3)&"/"&MID(I34,8,4)&"-"&MID(I34,12,2)),IF(X34="CNPJ_INCOMPLETO_2",("00."&LEFT(I34,3)&"."&MID(I34,4,3)&"/"&MID(I34,7,4)&"-"&MID(I34,11,2)),IF(X34="CNPJ",(LEFT(I34,2)&"."&MID(I34,3,3)&"."&MID(I34,6,3)&"/"&MID(I34,9,4)&"-"&MID(I34,13,2)),IF(X34="CPF_Incompleto",("0"&LEFT(I34,2)&"."&MID(I34,3,3)&"."&MID(I34,6,3)&"-"&MID(I34,9,2)),(LEFT(I34,3)&"."&MID(I34,4,3)&"."&MID(I34,7,3)&"-"&MID(I34,10,2)))))) -> 17.250.059/0001-30 | Z34: =VLOOKUP(Y34,FORNECEDORES!$A$2:$G$9043,3,0) -> SILVERIO DA SILVEIRA ME | AA34: =VLOOKUP(Y34,FORNECEDORES!$A$2:$G$9041,7,0) -> silveriosilveira86@hotmail.com;
A35: CON:3495 | B35: 4417812014686304 | C35: 45841 | D35: 45848 | E35: SDO | F35: 228 | G35: EFETIVADA | H35: SILVERIO DA SILVEIRA | I35: 17250059000130 | J35: ATL5J69 | K35: 101200614 | L35: SP | M35: 144722 | N35: 263902 | O35: 3495 | P35: RS | Q35: RS | R35: Finalizado | S35: Finalizada | T35: EFETIVADA | U35: Quinta feira | V35: Quinta feira | W35: =LEN(I35) -> 14 | X35: =IF(W35=14,"CNPJ",IF(W35=12,"CNPJ_INCOMPLETO_2",IF(W35=13,"CNPJ_INCOMPLETO_1",IF(W35=10,"CPF_Incompleto","CPF")))) -> CNPJ | Y35: =IF(X35="CNPJ_INCOMPLETO_1",("0"&LEFT(I35,1)&"."&MID(I35,2,3)&"."&MID(I35,5,3)&"/"&MID(I35,8,4)&"-"&MID(I35,12,2)),IF(X35="CNPJ_INCOMPLETO_2",("00."&LEFT(I35,3)&"."&MID(I35,4,3)&"/"&MID(I35,7,4)&"-"&MID(I35,11,2)),IF(X35="CNPJ",(LEFT(I35,2)&"."&MID(I35,3,3)&"."&MID(I35,6,3)&"/"&MID(I35,9,4)&"-"&MID(I35,13,2)),IF(X35="CPF_Incompleto",("0"&LEFT(I35,2)&"."&MID(I35,3,3)&"."&MID(I35,6,3)&"-"&MID(I35,9,2)),(LEFT(I35,3)&"."&MID(I35,4,3)&"."&MID(I35,7,3)&"-"&MID(I35,10,2)))))) -> 17.250.059/0001-30 | Z35: =VLOOKUP(Y35,FORNECEDORES!$A$2:$G$9043,3,0) -> SILVERIO DA SILVEIRA ME | AA35: =VLOOKUP(Y35,FORNECEDORES!$A$2:$G$9041,7,0) -> silveriosilveira86@hotmail.com;
A36: CON:3496 | B36: 4417812015511030 | C36: 45841 | D36: 45842 | E36: ADT | F36: 1109.22 | G36: EFETIVADA | H36: Denis Camillo Da Silva | I36: 96685697091 | J36: IQM9933 | K36: 101206509 | L36: SP | M36: 144727 | N36: 263925 | O36: 3496 | P36: RS | Q36: RS | R36: Finalizado | S36: Finalizada | T36: EFETIVADA | U36: Quinta feira | V36: Quinta feira | W36: =LEN(I36) -> 11 | X36: =IF(W36=14,"CNPJ",IF(W36=12,"CNPJ_INCOMPLETO_2",IF(W36=13,"CNPJ_INCOMPLETO_1",IF(W36=10,"CPF_Incompleto","CPF")))) -> CPF | Y36: =IF(X36="CNPJ_INCOMPLETO_1",("0"&LEFT(I36,1)&"."&MID(I36,2,3)&"."&MID(I36,5,3)&"/"&MID(I36,8,4)&"-"&MID(I36,12,2)),IF(X36="CNPJ_INCOMPLETO_2",("00."&LEFT(I36,3)&"."&MID(I36,4,3)&"/"&MID(I36,7,4)&"-"&MID(I36,11,2)),IF(X36="CNPJ",(LEFT(I36,2)&"."&MID(I36,3,3)&"."&MID(I36,6,3)&"/"&MID(I36,9,4)&"-"&MID(I36,13,2)),IF(X36="CPF_Incompleto",("0"&LEFT(I36,2)&"."&MID(I36,3,3)&"."&MID(I36,6,3)&"-"&MID(I36,9,2)),(LEFT(I36,3)&"."&MID(I36,4,3)&"."&MID(I36,7,3)&"-"&MID(I36,10,2)))))) -> 966.856.970-91 | Z36: =VLOOKUP(Y36,FORNECEDORES!$A$2:$G$9043,3,0) -> DENIS CAMILLO DA SILVA | AA36: =VLOOKUP(Y36,FORNECEDORES!$A$2:$G$9041,7,0) -> deniscamillo29@gmail.com;
A37: CON:3496 | B37: 4417812015511030 | C37: 45841 | D37: 45848 | E37: SDO | F37: 739.48 | G37: EFETIVADA | H37: Denis Camillo Da Silva | I37: 96685697091 | J37: IQM9933 | K37: 101206509 | L37: SP | M37: 144727 | N37: 263925 | O37: 3496 | P37: RS | Q37: RS | R37: Finalizado | S37: Finalizada | T37: EFETIVADA | U37: Quinta feira | V37: Quinta feira | W37: =LEN(I37) -> 11 | X37: =IF(W37=14,"CNPJ",IF(W37=12,"CNPJ_INCOMPLETO_2",IF(W37=13,"CNPJ_INCOMPLETO_1",IF(W37=10,"CPF_Incompleto","CPF")))) -> CPF | Y37: =IF(X37="CNPJ_INCOMPLETO_1",("0"&LEFT(I37,1)&"."&MID(I37,2,3)&"."&MID(I37,5,3)&"/"&MID(I37,8,4)&"-"&MID(I37,12,2)),IF(X37="CNPJ_INCOMPLETO_2",("00."&LEFT(I37,3)&"."&MID(I37,4,3)&"/"&MID(I37,7,4)&"-"&MID(I37,11,2)),IF(X37="CNPJ",(LEFT(I37,2)&"."&MID(I37,3,3)&"."&MID(I37,6,3)&"/"&MID(I37,9,4)&"-"&MID(I37,13,2)),IF(X37="CPF_Incompleto",("0"&LEFT(I37,2)&"."&MID(I37,3,3)&"."&MID(I37,6,3)&"-"&MID(I37,9,2)),(LEFT(I37,3)&"."&MID(I37,4,3)&"."&MID(I37,7,3)&"-"&MID(I37,10,2)))))) -> 966.856.970-91 | Z37: =VLOOKUP(Y37,FORNECEDORES!$A$2:$G$9043,3,0) -> DENIS CAMILLO DA SILVA | AA37: =VLOOKUP(Y37,FORNECEDORES!$A$2:$G$9041,7,0) -> deniscamillo29@gmail.com;
A38: CON:3497 | B38: 4417812013265605 | C38: 45841 | D38: 45842 | E38: ADT | F38: 1576.26 | G38: EFETIVADA | H38: VANDERLI DASSOLER | I38: 58751050030 | J38: MKS4A50 | K38: 101207475 | L38: SP | M38: 144730 | N38: 263933 | O38: 3497 | P38: RS | Q38: RS | R38: Finalizado | S38: Finalizada | T38: EFETIVADA | U38: Quinta feira | V38: Quinta feira | W38: =LEN(I38) -> 11 | X38: =IF(W38=14,"CNPJ",IF(W38=12,"CNPJ_INCOMPLETO_2",IF(W38=13,"CNPJ_INCOMPLETO_1",IF(W38=10,"CPF_Incompleto","CPF")))) -> CPF | Y38: =IF(X38="CNPJ_INCOMPLETO_1",("0"&LEFT(I38,1)&"."&MID(I38,2,3)&"."&MID(I38,5,3)&"/"&MID(I38,8,4)&"-"&MID(I38,12,2)),IF(X38="CNPJ_INCOMPLETO_2",("00."&LEFT(I38,3)&"."&MID(I38,4,3)&"/"&MID(I38,7,4)&"-"&MID(I38,11,2)),IF(X38="CNPJ",(LEFT(I38,2)&"."&MID(I38,3,3)&"."&MID(I38,6,3)&"/"&MID(I38,9,4)&"-"&MID(I38,13,2)),IF(X38="CPF_Incompleto",("0"&LEFT(I38,2)&"."&MID(I38,3,3)&"."&MID(I38,6,3)&"-"&MID(I38,9,2)),(LEFT(I38,3)&"."&MID(I38,4,3)&"."&MID(I38,7,3)&"-"&MID(I38,10,2)))))) -> 587.510.500-30 | Z38: =VLOOKUP(Y38,FORNECEDORES!$A$2:$G$9043,3,0) -> VANDERLI DASSOLER | AA38: =VLOOKUP(Y38,FORNECEDORES!$A$2:$G$9041,7,0) -> vanderliegv@gmail.com;
A39: CON:3497 | B39: 4417812013265605 | C39: 45841 | D39: 45848 | E39: SDO | F39: 1050.84 | G39: EFETIVADA | H39: VANDERLI DASSOLER | I39: 58751050030 | J39: MKS4A50 | K39: 101207475 | L39: SP | M39: 144730 | N39: 263933 | O39: 3497 | P39: RS | Q39: RS | R39: Finalizado | S39: Finalizada | T39: EFETIVADA | U39: Quinta feira | V39: Quinta feira | W39: =LEN(I39) -> 11 | X39: =IF(W39=14,"CNPJ",IF(W39=12,"CNPJ_INCOMPLETO_2",IF(W39=13,"CNPJ_INCOMPLETO_1",IF(W39=10,"CPF_Incompleto","CPF")))) -> CPF | Y39: =IF(X39="CNPJ_INCOMPLETO_1",("0"&LEFT(I39,1)&"."&MID(I39,2,3)&"."&MID(I39,5,3)&"/"&MID(I39,8,4)&"-"&MID(I39,12,2)),IF(X39="CNPJ_INCOMPLETO_2",("00."&LEFT(I39,3)&"."&MID(I39,4,3)&"/"&MID(I39,7,4)&"-"&MID(I39,11,2)),IF(X39="CNPJ",(LEFT(I39,2)&"."&MID(I39,3,3)&"."&MID(I39,6,3)&"/"&MID(I39,9,4)&"-"&MID(I39,13,2)),IF(X39="CPF_Incompleto",("0"&LEFT(I39,2)&"."&MID(I39,3,3)&"."&MID(I39,6,3)&"-"&MID(I39,9,2)),(LEFT(I39,3)&"."&MID(I39,4,3)&"."&MID(I39,7,3)&"-"&MID(I39,10,2)))))) -> 587.510.500-30 | Z39: =VLOOKUP(Y39,FORNECEDORES!$A$2:$G$9043,3,0) -> VANDERLI DASSOLER | AA39: =VLOOKUP(Y39,FORNECEDORES!$A$2:$G$9041,7,0) -> vanderliegv@gmail.com;
A40: CON:3499 | B40: 4417812014686304 | C40: 45842 | D40: 45842 | E40: ADT | F40: 1020 | G40: EFETIVADA | H40: SILVERIO DA SILVEIRA | I40: 17250059000130 | J40: ATL5J69 | K40: 101223195 | L40: SP | M40: 144760 | N40: 263972 | O40: 3499, 3500 | P40: RS | Q40: RS | R40: Finalizado | S40: Finalizada | T40: EFETIVADA | U40: Quinta feira | V40: Quinta feira | W40: =LEN(I40) -> 14 | X40: =IF(W40=14,"CNPJ",IF(W40=12,"CNPJ_INCOMPLETO_2",IF(W40=13,"CNPJ_INCOMPLETO_1",IF(W40=10,"CPF_Incompleto","CPF")))) -> CNPJ | Y40: =IF(X40="CNPJ_INCOMPLETO_1",("0"&LEFT(I40,1)&"."&MID(I40,2,3)&"."&MID(I40,5,3)&"/"&MID(I40,8,4)&"-"&MID(I40,12,2)),IF(X40="CNPJ_INCOMPLETO_2",("00."&LEFT(I40,3)&"."&MID(I40,4,3)&"/"&MID(I40,7,4)&"-"&MID(I40,11,2)),IF(X40="CNPJ",(LEFT(I40,2)&"."&MID(I40,3,3)&"."&MID(I40,6,3)&"/"&MID(I40,9,4)&"-"&MID(I40,13,2)),IF(X40="CPF_Incompleto",("0"&LEFT(I40,2)&"."&MID(I40,3,3)&"."&MID(I40,6,3)&"-"&MID(I40,9,2)),(LEFT(I40,3)&"."&MID(I40,4,3)&"."&MID(I40,7,3)&"-"&MID(I40,10,2)))))) -> 17.250.059/0001-30 | Z40: =VLOOKUP(Y40,FORNECEDORES!$A$2:$G$9043,3,0) -> SILVERIO DA SILVEIRA ME | AA40: =VLOOKUP(Y40,FORNECEDORES!$A$2:$G$9041,7,0) -> silveriosilveira86@hotmail.com;
A41: CON:3499 | B41: 4417812014686304 | C41: 45842 | D41: 45848 | E41: SDO | F41: 680 | G41: EFETIVADA | H41: SILVERIO DA SILVEIRA | I41: 17250059000130 | J41: ATL5J69 | K41: 101223195 | L41: SP | M41: 144760 | N41: 263972 | O41: 3499, 3500 | P41: RS | Q41: RS | R41: Finalizado | S41: Finalizada | T41: EFETIVADA | U41: Quinta feira | V41: Quinta feira | W41: =LEN(I41) -> 14 | X41: =IF(W41=14,"CNPJ",IF(W41=12,"CNPJ_INCOMPLETO_2",IF(W41=13,"CNPJ_INCOMPLETO_1",IF(W41=10,"CPF_Incompleto","CPF")))) -> CNPJ | Y41: =IF(X41="CNPJ_INCOMPLETO_1",("0"&LEFT(I41,1)&"."&MID(I41,2,3)&"."&MID(I41,5,3)&"/"&MID(I41,8,4)&"-"&MID(I41,12,2)),IF(X41="CNPJ_INCOMPLETO_2",("00."&LEFT(I41,3)&"."&MID(I41,4,3)&"/"&MID(I41,7,4)&"-"&MID(I41,11,2)),IF(X41="CNPJ",(LEFT(I41,2)&"."&MID(I41,3,3)&"."&MID(I41,6,3)&"/"&MID(I41,9,4)&"-"&MID(I41,13,2)),IF(X41="CPF_Incompleto",("0"&LEFT(I41,2)&"."&MID(I41,3,3)&"."&MID(I41,6,3)&"-"&MID(I41,9,2)),(LEFT(I41,3)&"."&MID(I41,4,3)&"."&MID(I41,7,3)&"-"&MID(I41,10,2)))))) -> 17.250.059/0001-30 | Z41: =VLOOKUP(Y41,FORNECEDORES!$A$2:$G$9043,3,0) -> SILVERIO DA SILVEIRA ME | AA41: =VLOOKUP(Y41,FORNECEDORES!$A$2:$G$9041,7,0) -> silveriosilveira86@hotmail.com;
A42: CON:3501 | B42: 4417812010875943 | C42: 45842 | D42: 45873 | E42: DES | F42: 540 | G42: EFETIVADA | H42: ANDRE L.A. ENDRES - ME | I42: 92309194000120 | J42: AFK2804 | K42: 101230591 | L42: SP | M42: 144769 | N42: 263987 | O42: 3501 | P42: RS | Q42: RS | R42: Finalizado | S42: Finalizada | T42: EFETIVADA | U42: 30 | V42: 45879 | W42: =LEN(I42) -> 14 | X42: =IF(W42=14,"CNPJ",IF(W42=12,"CNPJ_INCOMPLETO_2",IF(W42=13,"CNPJ_INCOMPLETO_1",IF(W42=10,"CPF_Incompleto","CPF")))) -> CNPJ | Y42: =IF(X42="CNPJ_INCOMPLETO_1",("0"&LEFT(I42,1)&"."&MID(I42,2,3)&"."&MID(I42,5,3)&"/"&MID(I42,8,4)&"-"&MID(I42,12,2)),IF(X42="CNPJ_INCOMPLETO_2",("00."&LEFT(I42,3)&"."&MID(I42,4,3)&"/"&MID(I42,7,4)&"-"&MID(I42,11,2)),IF(X42="CNPJ",(LEFT(I42,2)&"."&MID(I42,3,3)&"."&MID(I42,6,3)&"/"&MID(I42,9,4)&"-"&MID(I42,13,2)),IF(X42="CPF_Incompleto",("0"&LEFT(I42,2)&"."&MID(I42,3,3)&"."&MID(I42,6,3)&"-"&MID(I42,9,2)),(LEFT(I42,3)&"."&MID(I42,4,3)&"."&MID(I42,7,3)&"-"&MID(I42,10,2)))))) -> 92.309.194/0001-20 | Z42: =VLOOKUP(Y42,FORNECEDORES!$A$2:$G$9043,3,0) -> ANDRE L.A. ENDRES - ME | AA42: =VLOOKUP(Y42,FORNECEDORES!$A$2:$G$9041,7,0) -> endrestransportes@outlook.com
A43: CON:3502 | B43: 4417812022858440 | C43: 45842 | D43: 45842 | E43: ADT | F43: 1050.84 | G43: EFETIVADA | H43: JOSE DAGOBERTO MACHADO | I43: 40573680000 | J43: IKV8F25 | K43: 101244512 | L43: SP | M43: 144776 | N43: 264036 | O43: 3502, 3503 | P43: RS | Q43: RS | R43: Finalizado | S43: Finalizada | T43: EFETIVADA | U43: Quinta feira | V43: Quinta feira | W43: =LEN(I43) -> 11 | X43: =IF(W43=14,"CNPJ",IF(W43=12,"CNPJ_INCOMPLETO_2",IF(W43=13,"CNPJ_INCOMPLETO_1",IF(W43=10,"CPF_Incompleto","CPF")))) -> CPF | Y43: =IF(X43="CNPJ_INCOMPLETO_1",("0"&LEFT(I43,1)&"."&MID(I43,2,3)&"."&MID(I43,5,3)&"/"&MID(I43,8,4)&"-"&MID(I43,12,2)),IF(X43="CNPJ_INCOMPLETO_2",("00."&LEFT(I43,3)&"."&MID(I43,4,3)&"/"&MID(I43,7,4)&"-"&MID(I43,11,2)),IF(X43="CNPJ",(LEFT(I43,2)&"."&MID(I43,3,3)&"."&MID(I43,6,3)&"/"&MID(I43,9,4)&"-"&MID(I43,13,2)),IF(X43="CPF_Incompleto",("0"&LEFT(I43,2)&"."&MID(I43,3,3)&"."&MID(I43,6,3)&"-"&MID(I43,9,2)),(LEFT(I43,3)&"."&MID(I43,4,3)&"."&MID(I43,7,3)&"-"&MID(I43,10,2)))))) -> 405.736.800-00 | Z43: =VLOOKUP(Y43,FORNECEDORES!$A$2:$G$9043,3,0) -> JOSÉ DAGOBERTO MACHADO | AA43: =VLOOKUP(Y43,FORNECEDORES!$A$2:$G$9041,7,0) -> jdmdago@gmail.com;
A44: CON:3502 | B44: 4417812022858440 | C44: 45842 | D44: 45848 | E44: SDO | F44: 700.56 | G44: EFETIVADA | H44: JOSE DAGOBERTO MACHADO | I44: 40573680000 | J44: IKV8F25 | K44: 101244512 | L44: SP | M44: 144776 | N44: 264036 | O44: 3502, 3503 | P44: RS | Q44: RS | R44: Finalizado | S44: Finalizada | T44: EFETIVADA | U44: Quinta feira | V44: Quinta feira | W44: =LEN(I44) -> 11 | X44: =IF(W44=14,"CNPJ",IF(W44=12,"CNPJ_INCOMPLETO_2",IF(W44=13,"CNPJ_INCOMPLETO_1",IF(W44=10,"CPF_Incompleto","CPF")))) -> CPF | Y44: =IF(X44="CNPJ_INCOMPLETO_1",("0"&LEFT(I44,1)&"."&MID(I44,2,3)&"."&MID(I44,5,3)&"/"&MID(I44,8,4)&"-"&MID(I44,12,2)),IF(X44="CNPJ_INCOMPLETO_2",("00."&LEFT(I44,3)&"."&MID(I44,4,3)&"/"&MID(I44,7,4)&"-"&MID(I44,11,2)),IF(X44="CNPJ",(LEFT(I44,2)&"."&MID(I44,3,3)&"."&MID(I44,6,3)&"/"&MID(I44,9,4)&"-"&MID(I44,13,2)),IF(X44="CPF_Incompleto",("0"&LEFT(I44,2)&"."&MID(I44,3,3)&"."&MID(I44,6,3)&"-"&MID(I44,9,2)),(LEFT(I44,3)&"."&MID(I44,4,3)&"."&MID(I44,7,3)&"-"&MID(I44,10,2)))))) -> 405.736.800-00 | Z44: =VLOOKUP(Y44,FORNECEDORES!$A$2:$G$9043,3,0) -> JOSÉ DAGOBERTO MACHADO | AA44: =VLOOKUP(Y44,FORNECEDORES!$A$2:$G$9041,7,0) -> jdmdago@gmail.com;
A45: CON:3506 | B45: 4417812010875943 | C45: 45843 | D45: 45873 | E45: DES | F45: 2900 | G45: EFETIVADA | H45: ANDRE L.A. ENDRES - ME | I45: 92309194000120 | J45: AFK2804 | K45: 101274605 | L45: SP | M45: 144817 | N45: 264116 | O45: 3506 | P45: RS | Q45: RS | R45: Finalizado | S45: Finalizada | T45: EFETIVADA | U45: 30 | V45: 45879 | W45: =LEN(I45) -> 14 | X45: =IF(W45=14,"CNPJ",IF(W45=12,"CNPJ_INCOMPLETO_2",IF(W45=13,"CNPJ_INCOMPLETO_1",IF(W45=10,"CPF_Incompleto","CPF")))) -> CNPJ | Y45: =IF(X45="CNPJ_INCOMPLETO_1",("0"&LEFT(I45,1)&"."&MID(I45,2,3)&"."&MID(I45,5,3)&"/"&MID(I45,8,4)&"-"&MID(I45,12,2)),IF(X45="CNPJ_INCOMPLETO_2",("00."&LEFT(I45,3)&"."&MID(I45,4,3)&"/"&MID(I45,7,4)&"-"&MID(I45,11,2)),IF(X45="CNPJ",(LEFT(I45,2)&"."&MID(I45,3,3)&"."&MID(I45,6,3)&"/"&MID(I45,9,4)&"-"&MID(I45,13,2)),IF(X45="CPF_Incompleto",("0"&LEFT(I45,2)&"."&MID(I45,3,3)&"."&MID(I45,6,3)&"-"&MID(I45,9,2)),(LEFT(I45,3)&"."&MID(I45,4,3)&"."&MID(I45,7,3)&"-"&MID(I45,10,2)))))) -> 92.309.194/0001-20 | Z45: =VLOOKUP(Y45,FORNECEDORES!$A$2:$G$9043,3,0) -> ANDRE L.A. ENDRES - ME | AA45: =VLOOKUP(Y45,FORNECEDORES!$A$2:$G$9041,7,0) -> endrestransportes@outlook.com
A46: CON:3492 | B46: 4417812014686304 | C46: 45845 | D46: 45845 | E46: ADT | F46: 1500 | G46: EFETIVADA | H46: SILVERIO DA SILVEIRA | I46: 17250059000130 | J46: ATL5J69 | K46: 101295510 | L46: SP | M46: 144697 | N46: 263812 | O46: 3492 | P46: RS | Q46: RS | R46: Aprovado | S46: Em Transporte | T46: EFETIVADA | U46: Quinta feira | V46: Quinta feira | W46: =LEN(I46) -> 14 | X46: =IF(W46=14,"CNPJ",IF(W46=12,"CNPJ_INCOMPLETO_2",IF(W46=13,"CNPJ_INCOMPLETO_1",IF(W46=10,"CPF_Incompleto","CPF")))) -> CNPJ | Y46: =IF(X46="CNPJ_INCOMPLETO_1",("0"&LEFT(I46,1)&"."&MID(I46,2,3)&"."&MID(I46,5,3)&"/"&MID(I46,8,4)&"-"&MID(I46,12,2)),IF(X46="CNPJ_INCOMPLETO_2",("00."&LEFT(I46,3)&"."&MID(I46,4,3)&"/"&MID(I46,7,4)&"-"&MID(I46,11,2)),IF(X46="CNPJ",(LEFT(I46,2)&"."&MID(I46,3,3)&"."&MID(I46,6,3)&"/"&MID(I46,9,4)&"-"&MID(I46,13,2)),IF(X46="CPF_Incompleto",("0"&LEFT(I46,2)&"."&MID(I46,3,3)&"."&MID(I46,6,3)&"-"&MID(I46,9,2)),(LEFT(I46,3)&"."&MID(I46,4,3)&"."&MID(I46,7,3)&"-"&MID(I46,10,2)))))) -> 17.250.059/0001-30 | Z46: =VLOOKUP(Y46,FORNECEDORES!$A$2:$G$9043,3,0) -> SILVERIO DA SILVEIRA ME | AA46: =VLOOKUP(Y46,FORNECEDORES!$A$2:$G$9041,7,0) -> silveriosilveira86@hotmail.com;
A47: CON:3492 | B47: 4417812014686304 | C47: 45845 | D47: 45848 | E47: SDO | F47: 1000 | G47: EFETIVADA | H47: SILVERIO DA SILVEIRA | I47: 17250059000130 | J47: ATL5J69 | K47: 101295510 | L47: SP | M47: 144697 | N47: 263812 | O47: 3492 | P47: RS | Q47: RS | R47: Aprovado | S47: Em Transporte | T47: EFETIVADA | U47: Quinta feira | V47: Quinta feira | W47: =LEN(I47) -> 14 | X47: =IF(W47=14,"CNPJ",IF(W47=12,"CNPJ_INCOMPLETO_2",IF(W47=13,"CNPJ_INCOMPLETO_1",IF(W47=10,"CPF_Incompleto","CPF")))) -> CNPJ | Y47: =IF(X47="CNPJ_INCOMPLETO_1",("0"&LEFT(I47,1)&"."&MID(I47,2,3)&"."&MID(I47,5,3)&"/"&MID(I47,8,4)&"-"&MID(I47,12,2)),IF(X47="CNPJ_INCOMPLETO_2",("00."&LEFT(I47,3)&"."&MID(I47,4,3)&"/"&MID(I47,7,4)&"-"&MID(I47,11,2)),IF(X47="CNPJ",(LEFT(I47,2)&"."&MID(I47,3,3)&"."&MID(I47,6,3)&"/"&MID(I47,9,4)&"-"&MID(I47,13,2)),IF(X47="CPF_Incompleto",("0"&LEFT(I47,2)&"."&MID(I47,3,3)&"."&MID(I47,6,3)&"-"&MID(I47,9,2)),(LEFT(I47,3)&"."&MID(I47,4,3)&"."&MID(I47,7,3)&"-"&MID(I47,10,2)))))) -> 17.250.059/0001-30 | Z47: =VLOOKUP(Y47,FORNECEDORES!$A$2:$G$9043,3,0) -> SILVERIO DA SILVEIRA ME | AA47: =VLOOKUP(Y47,FORNECEDORES!$A$2:$G$9041,7,0) -> silveriosilveira86@hotmail.com;
A48: CON:3507 | B48: 4417812013265605 | C48: 45845 | D48: 45845 | E48: ADT | F48: 1693.02 | G48: EFETIVADA | H48: VANDERLI DASSOLER | I48: 58751050030 | J48: MKS4A50 | K48: 101298124 | L48: SP | M48: 144852 | N48: 264188 | O48: 3507 | P48: RS | Q48: RS | R48: Finalizado | S48: Finalizada | T48: EFETIVADA | U48: Quinta feira | V48: Quinta feira | W48: =LEN(I48) -> 11 | X48: =IF(W48=14,"CNPJ",IF(W48=12,"CNPJ_INCOMPLETO_2",IF(W48=13,"CNPJ_INCOMPLETO_1",IF(W48=10,"CPF_Incompleto","CPF")))) -> CPF | Y48: =IF(X48="CNPJ_INCOMPLETO_1",("0"&LEFT(I48,1)&"."&MID(I48,2,3)&"."&MID(I48,5,3)&"/"&MID(I48,8,4)&"-"&MID(I48,12,2)),IF(X48="CNPJ_INCOMPLETO_2",("00."&LEFT(I48,3)&"."&MID(I48,4,3)&"/"&MID(I48,7,4)&"-"&MID(I48,11,2)),IF(X48="CNPJ",(LEFT(I48,2)&"."&MID(I48,3,3)&"."&MID(I48,6,3)&"/"&MID(I48,9,4)&"-"&MID(I48,13,2)),IF(X48="CPF_Incompleto",("0"&LEFT(I48,2)&"."&MID(I48,3,3)&"."&MID(I48,6,3)&"-"&MID(I48,9,2)),(LEFT(I48,3)&"."&MID(I48,4,3)&"."&MID(I48,7,3)&"-"&MID(I48,10,2)))))) -> 587.510.500-30 | Z48: =VLOOKUP(Y48,FORNECEDORES!$A$2:$G$9043,3,0) -> VANDERLI DASSOLER | AA48: =VLOOKUP(Y48,FORNECEDORES!$A$2:$G$9041,7,0) -> vanderliegv@gmail.com;
A49: CON:3507 | B49: 4417812013265605 | C49: 45845 | D49: 45848 | E49: SDO | F49: 1128.68 | G49: EFETIVADA | H49: VANDERLI DASSOLER | I49: 58751050030 | J49: MKS4A50 | K49: 101298124 | L49: SP | M49: 144852 | N49: 264188 | O49: 3507 | P49: RS | Q49: RS | R49: Finalizado | S49: Finalizada | T49: EFETIVADA | U49: Quinta feira | V49: Quinta feira | W49: =LEN(I49) -> 11 | X49: =IF(W49=14,"CNPJ",IF(W49=12,"CNPJ_INCOMPLETO_2",IF(W49=13,"CNPJ_INCOMPLETO_1",IF(W49=10,"CPF_Incompleto","CPF")))) -> CPF | Y49: =IF(X49="CNPJ_INCOMPLETO_1",("0"&LEFT(I49,1)&"."&MID(I49,2,3)&"."&MID(I49,5,3)&"/"&MID(I49,8,4)&"-"&MID(I49,12,2)),IF(X49="CNPJ_INCOMPLETO_2",("00."&LEFT(I49,3)&"."&MID(I49,4,3)&"/"&MID(I49,7,4)&"-"&MID(I49,11,2)),IF(X49="CNPJ",(LEFT(I49,2)&"."&MID(I49,3,3)&"."&MID(I49,6,3)&"/"&MID(I49,9,4)&"-"&MID(I49,13,2)),IF(X49="CPF_Incompleto",("0"&LEFT(I49,2)&"."&MID(I49,3,3)&"."&MID(I49,6,3)&"-"&MID(I49,9,2)),(LEFT(I49,3)&"."&MID(I49,4,3)&"."&MID(I49,7,3)&"-"&MID(I49,10,2)))))) -> 587.510.500-30 | Z49: =VLOOKUP(Y49,FORNECEDORES!$A$2:$G$9043,3,0) -> VANDERLI DASSOLER | AA49: =VLOOKUP(Y49,FORNECEDORES!$A$2:$G$9041,7,0) -> vanderliegv@gmail.com;
A50: CON:3508 | B50: 4417812014686304 | C50: 45845 | D50: 45845 | E50: ADT | F50: 1620 | G50: EFETIVADA | H50: SILVERIO DA SILVEIRA | I50: 17250059000130 | J50: ATL5J69 | K50: 101301368 | L50: SP | M50: 144858 | N50: 264208 | O50: 3508 | P50: RS | Q50: RS | R50: Finalizado | S50: Finalizada | T50: EFETIVADA | U50: Quinta feira | V50: Quinta feira | W50: =LEN(I50) -> 14 | X50: =IF(W50=14,"CNPJ",IF(W50=12,"CNPJ_INCOMPLETO_2",IF(W50=13,"CNPJ_INCOMPLETO_1",IF(W50=10,"CPF_Incompleto","CPF")))) -> CNPJ | Y50: =IF(X50="CNPJ_INCOMPLETO_1",("0"&LEFT(I50,1)&"."&MID(I50,2,3)&"."&MID(I50,5,3)&"/"&MID(I50,8,4)&"-"&MID(I50,12,2)),IF(X50="CNPJ_INCOMPLETO_2",("00."&LEFT(I50,3)&"."&MID(I50,4,3)&"/"&MID(I50,7,4)&"-"&MID(I50,11,2)),IF(X50="CNPJ",(LEFT(I50,2)&"."&MID(I50,3,3)&"."&MID(I50,6,3)&"/"&MID(I50,9,4)&"-"&MID(I50,13,2)),IF(X50="CPF_Incompleto",("0"&LEFT(I50,2)&"."&MID(I50,3,3)&"."&MID(I50,6,3)&"-"&MID(I50,9,2)),(LEFT(I50,3)&"."&MID(I50,4,3)&"."&MID(I50,7,3)&"-"&MID(I50,10,2)))))) -> 17.250.059/0001-30 | Z50: =VLOOKUP(Y50,FORNECEDORES!$A$2:$G$9043,3,0) -> SILVERIO DA SILVEIRA ME | AA50: =VLOOKUP(Y50,FORNECEDORES!$A$2:$G$9041,7,0) -> silveriosilveira86@hotmail.com;
A51: CON:3508 | B51: 4417812014686304 | C51: 45845 | D51: 45848 | E51: SDO | F51: 1080 | G51: EFETIVADA | H51: SILVERIO DA SILVEIRA | I51: 17250059000130 | J51: ATL5J69 | K51: 101301368 | L51: SP | M51: 144858 | N51: 264208 | O51: 3508 | P51: RS | Q51: RS | R51: Finalizado | S51: Finalizada | T51: EFETIVADA | U51: Quinta feira | V51: Quinta feira | W51: =LEN(I51) -> 14 | X51: =IF(W51=14,"CNPJ",IF(W51=12,"CNPJ_INCOMPLETO_2",IF(W51=13,"CNPJ_INCOMPLETO_1",IF(W51=10,"CPF_Incompleto","CPF")))) -> CNPJ | Y51: =IF(X51="CNPJ_INCOMPLETO_1",("0"&LEFT(I51,1)&"."&MID(I51,2,3)&"."&MID(I51,5,3)&"/"&MID(I51,8,4)&"-"&MID(I51,12,2)),IF(X51="CNPJ_INCOMPLETO_2",("00."&LEFT(I51,3)&"."&MID(I51,4,3)&"/"&MID(I51,7,4)&"-"&MID(I51,11,2)),IF(X51="CNPJ",(LEFT(I51,2)&"."&MID(I51,3,3)&"."&MID(I51,6,3)&"/"&MID(I51,9,4)&"-"&MID(I51,13,2)),IF(X51="CPF_Incompleto",("0"&LEFT(I51,2)&"."&MID(I51,3,3)&"."&MID(I51,6,3)&"-"&MID(I51,9,2)),(LEFT(I51,3)&"."&MID(I51,4,3)&"."&MID(I51,7,3)&"-"&MID(I51,10,2)))))) -> 17.250.059/0001-30 | Z51: =VLOOKUP(Y51,FORNECEDORES!$A$2:$G$9043,3,0) -> SILVERIO DA SILVEIRA ME | AA51: =VLOOKUP(Y51,FORNECEDORES!$A$2:$G$9041,7,0) -> silveriosilveira86@hotmail.com;
A52: CON:3509 | B52: 4417812022858440 | C52: 45845 | D52: 45845 | E52: ADT | F52: 1050.84 | G52: EFETIVADA | H52: JOSE DAGOBERTO MACHADO | I52: 40573680000 | J52: IKV8F25 | K52: 101310608 | L52: SP | M52: 144868 | N52: 264241 | O52: 3509 | P52: RS | Q52: RS | R52: Finalizado | S52: Finalizada | T52: EFETIVADA | U52: Quinta feira | V52: Quinta feira | W52: =LEN(I52) -> 11 | X52: =IF(W52=14,"CNPJ",IF(W52=12,"CNPJ_INCOMPLETO_2",IF(W52=13,"CNPJ_INCOMPLETO_1",IF(W52=10,"CPF_Incompleto","CPF")))) -> CPF | Y52: =IF(X52="CNPJ_INCOMPLETO_1",("0"&LEFT(I52,1)&"."&MID(I52,2,3)&"."&MID(I52,5,3)&"/"&MID(I52,8,4)&"-"&MID(I52,12,2)),IF(X52="CNPJ_INCOMPLETO_2",("00."&LEFT(I52,3)&"."&MID(I52,4,3)&"/"&MID(I52,7,4)&"-"&MID(I52,11,2)),IF(X52="CNPJ",(LEFT(I52,2)&"."&MID(I52,3,3)&"."&MID(I52,6,3)&"/"&MID(I52,9,4)&"-"&MID(I52,13,2)),IF(X52="CPF_Incompleto",("0"&LEFT(I52,2)&"."&MID(I52,3,3)&"."&MID(I52,6,3)&"-"&MID(I52,9,2)),(LEFT(I52,3)&"."&MID(I52,4,3)&"."&MID(I52,7,3)&"-"&MID(I52,10,2)))))) -> 405.736.800-00 | Z52: =VLOOKUP(Y52,FORNECEDORES!$A$2:$G$9043,3,0) -> JOSÉ DAGOBERTO MACHADO | AA52: =VLOOKUP(Y52,FORNECEDORES!$A$2:$G$9041,7,0) -> jdmdago@gmail.com;
A53: CON:3509 | B53: 4417812022858440 | C53: 45845 | D53: 45848 | E53: SDO | F53: 700.56 | G53: EFETIVADA | H53: JOSE DAGOBERTO MACHADO | I53: 40573680000 | J53: IKV8F25 | K53: 101310608 | L53: SP | M53: 144868 | N53: 264241 | O53: 3509 | P53: RS | Q53: RS | R53: Finalizado | S53: Finalizada | T53: EFETIVADA | U53: Quinta feira | V53: Quinta feira | W53: =LEN(I53) -> 11 | X53: =IF(W53=14,"CNPJ",IF(W53=12,"CNPJ_INCOMPLETO_2",IF(W53=13,"CNPJ_INCOMPLETO_1",IF(W53=10,"CPF_Incompleto","CPF")))) -> CPF | Y53: =IF(X53="CNPJ_INCOMPLETO_1",("0"&LEFT(I53,1)&"."&MID(I53,2,3)&"."&MID(I53,5,3)&"/"&MID(I53,8,4)&"-"&MID(I53,12,2)),IF(X53="CNPJ_INCOMPLETO_2",("00."&LEFT(I53,3)&"."&MID(I53,4,3)&"/"&MID(I53,7,4)&"-"&MID(I53,11,2)),IF(X53="CNPJ",(LEFT(I53,2)&"."&MID(I53,3,3)&"."&MID(I53,6,3)&"/"&MID(I53,9,4)&"-"&MID(I53,13,2)),IF(X53="CPF_Incompleto",("0"&LEFT(I53,2)&"."&MID(I53,3,3)&"."&MID(I53,6,3)&"-"&MID(I53,9,2)),(LEFT(I53,3)&"."&MID(I53,4,3)&"."&MID(I53,7,3)&"-"&MID(I53,10,2)))))) -> 405.736.800-00 | Z53: =VLOOKUP(Y53,FORNECEDORES!$A$2:$G$9043,3,0) -> JOSÉ DAGOBERTO MACHADO | AA53: =VLOOKUP(Y53,FORNECEDORES!$A$2:$G$9041,7,0) -> jdmdago@gmail.com;
A54: CON:3510 | B54: 4417812015511030 | C54: 45845 | D54: 45845 | E54: ADT | F54: 1109.22 | G54: EFETIVADA | H54: Denis Camillo Da Silva | I54: 96685697091 | J54: IQM9933 | K54: 101313736 | L54: SP | M54: 144871 | N54: 264253 | O54: 3510 | P54: RS | Q54: RS | R54: Finalizado | S54: Finalizada | T54: EFETIVADA | U54: Quinta feira | V54: Quinta feira | W54: =LEN(I54) -> 11 | X54: =IF(W54=14,"CNPJ",IF(W54=12,"CNPJ_INCOMPLETO_2",IF(W54=13,"CNPJ_INCOMPLETO_1",IF(W54=10,"CPF_Incompleto","CPF")))) -> CPF | Y54: =IF(X54="CNPJ_INCOMPLETO_1",("0"&LEFT(I54,1)&"."&MID(I54,2,3)&"."&MID(I54,5,3)&"/"&MID(I54,8,4)&"-"&MID(I54,12,2)),IF(X54="CNPJ_INCOMPLETO_2",("00."&LEFT(I54,3)&"."&MID(I54,4,3)&"/"&MID(I54,7,4)&"-"&MID(I54,11,2)),IF(X54="CNPJ",(LEFT(I54,2)&"."&MID(I54,3,3)&"."&MID(I54,6,3)&"/"&MID(I54,9,4)&"-"&MID(I54,13,2)),IF(X54="CPF_Incompleto",("0"&LEFT(I54,2)&"."&MID(I54,3,3)&"."&MID(I54,6,3)&"-"&MID(I54,9,2)),(LEFT(I54,3)&"."&MID(I54,4,3)&"."&MID(I54,7,3)&"-"&MID(I54,10,2)))))) -> 966.856.970-91 | Z54: =VLOOKUP(Y54,FORNECEDORES!$A$2:$G$9043,3,0) -> DENIS CAMILLO DA SILVA | AA54: =VLOOKUP(Y54,FORNECEDORES!$A$2:$G$9041,7,0) -> deniscamillo29@gmail.com;
A55: CON:3510 | B55: 4417812015511030 | C55: 45845 | D55: 45848 | E55: SDO | F55: 739.48 | G55: EFETIVADA | H55: Denis Camillo Da Silva | I55: 96685697091 | J55: IQM9933 | K55: 101313736 | L55: SP | M55: 144871 | N55: 264253 | O55: 3510 | P55: RS | Q55: RS | R55: Finalizado | S55: Finalizada | T55: EFETIVADA | U55: Quinta feira | V55: Quinta feira | W55: =LEN(I55) -> 11 | X55: =IF(W55=14,"CNPJ",IF(W55=12,"CNPJ_INCOMPLETO_2",IF(W55=13,"CNPJ_INCOMPLETO_1",IF(W55=10,"CPF_Incompleto","CPF")))) -> CPF | Y55: =IF(X55="CNPJ_INCOMPLETO_1",("0"&LEFT(I55,1)&"."&MID(I55,2,3)&"."&MID(I55,5,3)&"/"&MID(I55,8,4)&"-"&MID(I55,12,2)),IF(X55="CNPJ_INCOMPLETO_2",("00."&LEFT(I55,3)&"."&MID(I55,4,3)&"/"&MID(I55,7,4)&"-"&MID(I55,11,2)),IF(X55="CNPJ",(LEFT(I55,2)&"."&MID(I55,3,3)&"."&MID(I55,6,3)&"/"&MID(I55,9,4)&"-"&MID(I55,13,2)),IF(X55="CPF_Incompleto",("0"&LEFT(I55,2)&"."&MID(I55,3,3)&"."&MID(I55,6,3)&"-"&MID(I55,9,2)),(LEFT(I55,3)&"."&MID(I55,4,3)&"."&MID(I55,7,3)&"-"&MID(I55,10,2)))))) -> 966.856.970-91 | Z55: =VLOOKUP(Y55,FORNECEDORES!$A$2:$G$9043,3,0) -> DENIS CAMILLO DA SILVA | AA55: =VLOOKUP(Y55,FORNECEDORES!$A$2:$G$9041,7,0) -> deniscamillo29@gmail.com;
A56: CON:1683 | B56: 4417812013265605 | C56: 45846 | D56: 45846 | E56: ADT | F56: 2335.2 | G56: EFETIVADA | H56: VANDERLI DASSOLER | I56: 58751050030 | J56: MKS4A50 | K56: 101335404 | L56: SP | M56: 144901 | N56: 264327 | O56: 1683, 1684, 1685 | P56: RS | Q56: RS | R56: Finalizado | S56: Finalizada | T56: EFETIVADA | U56: Quinta feira | V56: Quinta feira | W56: =LEN(I56) -> 11 | X56: =IF(W56=14,"CNPJ",IF(W56=12,"CNPJ_INCOMPLETO_2",IF(W56=13,"CNPJ_INCOMPLETO_1",IF(W56=10,"CPF_Incompleto","CPF")))) -> CPF | Y56: =IF(X56="CNPJ_INCOMPLETO_1",("0"&LEFT(I56,1)&"."&MID(I56,2,3)&"."&MID(I56,5,3)&"/"&MID(I56,8,4)&"-"&MID(I56,12,2)),IF(X56="CNPJ_INCOMPLETO_2",("00."&LEFT(I56,3)&"."&MID(I56,4,3)&"/"&MID(I56,7,4)&"-"&MID(I56,11,2)),IF(X56="CNPJ",(LEFT(I56,2)&"."&MID(I56,3,3)&"."&MID(I56,6,3)&"/"&MID(I56,9,4)&"-"&MID(I56,13,2)),IF(X56="CPF_Incompleto",("0"&LEFT(I56,2)&"."&MID(I56,3,3)&"."&MID(I56,6,3)&"-"&MID(I56,9,2)),(LEFT(I56,3)&"."&MID(I56,4,3)&"."&MID(I56,7,3)&"-"&MID(I56,10,2)))))) -> 587.510.500-30 | Z56: =VLOOKUP(Y56,FORNECEDORES!$A$2:$G$9043,3,0) -> VANDERLI DASSOLER | AA56: =VLOOKUP(Y56,FORNECEDORES!$A$2:$G$9041,7,0) -> vanderliegv@gmail.com;
A57: CON:1683 | B57: 4417812013265605 | C57: 45846 | D57: 45848 | E57: SDO | F57: 1556.8 | G57: EFETIVADA | H57: VANDERLI DASSOLER | I57: 58751050030 | J57: MKS4A50 | K57: 101335404 | L57: SP | M57: 144901 | N57: 264327 | O57: 1683, 1684, 1685 | P57: RS | Q57: RS | R57: Finalizado | S57: Finalizada | T57: EFETIVADA | U57: Quinta feira | V57: Quinta feira | W57: =LEN(I57) -> 11 | X57: =IF(W57=14,"CNPJ",IF(W57=12,"CNPJ_INCOMPLETO_2",IF(W57=13,"CNPJ_INCOMPLETO_1",IF(W57=10,"CPF_Incompleto","CPF")))) -> CPF | Y57: =IF(X57="CNPJ_INCOMPLETO_1",("0"&LEFT(I57,1)&"."&MID(I57,2,3)&"."&MID(I57,5,3)&"/"&MID(I57,8,4)&"-"&MID(I57,12,2)),IF(X57="CNPJ_INCOMPLETO_2",("00."&LEFT(I57,3)&"."&MID(I57,4,3)&"/"&MID(I57,7,4)&"-"&MID(I57,11,2)),IF(X57="CNPJ",(LEFT(I57,2)&"."&MID(I57,3,3)&"."&MID(I57,6,3)&"/"&MID(I57,9,4)&"-"&MID(I57,13,2)),IF(X57="CPF_Incompleto",("0"&LEFT(I57,2)&"."&MID(I57,3,3)&"."&MID(I57,6,3)&"-"&MID(I57,9,2)),(LEFT(I57,3)&"."&MID(I57,4,3)&"."&MID(I57,7,3)&"-"&MID(I57,10,2)))))) -> 587.510.500-30 | Z57: =VLOOKUP(Y57,FORNECEDORES!$A$2:$G$9043,3,0) -> VANDERLI DASSOLER | AA57: =VLOOKUP(Y57,FORNECEDORES!$A$2:$G$9041,7,0) -> vanderliegv@gmail.com;
A58: CON:3513 | B58: 4417812010875943 | C58: 45846 | D58: 45876 | E58: DES | F58: 1800 | G58: EFETIVADA | H58: ANDRE L.A. ENDRES - ME | I58: 92309194000120 | J58: AFK2804 | K58: 101360970 | L58: SP | M58: 144935 | N58: 264500 | O58: 3513 | P58: RS | Q58: RS | R58: Finalizado | S58: Finalizada | T58: EFETIVADA | U58: 30 | V58: 45879 | W58: =LEN(I58) -> 14 | X58: =IF(W58=14,"CNPJ",IF(W58=12,"CNPJ_INCOMPLETO_2",IF(W58=13,"CNPJ_INCOMPLETO_1",IF(W58=10,"CPF_Incompleto","CPF")))) -> CNPJ | Y58: =IF(X58="CNPJ_INCOMPLETO_1",("0"&LEFT(I58,1)&"."&MID(I58,2,3)&"."&MID(I58,5,3)&"/"&MID(I58,8,4)&"-"&MID(I58,12,2)),IF(X58="CNPJ_INCOMPLETO_2",("00."&LEFT(I58,3)&"."&MID(I58,4,3)&"/"&MID(I58,7,4)&"-"&MID(I58,11,2)),IF(X58="CNPJ",(LEFT(I58,2)&"."&MID(I58,3,3)&"."&MID(I58,6,3)&"/"&MID(I58,9,4)&"-"&MID(I58,13,2)),IF(X58="CPF_Incompleto",("0"&LEFT(I58,2)&"."&MID(I58,3,3)&"."&MID(I58,6,3)&"-"&MID(I58,9,2)),(LEFT(I58,3)&"."&MID(I58,4,3)&"."&MID(I58,7,3)&"-"&MID(I58,10,2)))))) -> 92.309.194/0001-20 | Z58: =VLOOKUP(Y58,FORNECEDORES!$A$2:$G$9043,3,0) -> ANDRE L.A. ENDRES - ME | AA58: =VLOOKUP(Y58,FORNECEDORES!$A$2:$G$9041,7,0) -> endrestransportes@outlook.com
A59: CON:3515 | B59: 4417812022858440 | C59: 45847 | D59: 45848 | E59: ADT | F59: 1576.26 | G59: EFETIVADA | H59: JOSE DAGOBERTO MACHADO | I59: 40573680000 | J59: IKV8F25 | K59: 101393374 | L59: SP | M59: 144991 | N59: 264646 | O59: 3515 | P59: RS | Q59: RS | R59: Finalizado | S59: Finalizada | T59: EFETIVADA | U59: Quinta feira | V59: Quinta feira | W59: =LEN(I59) -> 11 | X59: =IF(W59=14,"CNPJ",IF(W59=12,"CNPJ_INCOMPLETO_2",IF(W59=13,"CNPJ_INCOMPLETO_1",IF(W59=10,"CPF_Incompleto","CPF")))) -> CPF | Y59: =IF(X59="CNPJ_INCOMPLETO_1",("0"&LEFT(I59,1)&"."&MID(I59,2,3)&"."&MID(I59,5,3)&"/"&MID(I59,8,4)&"-"&MID(I59,12,2)),IF(X59="CNPJ_INCOMPLETO_2",("00."&LEFT(I59,3)&"."&MID(I59,4,3)&"/"&MID(I59,7,4)&"-"&MID(I59,11,2)),IF(X59="CNPJ",(LEFT(I59,2)&"."&MID(I59,3,3)&"."&MID(I59,6,3)&"/"&MID(I59,9,4)&"-"&MID(I59,13,2)),IF(X59="CPF_Incompleto",("0"&LEFT(I59,2)&"."&MID(I59,3,3)&"."&MID(I59,6,3)&"-"&MID(I59,9,2)),(LEFT(I59,3)&"."&MID(I59,4,3)&"."&MID(I59,7,3)&"-"&MID(I59,10,2)))))) -> 405.736.800-00 | Z59: =VLOOKUP(Y59,FORNECEDORES!$A$2:$G$9043,3,0) -> JOSÉ DAGOBERTO MACHADO | AA59: =VLOOKUP(Y59,FORNECEDORES!$A$2:$G$9041,7,0) -> jdmdago@gmail.com;
A60: CON:3515 | B60: 4417812022858440 | C60: 45847 | D60: 45855 | E60: SDO | F60: 1050.84 | G60: EFETIVADA | H60: JOSE DAGOBERTO MACHADO | I60: 40573680000 | J60: IKV8F25 | K60: 101393374 | L60: SP | M60: 144991 | N60: 264646 | O60: 3515 | P60: RS | Q60: RS | R60: Finalizado | S60: Finalizada | T60: EFETIVADA | U60: Quinta feira | V60: Quinta feira | W60: =LEN(I60) -> 11 | X60: =IF(W60=14,"CNPJ",IF(W60=12,"CNPJ_INCOMPLETO_2",IF(W60=13,"CNPJ_INCOMPLETO_1",IF(W60=10,"CPF_Incompleto","CPF")))) -> CPF | Y60: =IF(X60="CNPJ_INCOMPLETO_1",("0"&LEFT(I60,1)&"."&MID(I60,2,3)&"."&MID(I60,5,3)&"/"&MID(I60,8,4)&"-"&MID(I60,12,2)),IF(X60="CNPJ_INCOMPLETO_2",("00."&LEFT(I60,3)&"."&MID(I60,4,3)&"/"&MID(I60,7,4)&"-"&MID(I60,11,2)),IF(X60="CNPJ",(LEFT(I60,2)&"."&MID(I60,3,3)&"."&MID(I60,6,3)&"/"&MID(I60,9,4)&"-"&MID(I60,13,2)),IF(X60="CPF_Incompleto",("0"&LEFT(I60,2)&"."&MID(I60,3,3)&"."&MID(I60,6,3)&"-"&MID(I60,9,2)),(LEFT(I60,3)&"."&MID(I60,4,3)&"."&MID(I60,7,3)&"-"&MID(I60,10,2)))))) -> 405.736.800-00 | Z60: =VLOOKUP(Y60,FORNECEDORES!$A$2:$G$9043,3,0) -> JOSÉ DAGOBERTO MACHADO | AA60: =VLOOKUP(Y60,FORNECEDORES!$A$2:$G$9041,7,0) -> jdmdago@gmail.com;
A61: CON:3516 | B61: 4417812013265605 | C61: 45847 | D61: 45848 | E61: ADT | F61: 1576.26 | G61: EFETIVADA | H61: VANDERLI DASSOLER | I61: 58751050030 | J61: MKS4A50 | K61: 101398523 | L61: SP | M61: 145002 | N61: 264656 | O61: 3516 | P61: RS | Q61: RS | R61: Finalizado | S61: Finalizada | T61: EFETIVADA | U61: Quinta feira | V61: Quinta feira | W61: =LEN(I61) -> 11 | X61: =IF(W61=14,"CNPJ",IF(W61=12,"CNPJ_INCOMPLETO_2",IF(W61=13,"CNPJ_INCOMPLETO_1",IF(W61=10,"CPF_Incompleto","CPF")))) -> CPF | Y61: =IF(X61="CNPJ_INCOMPLETO_1",("0"&LEFT(I61,1)&"."&MID(I61,2,3)&"."&MID(I61,5,3)&"/"&MID(I61,8,4)&"-"&MID(I61,12,2)),IF(X61="CNPJ_INCOMPLETO_2",("00."&LEFT(I61,3)&"."&MID(I61,4,3)&"/"&MID(I61,7,4)&"-"&MID(I61,11,2)),IF(X61="CNPJ",(LEFT(I61,2)&"."&MID(I61,3,3)&"."&MID(I61,6,3)&"/"&MID(I61,9,4)&"-"&MID(I61,13,2)),IF(X61="CPF_Incompleto",("0"&LEFT(I61,2)&"."&MID(I61,3,3)&"."&MID(I61,6,3)&"-"&MID(I61,9,2)),(LEFT(I61,3)&"."&MID(I61,4,3)&"."&MID(I61,7,3)&"-"&MID(I61,10,2)))))) -> 587.510.500-30 | Z61: =VLOOKUP(Y61,FORNECEDORES!$A$2:$G$9043,3,0) -> VANDERLI DASSOLER | AA61: =VLOOKUP(Y61,FORNECEDORES!$A$2:$G$9041,7,0) -> vanderliegv@gmail.com;
A62: CON:3516 | B62: 4417812013265605 | C62: 45847 | D62: 45855 | E62: SDO | F62: 1050.84 | G62: EFETIVADA | H62: VANDERLI DASSOLER | I62: 58751050030 | J62: MKS4A50 | K62: 101398523 | L62: SP | M62: 145002 | N62: 264656 | O62: 3516 | P62: RS | Q62: RS | R62: Finalizado | S62: Finalizada | T62: EFETIVADA | U62: Quinta feira | V62: Quinta feira | W62: =LEN(I62) -> 11 | X62: =IF(W62=14,"CNPJ",IF(W62=12,"CNPJ_INCOMPLETO_2",IF(W62=13,"CNPJ_INCOMPLETO_1",IF(W62=10,"CPF_Incompleto","CPF")))) -> CPF | Y62: =IF(X62="CNPJ_INCOMPLETO_1",("0"&LEFT(I62,1)&"."&MID(I62,2,3)&"."&MID(I62,5,3)&"/"&MID(I62,8,4)&"-"&MID(I62,12,2)),IF(X62="CNPJ_INCOMPLETO_2",("00."&LEFT(I62,3)&"."&MID(I62,4,3)&"/"&MID(I62,7,4)&"-"&MID(I62,11,2)),IF(X62="CNPJ",(LEFT(I62,2)&"."&MID(I62,3,3)&"."&MID(I62,6,3)&"/"&MID(I62,9,4)&"-"&MID(I62,13,2)),IF(X62="CPF_Incompleto",("0"&LEFT(I62,2)&"."&MID(I62,3,3)&"."&MID(I62,6,3)&"-"&MID(I62,9,2)),(LEFT(I62,3)&"."&MID(I62,4,3)&"."&MID(I62,7,3)&"-"&MID(I62,10,2)))))) -> 587.510.500-30 | Z62: =VLOOKUP(Y62,FORNECEDORES!$A$2:$G$9043,3,0) -> VANDERLI DASSOLER | AA62: =VLOOKUP(Y62,FORNECEDORES!$A$2:$G$9041,7,0) -> vanderliegv@gmail.com;
A63: CON:3517 | B63: 4417812014686304 | C63: 45848 | D63: 45848 | E63: ADT | F63: 840 | G63: EFETIVADA | H63: SILVERIO DA SILVEIRA | I63: 17250059000130 | J63: ATL5J69 | K63: 101412592 | L63: SP | M63: 145023 | N63: 264714 | O63: 3517 | P63: RS | Q63: RS | R63: Finalizado | S63: Finalizada | T63: EFETIVADA | U63: Quinta feira | V63: Quinta feira | W63: =LEN(I63) -> 14 | X63: =IF(W63=14,"CNPJ",IF(W63=12,"CNPJ_INCOMPLETO_2",IF(W63=13,"CNPJ_INCOMPLETO_1",IF(W63=10,"CPF_Incompleto","CPF")))) -> CNPJ | Y63: =IF(X63="CNPJ_INCOMPLETO_1",("0"&LEFT(I63,1)&"."&MID(I63,2,3)&"."&MID(I63,5,3)&"/"&MID(I63,8,4)&"-"&MID(I63,12,2)),IF(X63="CNPJ_INCOMPLETO_2",("00."&LEFT(I63,3)&"."&MID(I63,4,3)&"/"&MID(I63,7,4)&"-"&MID(I63,11,2)),IF(X63="CNPJ",(LEFT(I63,2)&"."&MID(I63,3,3)&"."&MID(I63,6,3)&"/"&MID(I63,9,4)&"-"&MID(I63,13,2)),IF(X63="CPF_Incompleto",("0"&LEFT(I63,2)&"."&MID(I63,3,3)&"."&MID(I63,6,3)&"-"&MID(I63,9,2)),(LEFT(I63,3)&"."&MID(I63,4,3)&"."&MID(I63,7,3)&"-"&MID(I63,10,2)))))) -> 17.250.059/0001-30 | Z63: =VLOOKUP(Y63,FORNECEDORES!$A$2:$G$9043,3,0) -> SILVERIO DA SILVEIRA ME | AA63: =VLOOKUP(Y63,FORNECEDORES!$A$2:$G$9041,7,0) -> silveriosilveira86@hotmail.com;
A64: CON:3517 | B64: 4417812014686304 | C64: 45848 | D64: 45855 | E64: SDO | F64: 560 | G64: EFETIVADA | H64: SILVERIO DA SILVEIRA | I64: 17250059000130 | J64: ATL5J69 | K64: 101412592 | L64: SP | M64: 145023 | N64: 264714 | O64: 3517 | P64: RS | Q64: RS | R64: Finalizado | S64: Finalizada | T64: EFETIVADA | U64: Quinta feira | V64: Quinta feira | W64: =LEN(I64) -> 14 | X64: =IF(W64=14,"CNPJ",IF(W64=12,"CNPJ_INCOMPLETO_2",IF(W64=13,"CNPJ_INCOMPLETO_1",IF(W64=10,"CPF_Incompleto","CPF")))) -> CNPJ | Y64: =IF(X64="CNPJ_INCOMPLETO_1",("0"&LEFT(I64,1)&"."&MID(I64,2,3)&"."&MID(I64,5,3)&"/"&MID(I64,8,4)&"-"&MID(I64,12,2)),IF(X64="CNPJ_INCOMPLETO_2",("00."&LEFT(I64,3)&"."&MID(I64,4,3)&"/"&MID(I64,7,4)&"-"&MID(I64,11,2)),IF(X64="CNPJ",(LEFT(I64,2)&"."&MID(I64,3,3)&"."&MID(I64,6,3)&"/"&MID(I64,9,4)&"-"&MID(I64,13,2)),IF(X64="CPF_Incompleto",("0"&LEFT(I64,2)&"."&MID(I64,3,3)&"."&MID(I64,6,3)&"-"&MID(I64,9,2)),(LEFT(I64,3)&"."&MID(I64,4,3)&"."&MID(I64,7,3)&"-"&MID(I64,10,2)))))) -> 17.250.059/0001-30 | Z64: =VLOOKUP(Y64,FORNECEDORES!$A$2:$G$9043,3,0) -> SILVERIO DA SILVEIRA ME | AA64: =VLOOKUP(Y64,FORNECEDORES!$A$2:$G$9041,7,0) -> silveriosilveira86@hotmail.com;
A65: CON:3518 | B65: 4417812015511030 | C65: 45848 | D65: 45848 | E65: ADT | F65: 992.46 | G65: EFETIVADA | H65: Denis Camillo Da Silva | I65: 96685697091 | J65: IQM9933 | K65: 101413823 | L65: SP | M65: 145024 | N65: 264720 | O65: 3518 | P65: RS | Q65: RS | R65: Finalizado | S65: Finalizada | T65: EFETIVADA | U65: Quinta feira | V65: Quinta feira | W65: =LEN(I65) -> 11 | X65: =IF(W65=14,"CNPJ",IF(W65=12,"CNPJ_INCOMPLETO_2",IF(W65=13,"CNPJ_INCOMPLETO_1",IF(W65=10,"CPF_Incompleto","CPF")))) -> CPF | Y65: =IF(X65="CNPJ_INCOMPLETO_1",("0"&LEFT(I65,1)&"."&MID(I65,2,3)&"."&MID(I65,5,3)&"/"&MID(I65,8,4)&"-"&MID(I65,12,2)),IF(X65="CNPJ_INCOMPLETO_2",("00."&LEFT(I65,3)&"."&MID(I65,4,3)&"/"&MID(I65,7,4)&"-"&MID(I65,11,2)),IF(X65="CNPJ",(LEFT(I65,2)&"."&MID(I65,3,3)&"."&MID(I65,6,3)&"/"&MID(I65,9,4)&"-"&MID(I65,13,2)),IF(X65="CPF_Incompleto",("0"&LEFT(I65,2)&"."&MID(I65,3,3)&"."&MID(I65,6,3)&"-"&MID(I65,9,2)),(LEFT(I65,3)&"."&MID(I65,4,3)&"."&MID(I65,7,3)&"-"&MID(I65,10,2)))))) -> 966.856.970-91 | Z65: =VLOOKUP(Y65,FORNECEDORES!$A$2:$G$9043,3,0) -> DENIS CAMILLO DA SILVA | AA65: =VLOOKUP(Y65,FORNECEDORES!$A$2:$G$9041,7,0) -> deniscamillo29@gmail.com;
A66: CON:3518 | B66: 4417812015511030 | C66: 45848 | D66: 45855 | E66: SDO | F66: 661.64 | G66: EFETIVADA | H66: Denis Camillo Da Silva | I66: 96685697091 | J66: IQM9933 | K66: 101413823 | L66: SP | M66: 145024 | N66: 264720 | O66: 3518 | P66: RS | Q66: RS | R66: Finalizado | S66: Finalizada | T66: EFETIVADA | U66: Quinta feira | V66: Quinta feira | W66: =LEN(I66) -> 11 | X66: =IF(W66=14,"CNPJ",IF(W66=12,"CNPJ_INCOMPLETO_2",IF(W66=13,"CNPJ_INCOMPLETO_1",IF(W66=10,"CPF_Incompleto","CPF")))) -> CPF | Y66: =IF(X66="CNPJ_INCOMPLETO_1",("0"&LEFT(I66,1)&"."&MID(I66,2,3)&"."&MID(I66,5,3)&"/"&MID(I66,8,4)&"-"&MID(I66,12,2)),IF(X66="CNPJ_INCOMPLETO_2",("00."&LEFT(I66,3)&"."&MID(I66,4,3)&"/"&MID(I66,7,4)&"-"&MID(I66,11,2)),IF(X66="CNPJ",(LEFT(I66,2)&"."&MID(I66,3,3)&"."&MID(I66,6,3)&"/"&MID(I66,9,4)&"-"&MID(I66,13,2)),IF(X66="CPF_Incompleto",("0"&LEFT(I66,2)&"."&MID(I66,3,3)&"."&MID(I66,6,3)&"-"&MID(I66,9,2)),(LEFT(I66,3)&"."&MID(I66,4,3)&"."&MID(I66,7,3)&"-"&MID(I66,10,2)))))) -> 966.856.970-91 | Z66: =VLOOKUP(Y66,FORNECEDORES!$A$2:$G$9043,3,0) -> DENIS CAMILLO DA SILVA | AA66: =VLOOKUP(Y66,FORNECEDORES!$A$2:$G$9041,7,0) -> deniscamillo29@gmail.com;
A67: CON:3520 | B67: 4417812010875943 | C67: 45848 | D67: 45877 | E67: DES | F67: 2700 | G67: EFETIVADA | H67: ANDRE L.A. ENDRES - ME | I67: 92309194000120 | J67: AFK2804 | K67: 101429289 | L67: SP | M67: 145048 | N67: 264781 | O67: 3520 | P67: RS | Q67: RS | R67: Finalizado | S67: Finalizada | T67: EFETIVADA | U67: 30 | V67: 45879 | W67: =LEN(I67) -> 14 | X67: =IF(W67=14,"CNPJ",IF(W67=12,"CNPJ_INCOMPLETO_2",IF(W67=13,"CNPJ_INCOMPLETO_1",IF(W67=10,"CPF_Incompleto","CPF")))) -> CNPJ | Y67: =IF(X67="CNPJ_INCOMPLETO_1",("0"&LEFT(I67,1)&"."&MID(I67,2,3)&"."&MID(I67,5,3)&"/"&MID(I67,8,4)&"-"&MID(I67,12,2)),IF(X67="CNPJ_INCOMPLETO_2",("00."&LEFT(I67,3)&"."&MID(I67,4,3)&"/"&MID(I67,7,4)&"-"&MID(I67,11,2)),IF(X67="CNPJ",(LEFT(I67,2)&"."&MID(I67,3,3)&"."&MID(I67,6,3)&"/"&MID(I67,9,4)&"-"&MID(I67,13,2)),IF(X67="CPF_Incompleto",("0"&LEFT(I67,2)&"."&MID(I67,3,3)&"."&MID(I67,6,3)&"-"&MID(I67,9,2)),(LEFT(I67,3)&"."&MID(I67,4,3)&"."&MID(I67,7,3)&"-"&MID(I67,10,2)))))) -> 92.309.194/0001-20 | Z67: =VLOOKUP(Y67,FORNECEDORES!$A$2:$G$9043,3,0) -> ANDRE L.A. ENDRES - ME | AA67: =VLOOKUP(Y67,FORNECEDORES!$A$2:$G$9041,7,0) -> endrestransportes@outlook.com
A68: CON:3522 | B68: 4417812015511030 | C68: 45848 | D68: 45848 | E68: ADT | F68: 297.74 | G68: EFETIVADA | H68: Denis Camillo Da Silva | I68: 96685697091 | J68: IQM9933 | K68: 101432253 | L68: SP | M68: 145050 | N68: 264790 | O68: 3522 | P68: RS | Q68: RS | R68: Finalizado | S68: Finalizada | T68: EFETIVADA | U68: Quinta feira | V68: Quinta feira | W68: =LEN(I68) -> 11 | X68: =IF(W68=14,"CNPJ",IF(W68=12,"CNPJ_INCOMPLETO_2",IF(W68=13,"CNPJ_INCOMPLETO_1",IF(W68=10,"CPF_Incompleto","CPF")))) -> CPF | Y68: =IF(X68="CNPJ_INCOMPLETO_1",("0"&LEFT(I68,1)&"."&MID(I68,2,3)&"."&MID(I68,5,3)&"/"&MID(I68,8,4)&"-"&MID(I68,12,2)),IF(X68="CNPJ_INCOMPLETO_2",("00."&LEFT(I68,3)&"."&MID(I68,4,3)&"/"&MID(I68,7,4)&"-"&MID(I68,11,2)),IF(X68="CNPJ",(LEFT(I68,2)&"."&MID(I68,3,3)&"."&MID(I68,6,3)&"/"&MID(I68,9,4)&"-"&MID(I68,13,2)),IF(X68="CPF_Incompleto",("0"&LEFT(I68,2)&"."&MID(I68,3,3)&"."&MID(I68,6,3)&"-"&MID(I68,9,2)),(LEFT(I68,3)&"."&MID(I68,4,3)&"."&MID(I68,7,3)&"-"&MID(I68,10,2)))))) -> 966.856.970-91 | Z68: =VLOOKUP(Y68,FORNECEDORES!$A$2:$G$9043,3,0) -> DENIS CAMILLO DA SILVA | AA68: =VLOOKUP(Y68,FORNECEDORES!$A$2:$G$9041,7,0) -> deniscamillo29@gmail.com;
A69: CON:3522 | B69: 4417812015511030 | C69: 45848 | D69: 45855 | E69: SDO | F69: 198.49 | G69: EFETIVADA | H69: Denis Camillo Da Silva | I69: 96685697091 | J69: IQM9933 | K69: 101432253 | L69: SP | M69: 145050 | N69: 264790 | O69: 3522 | P69: RS | Q69: RS | R69: Finalizado | S69: Finalizada | T69: EFETIVADA | U69: Quinta feira | V69: Quinta feira | W69: =LEN(I69) -> 11 | X69: =IF(W69=14,"CNPJ",IF(W69=12,"CNPJ_INCOMPLETO_2",IF(W69=13,"CNPJ_INCOMPLETO_1",IF(W69=10,"CPF_Incompleto","CPF")))) -> CPF | Y69: =IF(X69="CNPJ_INCOMPLETO_1",("0"&LEFT(I69,1)&"."&MID(I69,2,3)&"."&MID(I69,5,3)&"/"&MID(I69,8,4)&"-"&MID(I69,12,2)),IF(X69="CNPJ_INCOMPLETO_2",("00."&LEFT(I69,3)&"."&MID(I69,4,3)&"/"&MID(I69,7,4)&"-"&MID(I69,11,2)),IF(X69="CNPJ",(LEFT(I69,2)&"."&MID(I69,3,3)&"."&MID(I69,6,3)&"/"&MID(I69,9,4)&"-"&MID(I69,13,2)),IF(X69="CPF_Incompleto",("0"&LEFT(I69,2)&"."&MID(I69,3,3)&"."&MID(I69,6,3)&"-"&MID(I69,9,2)),(LEFT(I69,3)&"."&MID(I69,4,3)&"."&MID(I69,7,3)&"-"&MID(I69,10,2)))))) -> 966.856.970-91 | Z69: =VLOOKUP(Y69,FORNECEDORES!$A$2:$G$9043,3,0) -> DENIS CAMILLO DA SILVA | AA69: =VLOOKUP(Y69,FORNECEDORES!$A$2:$G$9041,7,0) -> deniscamillo29@gmail.com;
A70: CON:3521 | B70: 4417812014686304 | C70: 45848 | D70: 45848 | E70: ADT | F70: 1740 | G70: EFETIVADA | H70: SILVERIO DA SILVEIRA | I70: 17250059000130 | J70: ATL5J69 | K70: 101432255 | L70: SP | M70: 145051 | N70: 264791 | O70: 3521 | P70: RS | Q70: RS | R70: Finalizado | S70: Finalizada | T70: EFETIVADA | U70: Quinta feira | V70: Quinta feira | W70: =LEN(I70) -> 14 | X70: =IF(W70=14,"CNPJ",IF(W70=12,"CNPJ_INCOMPLETO_2",IF(W70=13,"CNPJ_INCOMPLETO_1",IF(W70=10,"CPF_Incompleto","CPF")))) -> CNPJ | Y70: =IF(X70="CNPJ_INCOMPLETO_1",("0"&LEFT(I70,1)&"."&MID(I70,2,3)&"."&MID(I70,5,3)&"/"&MID(I70,8,4)&"-"&MID(I70,12,2)),IF(X70="CNPJ_INCOMPLETO_2",("00."&LEFT(I70,3)&"."&MID(I70,4,3)&"/"&MID(I70,7,4)&"-"&MID(I70,11,2)),IF(X70="CNPJ",(LEFT(I70,2)&"."&MID(I70,3,3)&"."&MID(I70,6,3)&"/"&MID(I70,9,4)&"-"&MID(I70,13,2)),IF(X70="CPF_Incompleto",("0"&LEFT(I70,2)&"."&MID(I70,3,3)&"."&MID(I70,6,3)&"-"&MID(I70,9,2)),(LEFT(I70,3)&"."&MID(I70,4,3)&"."&MID(I70,7,3)&"-"&MID(I70,10,2)))))) -> 17.250.059/0001-30 | Z70: =VLOOKUP(Y70,FORNECEDORES!$A$2:$G$9043,3,0) -> SILVERIO DA SILVEIRA ME | AA70: =VLOOKUP(Y70,FORNECEDORES!$A$2:$G$9041,7,0) -> silveriosilveira86@hotmail.com;
A71: CON:3521 | B71: 4417812014686304 | C71: 45848 | D71: 45855 | E71: SDO | F71: 1160 | G71: EFETIVADA | H71: SILVERIO DA SILVEIRA | I71: 17250059000130 | J71: ATL5J69 | K71: 101432255 | L71: SP | M71: 145051 | N71: 264791 | O71: 3521 | P71: RS | Q71: RS | R71: Finalizado | S71: Finalizada | T71: EFETIVADA | U71: Quinta feira | V71: Quinta feira | W71: =LEN(I71) -> 14 | X71: =IF(W71=14,"CNPJ",IF(W71=12,"CNPJ_INCOMPLETO_2",IF(W71=13,"CNPJ_INCOMPLETO_1",IF(W71=10,"CPF_Incompleto","CPF")))) -> CNPJ | Y71: =IF(X71="CNPJ_INCOMPLETO_1",("0"&LEFT(I71,1)&"."&MID(I71,2,3)&"."&MID(I71,5,3)&"/"&MID(I71,8,4)&"-"&MID(I71,12,2)),IF(X71="CNPJ_INCOMPLETO_2",("00."&LEFT(I71,3)&"."&MID(I71,4,3)&"/"&MID(I71,7,4)&"-"&MID(I71,11,2)),IF(X71="CNPJ",(LEFT(I71,2)&"."&MID(I71,3,3)&"."&MID(I71,6,3)&"/"&MID(I71,9,4)&"-"&MID(I71,13,2)),IF(X71="CPF_Incompleto",("0"&LEFT(I71,2)&"."&MID(I71,3,3)&"."&MID(I71,6,3)&"-"&MID(I71,9,2)),(LEFT(I71,3)&"."&MID(I71,4,3)&"."&MID(I71,7,3)&"-"&MID(I71,10,2)))))) -> 17.250.059/0001-30 | Z71: =VLOOKUP(Y71,FORNECEDORES!$A$2:$G$9043,3,0) -> SILVERIO DA SILVEIRA ME | AA71: =VLOOKUP(Y71,FORNECEDORES!$A$2:$G$9041,7,0) -> silveriosilveira86@hotmail.com;
A72: CON:3525 | B72: 4417812013265605 | C72: 45849 | D72: 45849 | E72: ADT | F72: 1050.84 | G72: EFETIVADA | H72: VANDERLI DASSOLER | I72: 58751050030 | J72: MKS4A50 | K72: 101470232 | L72: SP | M72: 145129 | N72: 264923 | O72: 3525 | P72: RS | Q72: RS | R72: Finalizado | S72: Finalizada | T72: EFETIVADA | U72: Quinta feira | V72: Quinta feira | W72: =LEN(I72) -> 11 | X72: =IF(W72=14,"CNPJ",IF(W72=12,"CNPJ_INCOMPLETO_2",IF(W72=13,"CNPJ_INCOMPLETO_1",IF(W72=10,"CPF_Incompleto","CPF")))) -> CPF | Y72: =IF(X72="CNPJ_INCOMPLETO_1",("0"&LEFT(I72,1)&"."&MID(I72,2,3)&"."&MID(I72,5,3)&"/"&MID(I72,8,4)&"-"&MID(I72,12,2)),IF(X72="CNPJ_INCOMPLETO_2",("00."&LEFT(I72,3)&"."&MID(I72,4,3)&"/"&MID(I72,7,4)&"-"&MID(I72,11,2)),IF(X72="CNPJ",(LEFT(I72,2)&"."&MID(I72,3,3)&"."&MID(I72,6,3)&"/"&MID(I72,9,4)&"-"&MID(I72,13,2)),IF(X72="CPF_Incompleto",("0"&LEFT(I72,2)&"."&MID(I72,3,3)&"."&MID(I72,6,3)&"-"&MID(I72,9,2)),(LEFT(I72,3)&"."&MID(I72,4,3)&"."&MID(I72,7,3)&"-"&MID(I72,10,2)))))) -> 587.510.500-30 | Z72: =VLOOKUP(Y72,FORNECEDORES!$A$2:$G$9043,3,0) -> VANDERLI DASSOLER | AA72: =VLOOKUP(Y72,FORNECEDORES!$A$2:$G$9041,7,0) -> vanderliegv@gmail.com;
A73: CON:3525 | B73: 4417812013265605 | C73: 45849 | D73: 45855 | E73: SDO | F73: 700.56 | G73: EFETIVADA | H73: VANDERLI DASSOLER | I73: 58751050030 | J73: MKS4A50 | K73: 101470232 | L73: SP | M73: 145129 | N73: 264923 | O73: 3525 | P73: RS | Q73: RS | R73: Finalizado | S73: Finalizada | T73: EFETIVADA | U73: Quinta feira | V73: Quinta feira | W73: =LEN(I73) -> 11 | X73: =IF(W73=14,"CNPJ",IF(W73=12,"CNPJ_INCOMPLETO_2",IF(W73=13,"CNPJ_INCOMPLETO_1",IF(W73=10,"CPF_Incompleto","CPF")))) -> CPF | Y73: =IF(X73="CNPJ_INCOMPLETO_1",("0"&LEFT(I73,1)&"."&MID(I73,2,3)&"."&MID(I73,5,3)&"/"&MID(I73,8,4)&"-"&MID(I73,12,2)),IF(X73="CNPJ_INCOMPLETO_2",("00."&LEFT(I73,3)&"."&MID(I73,4,3)&"/"&MID(I73,7,4)&"-"&MID(I73,11,2)),IF(X73="CNPJ",(LEFT(I73,2)&"."&MID(I73,3,3)&"."&MID(I73,6,3)&"/"&MID(I73,9,4)&"-"&MID(I73,13,2)),IF(X73="CPF_Incompleto",("0"&LEFT(I73,2)&"."&MID(I73,3,3)&"."&MID(I73,6,3)&"-"&MID(I73,9,2)),(LEFT(I73,3)&"."&MID(I73,4,3)&"."&MID(I73,7,3)&"-"&MID(I73,10,2)))))) -> 587.510.500-30 | Z73: =VLOOKUP(Y73,FORNECEDORES!$A$2:$G$9043,3,0) -> VANDERLI DASSOLER | AA73: =VLOOKUP(Y73,FORNECEDORES!$A$2:$G$9041,7,0) -> vanderliegv@gmail.com;
A74: CON:3527 | B74: 4417812022858440 | C74: 45850 | D74: 45852 | E74: ADT | F74: 1693.02 | G74: EFETIVADA | H74: JOSE DAGOBERTO MACHADO | I74: 40573680000 | J74: IKV8F25 | K74: 101498589 | L74: SP | M74: 145181 | N74: 265007 | O74: 3527 | P74: RS | Q74: RS | R74: Finalizado | S74: Finalizada | T74: EFETIVADA | U74: Quinta feira | V74: Quinta feira | W74: =LEN(I74) -> 11 | X74: =IF(W74=14,"CNPJ",IF(W74=12,"CNPJ_INCOMPLETO_2",IF(W74=13,"CNPJ_INCOMPLETO_1",IF(W74=10,"CPF_Incompleto","CPF")))) -> CPF | Y74: =IF(X74="CNPJ_INCOMPLETO_1",("0"&LEFT(I74,1)&"."&MID(I74,2,3)&"."&MID(I74,5,3)&"/"&MID(I74,8,4)&"-"&MID(I74,12,2)),IF(X74="CNPJ_INCOMPLETO_2",("00."&LEFT(I74,3)&"."&MID(I74,4,3)&"/"&MID(I74,7,4)&"-"&MID(I74,11,2)),IF(X74="CNPJ",(LEFT(I74,2)&"."&MID(I74,3,3)&"."&MID(I74,6,3)&"/"&MID(I74,9,4)&"-"&MID(I74,13,2)),IF(X74="CPF_Incompleto",("0"&LEFT(I74,2)&"."&MID(I74,3,3)&"."&MID(I74,6,3)&"-"&MID(I74,9,2)),(LEFT(I74,3)&"."&MID(I74,4,3)&"."&MID(I74,7,3)&"-"&MID(I74,10,2)))))) -> 405.736.800-00 | Z74: =VLOOKUP(Y74,FORNECEDORES!$A$2:$G$9043,3,0) -> JOSÉ DAGOBERTO MACHADO | AA74: =VLOOKUP(Y74,FORNECEDORES!$A$2:$G$9041,7,0) -> jdmdago@gmail.com;
A75: CON:3527 | B75: 4417812022858440 | C75: 45850 | D75: 45855 | E75: SDO | F75: 1128.68 | G75: EFETIVADA | H75: JOSE DAGOBERTO MACHADO | I75: 40573680000 | J75: IKV8F25 | K75: 101498589 | L75: SP | M75: 145181 | N75: 265007 | O75: 3527 | P75: RS | Q75: RS | R75: Finalizado | S75: Finalizada | T75: EFETIVADA | U75: Quinta feira | V75: Quinta feira | W75: =LEN(I75) -> 11 | X75: =IF(W75=14,"CNPJ",IF(W75=12,"CNPJ_INCOMPLETO_2",IF(W75=13,"CNPJ_INCOMPLETO_1",IF(W75=10,"CPF_Incompleto","CPF")))) -> CPF | Y75: =IF(X75="CNPJ_INCOMPLETO_1",("0"&LEFT(I75,1)&"."&MID(I75,2,3)&"."&MID(I75,5,3)&"/"&MID(I75,8,4)&"-"&MID(I75,12,2)),IF(X75="CNPJ_INCOMPLETO_2",("00."&LEFT(I75,3)&"."&MID(I75,4,3)&"/"&MID(I75,7,4)&"-"&MID(I75,11,2)),IF(X75="CNPJ",(LEFT(I75,2)&"."&MID(I75,3,3)&"."&MID(I75,6,3)&"/"&MID(I75,9,4)&"-"&MID(I75,13,2)),IF(X75="CPF_Incompleto",("0"&LEFT(I75,2)&"."&MID(I75,3,3)&"."&MID(I75,6,3)&"-"&MID(I75,9,2)),(LEFT(I75,3)&"."&MID(I75,4,3)&"."&MID(I75,7,3)&"-"&MID(I75,10,2)))))) -> 405.736.800-00 | Z75: =VLOOKUP(Y75,FORNECEDORES!$A$2:$G$9043,3,0) -> JOSÉ DAGOBERTO MACHADO | AA75: =VLOOKUP(Y75,FORNECEDORES!$A$2:$G$9041,7,0) -> jdmdago@gmail.com;
A76: CON:3528 | B76: 4417812010875943 | C76: 45850 | D76: 45880 | E76: DES | F76: 2700 | G76: EFETIVADA | H76: ANDRE L.A. ENDRES - ME | I76: 92309194000120 | J76: AFK2804 | K76: 101502872 | L76: SP | M76: 145188 | N76: 265015 | O76: 3528 | P76: RS | Q76: RS | R76: Finalizado | S76: Finalizada | T76: EFETIVADA | U76: 30 | V76: 45889 | W76: =LEN(I76) -> 14 | X76: =IF(W76=14,"CNPJ",IF(W76=12,"CNPJ_INCOMPLETO_2",IF(W76=13,"CNPJ_INCOMPLETO_1",IF(W76=10,"CPF_Incompleto","CPF")))) -> CNPJ | Y76: =IF(X76="CNPJ_INCOMPLETO_1",("0"&LEFT(I76,1)&"."&MID(I76,2,3)&"."&MID(I76,5,3)&"/"&MID(I76,8,4)&"-"&MID(I76,12,2)),IF(X76="CNPJ_INCOMPLETO_2",("00."&LEFT(I76,3)&"."&MID(I76,4,3)&"/"&MID(I76,7,4)&"-"&MID(I76,11,2)),IF(X76="CNPJ",(LEFT(I76,2)&"."&MID(I76,3,3)&"."&MID(I76,6,3)&"/"&MID(I76,9,4)&"-"&MID(I76,13,2)),IF(X76="CPF_Incompleto",("0"&LEFT(I76,2)&"."&MID(I76,3,3)&"."&MID(I76,6,3)&"-"&MID(I76,9,2)),(LEFT(I76,3)&"."&MID(I76,4,3)&"."&MID(I76,7,3)&"-"&MID(I76,10,2)))))) -> 92.309.194/0001-20 | Z76: =VLOOKUP(Y76,FORNECEDORES!$A$2:$G$9043,3,0) -> ANDRE L.A. ENDRES - ME | AA76: =VLOOKUP(Y76,FORNECEDORES!$A$2:$G$9041,7,0) -> endrestransportes@outlook.com
A77: CON:3531 | B77: 4417812013265605 | C77: 45852 | D77: 45853 | E77: ADT | F77: 1050.84 | G77: EFETIVADA | H77: VANDERLI DASSOLER | I77: 58751050030 | J77: MKS4A50 | K77: 101549350 | L77: SP | M77: 145281 | N77: 265221 | O77: 3531 | P77: RS | Q77: RS | R77: Aprovado | S77: Em Transporte | T77: EFETIVADA | U77: Quinta feira | V77: Quinta feira | W77: =LEN(I77) -> 11 | X77: =IF(W77=14,"CNPJ",IF(W77=12,"CNPJ_INCOMPLETO_2",IF(W77=13,"CNPJ_INCOMPLETO_1",IF(W77=10,"CPF_Incompleto","CPF")))) -> CPF | Y77: =IF(X77="CNPJ_INCOMPLETO_1",("0"&LEFT(I77,1)&"."&MID(I77,2,3)&"."&MID(I77,5,3)&"/"&MID(I77,8,4)&"-"&MID(I77,12,2)),IF(X77="CNPJ_INCOMPLETO_2",("00."&LEFT(I77,3)&"."&MID(I77,4,3)&"/"&MID(I77,7,4)&"-"&MID(I77,11,2)),IF(X77="CNPJ",(LEFT(I77,2)&"."&MID(I77,3,3)&"."&MID(I77,6,3)&"/"&MID(I77,9,4)&"-"&MID(I77,13,2)),IF(X77="CPF_Incompleto",("0"&LEFT(I77,2)&"."&MID(I77,3,3)&"."&MID(I77,6,3)&"-"&MID(I77,9,2)),(LEFT(I77,3)&"."&MID(I77,4,3)&"."&MID(I77,7,3)&"-"&MID(I77,10,2)))))) -> 587.510.500-30 | Z77: =VLOOKUP(Y77,FORNECEDORES!$A$2:$G$9043,3,0) -> VANDERLI DASSOLER | AA77: =VLOOKUP(Y77,FORNECEDORES!$A$2:$G$9041,7,0) -> vanderliegv@gmail.com;
A78: CON:3531 | B78: 4417812013265605 | C78: 45852 | D78: 45855 | E78: SDO | F78: 700.56 | G78: EFETIVADA | H78: VANDERLI DASSOLER | I78: 58751050030 | J78: MKS4A50 | K78: 101549350 | L78: SP | M78: 145281 | N78: 265221 | O78: 3531 | P78: RS | Q78: RS | R78: Aprovado | S78: Em Transporte | T78: EFETIVADA | U78: Quinta feira | V78: Quinta feira | W78: =LEN(I78) -> 11 | X78: =IF(W78=14,"CNPJ",IF(W78=12,"CNPJ_INCOMPLETO_2",IF(W78=13,"CNPJ_INCOMPLETO_1",IF(W78=10,"CPF_Incompleto","CPF")))) -> CPF | Y78: =IF(X78="CNPJ_INCOMPLETO_1",("0"&LEFT(I78,1)&"."&MID(I78,2,3)&"."&MID(I78,5,3)&"/"&MID(I78,8,4)&"-"&MID(I78,12,2)),IF(X78="CNPJ_INCOMPLETO_2",("00."&LEFT(I78,3)&"."&MID(I78,4,3)&"/"&MID(I78,7,4)&"-"&MID(I78,11,2)),IF(X78="CNPJ",(LEFT(I78,2)&"."&MID(I78,3,3)&"."&MID(I78,6,3)&"/"&MID(I78,9,4)&"-"&MID(I78,13,2)),IF(X78="CPF_Incompleto",("0"&LEFT(I78,2)&"."&MID(I78,3,3)&"."&MID(I78,6,3)&"-"&MID(I78,9,2)),(LEFT(I78,3)&"."&MID(I78,4,3)&"."&MID(I78,7,3)&"-"&MID(I78,10,2)))))) -> 587.510.500-30 | Z78: =VLOOKUP(Y78,FORNECEDORES!$A$2:$G$9043,3,0) -> VANDERLI DASSOLER | AA78: =VLOOKUP(Y78,FORNECEDORES!$A$2:$G$9041,7,0) -> vanderliegv@gmail.com;
A79: CON:3530 | B79: 4417812015511030 | C79: 45852 | D79: 45853 | E79: ADT | F79: 817.32 | G79: EFETIVADA | H79: Denis Camillo Da Silva | I79: 96685697091 | J79: IQM9933 | K79: 101549364 | L79: SP | M79: 145282 | N79: 265222 | O79: 3530 | P79: RS | Q79: RS | R79: Finalizado | S79: Finalizada | T79: EFETIVADA | U79: Quinta feira | V79: Quinta feira | W79: =LEN(I79) -> 11 | X79: =IF(W79=14,"CNPJ",IF(W79=12,"CNPJ_INCOMPLETO_2",IF(W79=13,"CNPJ_INCOMPLETO_1",IF(W79=10,"CPF_Incompleto","CPF")))) -> CPF | Y79: =IF(X79="CNPJ_INCOMPLETO_1",("0"&LEFT(I79,1)&"."&MID(I79,2,3)&"."&MID(I79,5,3)&"/"&MID(I79,8,4)&"-"&MID(I79,12,2)),IF(X79="CNPJ_INCOMPLETO_2",("00."&LEFT(I79,3)&"."&MID(I79,4,3)&"/"&MID(I79,7,4)&"-"&MID(I79,11,2)),IF(X79="CNPJ",(LEFT(I79,2)&"."&MID(I79,3,3)&"."&MID(I79,6,3)&"/"&MID(I79,9,4)&"-"&MID(I79,13,2)),IF(X79="CPF_Incompleto",("0"&LEFT(I79,2)&"."&MID(I79,3,3)&"."&MID(I79,6,3)&"-"&MID(I79,9,2)),(LEFT(I79,3)&"."&MID(I79,4,3)&"."&MID(I79,7,3)&"-"&MID(I79,10,2)))))) -> 966.856.970-91 | Z79: =VLOOKUP(Y79,FORNECEDORES!$A$2:$G$9043,3,0) -> DENIS CAMILLO DA SILVA | AA79: =VLOOKUP(Y79,FORNECEDORES!$A$2:$G$9041,7,0) -> deniscamillo29@gmail.com;
A80: CON:3530 | B80: 4417812015511030 | C80: 45852 | D80: 45855 | E80: SDO | F80: 544.88 | G80: EFETIVADA | H80: Denis Camillo Da Silva | I80: 96685697091 | J80: IQM9933 | K80: 101549364 | L80: SP | M80: 145282 | N80: 265222 | O80: 3530 | P80: RS | Q80: RS | R80: Finalizado | S80: Finalizada | T80: EFETIVADA | U80: Quinta feira | V80: Quinta feira | W80: =LEN(I80) -> 11 | X80: =IF(W80=14,"CNPJ",IF(W80=12,"CNPJ_INCOMPLETO_2",IF(W80=13,"CNPJ_INCOMPLETO_1",IF(W80=10,"CPF_Incompleto","CPF")))) -> CPF | Y80: =IF(X80="CNPJ_INCOMPLETO_1",("0"&LEFT(I80,1)&"."&MID(I80,2,3)&"."&MID(I80,5,3)&"/"&MID(I80,8,4)&"-"&MID(I80,12,2)),IF(X80="CNPJ_INCOMPLETO_2",("00."&LEFT(I80,3)&"."&MID(I80,4,3)&"/"&MID(I80,7,4)&"-"&MID(I80,11,2)),IF(X80="CNPJ",(LEFT(I80,2)&"."&MID(I80,3,3)&"."&MID(I80,6,3)&"/"&MID(I80,9,4)&"-"&MID(I80,13,2)),IF(X80="CPF_Incompleto",("0"&LEFT(I80,2)&"."&MID(I80,3,3)&"."&MID(I80,6,3)&"-"&MID(I80,9,2)),(LEFT(I80,3)&"."&MID(I80,4,3)&"."&MID(I80,7,3)&"-"&MID(I80,10,2)))))) -> 966.856.970-91 | Z80: =VLOOKUP(Y80,FORNECEDORES!$A$2:$G$9043,3,0) -> DENIS CAMILLO DA SILVA | AA80: =VLOOKUP(Y80,FORNECEDORES!$A$2:$G$9041,7,0) -> deniscamillo29@gmail.com;
A81: CON:3532 | B81: 4417812013265605 | C81: 45853 | D81: 45853 | E81: ADT | F81: 1050.84 | G81: EFETIVADA | H81: VANDERLI DASSOLER | I81: 58751050030 | J81: MKS4A50 | K81: 101557831 | L81: SP | M81: 145296 | N81: 265259 | O81: 3532, 3533 | P81: RS | Q81: RS | R81: Finalizado | S81: Finalizada | T81: EFETIVADA | U81: Quinta feira | V81: Quinta feira | W81: =LEN(I81) -> 11 | X81: =IF(W81=14,"CNPJ",IF(W81=12,"CNPJ_INCOMPLETO_2",IF(W81=13,"CNPJ_INCOMPLETO_1",IF(W81=10,"CPF_Incompleto","CPF")))) -> CPF | Y81: =IF(X81="CNPJ_INCOMPLETO_1",("0"&LEFT(I81,1)&"."&MID(I81,2,3)&"."&MID(I81,5,3)&"/"&MID(I81,8,4)&"-"&MID(I81,12,2)),IF(X81="CNPJ_INCOMPLETO_2",("00."&LEFT(I81,3)&"."&MID(I81,4,3)&"/"&MID(I81,7,4)&"-"&MID(I81,11,2)),IF(X81="CNPJ",(LEFT(I81,2)&"."&MID(I81,3,3)&"."&MID(I81,6,3)&"/"&MID(I81,9,4)&"-"&MID(I81,13,2)),IF(X81="CPF_Incompleto",("0"&LEFT(I81,2)&"."&MID(I81,3,3)&"."&MID(I81,6,3)&"-"&MID(I81,9,2)),(LEFT(I81,3)&"."&MID(I81,4,3)&"."&MID(I81,7,3)&"-"&MID(I81,10,2)))))) -> 587.510.500-30 | Z81: =VLOOKUP(Y81,FORNECEDORES!$A$2:$G$9043,3,0) -> VANDERLI DASSOLER | AA81: =VLOOKUP(Y81,FORNECEDORES!$A$2:$G$9041,7,0) -> vanderliegv@gmail.com;
A82: CON:3532 | B82: 4417812013265605 | C82: 45853 | D82: 45855 | E82: SDO | F82: 700.56 | G82: EFETIVADA | H82: VANDERLI DASSOLER | I82: 58751050030 | J82: MKS4A50 | K82: 101557831 | L82: SP | M82: 145296 | N82: 265259 | O82: 3532, 3533 | P82: RS | Q82: RS | R82: Finalizado | S82: Finalizada | T82: EFETIVADA | U82: Quinta feira | V82: Quinta feira | W82: =LEN(I82) -> 11 | X82: =IF(W82=14,"CNPJ",IF(W82=12,"CNPJ_INCOMPLETO_2",IF(W82=13,"CNPJ_INCOMPLETO_1",IF(W82=10,"CPF_Incompleto","CPF")))) -> CPF | Y82: =IF(X82="CNPJ_INCOMPLETO_1",("0"&LEFT(I82,1)&"."&MID(I82,2,3)&"."&MID(I82,5,3)&"/"&MID(I82,8,4)&"-"&MID(I82,12,2)),IF(X82="CNPJ_INCOMPLETO_2",("00."&LEFT(I82,3)&"."&MID(I82,4,3)&"/"&MID(I82,7,4)&"-"&MID(I82,11,2)),IF(X82="CNPJ",(LEFT(I82,2)&"."&MID(I82,3,3)&"."&MID(I82,6,3)&"/"&MID(I82,9,4)&"-"&MID(I82,13,2)),IF(X82="CPF_Incompleto",("0"&LEFT(I82,2)&"."&MID(I82,3,3)&"."&MID(I82,6,3)&"-"&MID(I82,9,2)),(LEFT(I82,3)&"."&MID(I82,4,3)&"."&MID(I82,7,3)&"-"&MID(I82,10,2)))))) -> 587.510.500-30 | Z82: =VLOOKUP(Y82,FORNECEDORES!$A$2:$G$9043,3,0) -> VANDERLI DASSOLER | AA82: =VLOOKUP(Y82,FORNECEDORES!$A$2:$G$9041,7,0) -> vanderliegv@gmail.com;
A83: CON:3523 | B83: 4417812014686304 | C83: 45853 | D83: 45853 | E83: ADT | F83: 522 | G83: EFETIVADA | H83: SILVERIO DA SILVEIRA | I83: 17250059000130 | J83: ATL5J69 | K83: 101564797 | L83: SP | M83: 145123 | N83: 264893 | O83: 3523 | P83: RS | Q83: RS | R83: Finalizado | S83: Finalizada | T83: EFETIVADA | U83: Quinta feira | V83: Quinta feira | W83: =LEN(I83) -> 14 | X83: =IF(W83=14,"CNPJ",IF(W83=12,"CNPJ_INCOMPLETO_2",IF(W83=13,"CNPJ_INCOMPLETO_1",IF(W83=10,"CPF_Incompleto","CPF")))) -> CNPJ | Y83: =IF(X83="CNPJ_INCOMPLETO_1",("0"&LEFT(I83,1)&"."&MID(I83,2,3)&"."&MID(I83,5,3)&"/"&MID(I83,8,4)&"-"&MID(I83,12,2)),IF(X83="CNPJ_INCOMPLETO_2",("00."&LEFT(I83,3)&"."&MID(I83,4,3)&"/"&MID(I83,7,4)&"-"&MID(I83,11,2)),IF(X83="CNPJ",(LEFT(I83,2)&"."&MID(I83,3,3)&"."&MID(I83,6,3)&"/"&MID(I83,9,4)&"-"&MID(I83,13,2)),IF(X83="CPF_Incompleto",("0"&LEFT(I83,2)&"."&MID(I83,3,3)&"."&MID(I83,6,3)&"-"&MID(I83,9,2)),(LEFT(I83,3)&"."&MID(I83,4,3)&"."&MID(I83,7,3)&"-"&MID(I83,10,2)))))) -> 17.250.059/0001-30 | Z83: =VLOOKUP(Y83,FORNECEDORES!$A$2:$G$9043,3,0) -> SILVERIO DA SILVEIRA ME | AA83: =VLOOKUP(Y83,FORNECEDORES!$A$2:$G$9041,7,0) -> silveriosilveira86@hotmail.com;
A84: CON:3523 | B84: 4417812014686304 | C84: 45853 | D84: 45855 | E84: SDO | F84: 348 | G84: EFETIVADA | H84: SILVERIO DA SILVEIRA | I84: 17250059000130 | J84: ATL5J69 | K84: 101564797 | L84: SP | M84: 145123 | N84: 264893 | O84: 3523 | P84: RS | Q84: RS | R84: Finalizado | S84: Finalizada | T84: EFETIVADA | U84: Quinta feira | V84: Quinta feira | W84: =LEN(I84) -> 14 | X84: =IF(W84=14,"CNPJ",IF(W84=12,"CNPJ_INCOMPLETO_2",IF(W84=13,"CNPJ_INCOMPLETO_1",IF(W84=10,"CPF_Incompleto","CPF")))) -> CNPJ | Y84: =IF(X84="CNPJ_INCOMPLETO_1",("0"&LEFT(I84,1)&"."&MID(I84,2,3)&"."&MID(I84,5,3)&"/"&MID(I84,8,4)&"-"&MID(I84,12,2)),IF(X84="CNPJ_INCOMPLETO_2",("00."&LEFT(I84,3)&"."&MID(I84,4,3)&"/"&MID(I84,7,4)&"-"&MID(I84,11,2)),IF(X84="CNPJ",(LEFT(I84,2)&"."&MID(I84,3,3)&"."&MID(I84,6,3)&"/"&MID(I84,9,4)&"-"&MID(I84,13,2)),IF(X84="CPF_Incompleto",("0"&LEFT(I84,2)&"."&MID(I84,3,3)&"."&MID(I84,6,3)&"-"&MID(I84,9,2)),(LEFT(I84,3)&"."&MID(I84,4,3)&"."&MID(I84,7,3)&"-"&MID(I84,10,2)))))) -> 17.250.059/0001-30 | Z84: =VLOOKUP(Y84,FORNECEDORES!$A$2:$G$9043,3,0) -> SILVERIO DA SILVEIRA ME | AA84: =VLOOKUP(Y84,FORNECEDORES!$A$2:$G$9041,7,0) -> silveriosilveira86@hotmail.com;
A85: CON:3535 | B85: 4417812022858440 | C85: 45853 | D85: 45853 | E85: ADT | F85: 1693.02 | G85: EFETIVADA | H85: JOSE DAGOBERTO MACHADO | I85: 40573680000 | J85: IKV8F25 | K85: 101580973 | L85: SP | M85: 145331 | N85: 265369 | O85: 3535 | P85: RS | Q85: RS | R85: Finalizado | S85: Finalizada | T85: EFETIVADA | U85: Quinta feira | V85: Quinta feira | W85: =LEN(I85) -> 11 | X85: =IF(W85=14,"CNPJ",IF(W85=12,"CNPJ_INCOMPLETO_2",IF(W85=13,"CNPJ_INCOMPLETO_1",IF(W85=10,"CPF_Incompleto","CPF")))) -> CPF | Y85: =IF(X85="CNPJ_INCOMPLETO_1",("0"&LEFT(I85,1)&"."&MID(I85,2,3)&"."&MID(I85,5,3)&"/"&MID(I85,8,4)&"-"&MID(I85,12,2)),IF(X85="CNPJ_INCOMPLETO_2",("00."&LEFT(I85,3)&"."&MID(I85,4,3)&"/"&MID(I85,7,4)&"-"&MID(I85,11,2)),IF(X85="CNPJ",(LEFT(I85,2)&"."&MID(I85,3,3)&"."&MID(I85,6,3)&"/"&MID(I85,9,4)&"-"&MID(I85,13,2)),IF(X85="CPF_Incompleto",("0"&LEFT(I85,2)&"."&MID(I85,3,3)&"."&MID(I85,6,3)&"-"&MID(I85,9,2)),(LEFT(I85,3)&"."&MID(I85,4,3)&"."&MID(I85,7,3)&"-"&MID(I85,10,2)))))) -> 405.736.800-00 | Z85: =VLOOKUP(Y85,FORNECEDORES!$A$2:$G$9043,3,0) -> JOSÉ DAGOBERTO MACHADO | AA85: =VLOOKUP(Y85,FORNECEDORES!$A$2:$G$9041,7,0) -> jdmdago@gmail.com;
A86: CON:3535 | B86: 4417812022858440 | C86: 45853 | D86: 45855 | E86: SDO | F86: 1128.68 | G86: EFETIVADA | H86: JOSE DAGOBERTO MACHADO | I86: 40573680000 | J86: IKV8F25 | K86: 101580973 | L86: SP | M86: 145331 | N86: 265369 | O86: 3535 | P86: RS | Q86: RS | R86: Finalizado | S86: Finalizada | T86: EFETIVADA | U86: Quinta feira | V86: Quinta feira | W86: =LEN(I86) -> 11 | X86: =IF(W86=14,"CNPJ",IF(W86=12,"CNPJ_INCOMPLETO_2",IF(W86=13,"CNPJ_INCOMPLETO_1",IF(W86=10,"CPF_Incompleto","CPF")))) -> CPF | Y86: =IF(X86="CNPJ_INCOMPLETO_1",("0"&LEFT(I86,1)&"."&MID(I86,2,3)&"."&MID(I86,5,3)&"/"&MID(I86,8,4)&"-"&MID(I86,12,2)),IF(X86="CNPJ_INCOMPLETO_2",("00."&LEFT(I86,3)&"."&MID(I86,4,3)&"/"&MID(I86,7,4)&"-"&MID(I86,11,2)),IF(X86="CNPJ",(LEFT(I86,2)&"."&MID(I86,3,3)&"."&MID(I86,6,3)&"/"&MID(I86,9,4)&"-"&MID(I86,13,2)),IF(X86="CPF_Incompleto",("0"&LEFT(I86,2)&"."&MID(I86,3,3)&"."&MID(I86,6,3)&"-"&MID(I86,9,2)),(LEFT(I86,3)&"."&MID(I86,4,3)&"."&MID(I86,7,3)&"-"&MID(I86,10,2)))))) -> 405.736.800-00 | Z86: =VLOOKUP(Y86,FORNECEDORES!$A$2:$G$9043,3,0) -> JOSÉ DAGOBERTO MACHADO | AA86: =VLOOKUP(Y86,FORNECEDORES!$A$2:$G$9041,7,0) -> jdmdago@gmail.com;
A87: CON:3536 | B87: 4417812010875943 | C87: 45853 | D87: 45883 | E87: DES | F87: 1800 | G87: EFETIVADA | H87: ANDRE L.A. ENDRES - ME | I87: 92309194000120 | J87: AFK2804 | K87: 101589206 | L87: SP | M87: 145346 | N87: 265386 | O87: 3536 | P87: RS | Q87: RS | R87: Finalizado | S87: Finalizada | T87: EFETIVADA | U87: 30 | V87: 45889 | W87: =LEN(I87) -> 14 | X87: =IF(W87=14,"CNPJ",IF(W87=12,"CNPJ_INCOMPLETO_2",IF(W87=13,"CNPJ_INCOMPLETO_1",IF(W87=10,"CPF_Incompleto","CPF")))) -> CNPJ | Y87: =IF(X87="CNPJ_INCOMPLETO_1",("0"&LEFT(I87,1)&"."&MID(I87,2,3)&"."&MID(I87,5,3)&"/"&MID(I87,8,4)&"-"&MID(I87,12,2)),IF(X87="CNPJ_INCOMPLETO_2",("00."&LEFT(I87,3)&"."&MID(I87,4,3)&"/"&MID(I87,7,4)&"-"&MID(I87,11,2)),IF(X87="CNPJ",(LEFT(I87,2)&"."&MID(I87,3,3)&"."&MID(I87,6,3)&"/"&MID(I87,9,4)&"-"&MID(I87,13,2)),IF(X87="CPF_Incompleto",("0"&LEFT(I87,2)&"."&MID(I87,3,3)&"."&MID(I87,6,3)&"-"&MID(I87,9,2)),(LEFT(I87,3)&"."&MID(I87,4,3)&"."&MID(I87,7,3)&"-"&MID(I87,10,2)))))) -> 92.309.194/0001-20 | Z87: =VLOOKUP(Y87,FORNECEDORES!$A$2:$G$9043,3,0) -> ANDRE L.A. ENDRES - ME | AA87: =VLOOKUP(Y87,FORNECEDORES!$A$2:$G$9041,7,0) -> endrestransportes@outlook.com
A88: CON:3537 | B88: 4417812014686304 | C88: 45853 | D88: 45854 | E88: ADT | F88: 1140 | G88: EFETIVADA | H88: SILVERIO DA SILVEIRA | I88: 17250059000130 | J88: ATL5J69 | K88: 101590507 | L88: SP | M88: 145347 | N88: 265387 | O88: 3537 | P88: RS | Q88: RS | R88: Finalizado | S88: Finalizada | T88: EFETIVADA | U88: Quinta feira | V88: Quinta feira | W88: =LEN(I88) -> 14 | X88: =IF(W88=14,"CNPJ",IF(W88=12,"CNPJ_INCOMPLETO_2",IF(W88=13,"CNPJ_INCOMPLETO_1",IF(W88=10,"CPF_Incompleto","CPF")))) -> CNPJ | Y88: =IF(X88="CNPJ_INCOMPLETO_1",("0"&LEFT(I88,1)&"."&MID(I88,2,3)&"."&MID(I88,5,3)&"/"&MID(I88,8,4)&"-"&MID(I88,12,2)),IF(X88="CNPJ_INCOMPLETO_2",("00."&LEFT(I88,3)&"."&MID(I88,4,3)&"/"&MID(I88,7,4)&"-"&MID(I88,11,2)),IF(X88="CNPJ",(LEFT(I88,2)&"."&MID(I88,3,3)&"."&MID(I88,6,3)&"/"&MID(I88,9,4)&"-"&MID(I88,13,2)),IF(X88="CPF_Incompleto",("0"&LEFT(I88,2)&"."&MID(I88,3,3)&"."&MID(I88,6,3)&"-"&MID(I88,9,2)),(LEFT(I88,3)&"."&MID(I88,4,3)&"."&MID(I88,7,3)&"-"&MID(I88,10,2)))))) -> 17.250.059/0001-30 | Z88: =VLOOKUP(Y88,FORNECEDORES!$A$2:$G$9043,3,0) -> SILVERIO DA SILVEIRA ME | AA88: =VLOOKUP(Y88,FORNECEDORES!$A$2:$G$9041,7,0) -> silveriosilveira86@hotmail.com;
A89: CON:3537 | B89: 4417812014686304 | C89: 45853 | D89: 45855 | E89: SDO | F89: 760 | G89: EFETIVADA | H89: SILVERIO DA SILVEIRA | I89: 17250059000130 | J89: ATL5J69 | K89: 101590507 | L89: SP | M89: 145347 | N89: 265387 | O89: 3537 | P89: RS | Q89: RS | R89: Finalizado | S89: Finalizada | T89: EFETIVADA | U89: Quinta feira | V89: Quinta feira | W89: =LEN(I89) -> 14 | X89: =IF(W89=14,"CNPJ",IF(W89=12,"CNPJ_INCOMPLETO_2",IF(W89=13,"CNPJ_INCOMPLETO_1",IF(W89=10,"CPF_Incompleto","CPF")))) -> CNPJ | Y89: =IF(X89="CNPJ_INCOMPLETO_1",("0"&LEFT(I89,1)&"."&MID(I89,2,3)&"."&MID(I89,5,3)&"/"&MID(I89,8,4)&"-"&MID(I89,12,2)),IF(X89="CNPJ_INCOMPLETO_2",("00."&LEFT(I89,3)&"."&MID(I89,4,3)&"/"&MID(I89,7,4)&"-"&MID(I89,11,2)),IF(X89="CNPJ",(LEFT(I89,2)&"."&MID(I89,3,3)&"."&MID(I89,6,3)&"/"&MID(I89,9,4)&"-"&MID(I89,13,2)),IF(X89="CPF_Incompleto",("0"&LEFT(I89,2)&"."&MID(I89,3,3)&"."&MID(I89,6,3)&"-"&MID(I89,9,2)),(LEFT(I89,3)&"."&MID(I89,4,3)&"."&MID(I89,7,3)&"-"&MID(I89,10,2)))))) -> 17.250.059/0001-30 | Z89: =VLOOKUP(Y89,FORNECEDORES!$A$2:$G$9043,3,0) -> SILVERIO DA SILVEIRA ME | AA89: =VLOOKUP(Y89,FORNECEDORES!$A$2:$G$9041,7,0) -> silveriosilveira86@hotmail.com;
A90: CON:3540 | B90: 4417812014686304 | C90: 45854 | D90: 45855 | E90: ADT | F90: 342 | G90: EFETIVADA | H90: SILVERIO DA SILVEIRA | I90: 17250059000130 | J90: ATL5J69 | K90: 101615990 | L90: SP | M90: 145385 | N90: 265480 | O90: 3540 | P90: RS | Q90: RS | R90: Finalizado | S90: Finalizada | T90: EFETIVADA | U90: Quinta feira | V90: Quinta feira | W90: =LEN(I90) -> 14 | X90: =IF(W90=14,"CNPJ",IF(W90=12,"CNPJ_INCOMPLETO_2",IF(W90=13,"CNPJ_INCOMPLETO_1",IF(W90=10,"CPF_Incompleto","CPF")))) -> CNPJ | Y90: =IF(X90="CNPJ_INCOMPLETO_1",("0"&LEFT(I90,1)&"."&MID(I90,2,3)&"."&MID(I90,5,3)&"/"&MID(I90,8,4)&"-"&MID(I90,12,2)),IF(X90="CNPJ_INCOMPLETO_2",("00."&LEFT(I90,3)&"."&MID(I90,4,3)&"/"&MID(I90,7,4)&"-"&MID(I90,11,2)),IF(X90="CNPJ",(LEFT(I90,2)&"."&MID(I90,3,3)&"."&MID(I90,6,3)&"/"&MID(I90,9,4)&"-"&MID(I90,13,2)),IF(X90="CPF_Incompleto",("0"&LEFT(I90,2)&"."&MID(I90,3,3)&"."&MID(I90,6,3)&"-"&MID(I90,9,2)),(LEFT(I90,3)&"."&MID(I90,4,3)&"."&MID(I90,7,3)&"-"&MID(I90,10,2)))))) -> 17.250.059/0001-30 | Z90: =VLOOKUP(Y90,FORNECEDORES!$A$2:$G$9043,3,0) -> SILVERIO DA SILVEIRA ME | AA90: =VLOOKUP(Y90,FORNECEDORES!$A$2:$G$9041,7,0) -> silveriosilveira86@hotmail.com;
A91: CON:3540 | B91: 4417812014686304 | C91: 45854 | D91: 45855 | E91: SDO | F91: 228 | G91: EFETIVADA | H91: SILVERIO DA SILVEIRA | I91: 17250059000130 | J91: ATL5J69 | K91: 101615990 | L91: SP | M91: 145385 | N91: 265480 | O91: 3540 | P91: RS | Q91: RS | R91: Finalizado | S91: Finalizada | T91: EFETIVADA | U91: Quinta feira | V91: Quinta feira | W91: =LEN(I91) -> 14 | X91: =IF(W91=14,"CNPJ",IF(W91=12,"CNPJ_INCOMPLETO_2",IF(W91=13,"CNPJ_INCOMPLETO_1",IF(W91=10,"CPF_Incompleto","CPF")))) -> CNPJ | Y91: =IF(X91="CNPJ_INCOMPLETO_1",("0"&LEFT(I91,1)&"."&MID(I91,2,3)&"."&MID(I91,5,3)&"/"&MID(I91,8,4)&"-"&MID(I91,12,2)),IF(X91="CNPJ_INCOMPLETO_2",("00."&LEFT(I91,3)&"."&MID(I91,4,3)&"/"&MID(I91,7,4)&"-"&MID(I91,11,2)),IF(X91="CNPJ",(LEFT(I91,2)&"."&MID(I91,3,3)&"."&MID(I91,6,3)&"/"&MID(I91,9,4)&"-"&MID(I91,13,2)),IF(X91="CPF_Incompleto",("0"&LEFT(I91,2)&"."&MID(I91,3,3)&"."&MID(I91,6,3)&"-"&MID(I91,9,2)),(LEFT(I91,3)&"."&MID(I91,4,3)&"."&MID(I91,7,3)&"-"&MID(I91,10,2)))))) -> 17.250.059/0001-30 | Z91: =VLOOKUP(Y91,FORNECEDORES!$A$2:$G$9043,3,0) -> SILVERIO DA SILVEIRA ME | AA91: =VLOOKUP(Y91,FORNECEDORES!$A$2:$G$9041,7,0) -> silveriosilveira86@hotmail.com;
A92: CON:3542 | B92: 4417812013265605 | C92: 45854 | D92: 45855 | E92: ADT | F92: 1693.02 | G92: EFETIVADA | H92: VANDERLI DASSOLER | I92: 58751050030 | J92: MKS4A50 | K92: 101626400 | L92: SP | M92: 145394 | N92: 265508 | O92: 3542 | P92: RS | Q92: RS | R92: Finalizado | S92: Finalizada | T92: EFETIVADA | U92: Quinta feira | V92: Quinta feira | W92: =LEN(I92) -> 11 | X92: =IF(W92=14,"CNPJ",IF(W92=12,"CNPJ_INCOMPLETO_2",IF(W92=13,"CNPJ_INCOMPLETO_1",IF(W92=10,"CPF_Incompleto","CPF")))) -> CPF | Y92: =IF(X92="CNPJ_INCOMPLETO_1",("0"&LEFT(I92,1)&"."&MID(I92,2,3)&"."&MID(I92,5,3)&"/"&MID(I92,8,4)&"-"&MID(I92,12,2)),IF(X92="CNPJ_INCOMPLETO_2",("00."&LEFT(I92,3)&"."&MID(I92,4,3)&"/"&MID(I92,7,4)&"-"&MID(I92,11,2)),IF(X92="CNPJ",(LEFT(I92,2)&"."&MID(I92,3,3)&"."&MID(I92,6,3)&"/"&MID(I92,9,4)&"-"&MID(I92,13,2)),IF(X92="CPF_Incompleto",("0"&LEFT(I92,2)&"."&MID(I92,3,3)&"."&MID(I92,6,3)&"-"&MID(I92,9,2)),(LEFT(I92,3)&"."&MID(I92,4,3)&"."&MID(I92,7,3)&"-"&MID(I92,10,2)))))) -> 587.510.500-30 | Z92: =VLOOKUP(Y92,FORNECEDORES!$A$2:$G$9043,3,0) -> VANDERLI DASSOLER | AA92: =VLOOKUP(Y92,FORNECEDORES!$A$2:$G$9041,7,0) -> vanderliegv@gmail.com;
A93: CON:3542 | B93: 4417812013265605 | C93: 45854 | D93: 45855 | E93: SDO | F93: 1128.68 | G93: EFETIVADA | H93: VANDERLI DASSOLER | I93: 58751050030 | J93: MKS4A50 | K93: 101626400 | L93: SP | M93: 145394 | N93: 265508 | O93: 3542 | P93: RS | Q93: RS | R93: Finalizado | S93: Finalizada | T93: EFETIVADA | U93: Quinta feira | V93: Quinta feira | W93: =LEN(I93) -> 11 | X93: =IF(W93=14,"CNPJ",IF(W93=12,"CNPJ_INCOMPLETO_2",IF(W93=13,"CNPJ_INCOMPLETO_1",IF(W93=10,"CPF_Incompleto","CPF")))) -> CPF | Y93: =IF(X93="CNPJ_INCOMPLETO_1",("0"&LEFT(I93,1)&"."&MID(I93,2,3)&"."&MID(I93,5,3)&"/"&MID(I93,8,4)&"-"&MID(I93,12,2)),IF(X93="CNPJ_INCOMPLETO_2",("00."&LEFT(I93,3)&"."&MID(I93,4,3)&"/"&MID(I93,7,4)&"-"&MID(I93,11,2)),IF(X93="CNPJ",(LEFT(I93,2)&"."&MID(I93,3,3)&"."&MID(I93,6,3)&"/"&MID(I93,9,4)&"-"&MID(I93,13,2)),IF(X93="CPF_Incompleto",("0"&LEFT(I93,2)&"."&MID(I93,3,3)&"."&MID(I93,6,3)&"-"&MID(I93,9,2)),(LEFT(I93,3)&"."&MID(I93,4,3)&"."&MID(I93,7,3)&"-"&MID(I93,10,2)))))) -> 587.510.500-30 | Z93: =VLOOKUP(Y93,FORNECEDORES!$A$2:$G$9043,3,0) -> VANDERLI DASSOLER | AA93: =VLOOKUP(Y93,FORNECEDORES!$A$2:$G$9041,7,0) -> vanderliegv@gmail.com;
A94: CON:3544 | B94: 4417812013265605 | C94: 45855 | D94: 45855 | E94: ADT | F94: 507.91 | G94: EFETIVADA | H94: VANDERLI DASSOLER | I94: 58751050030 | J94: MKS4A50 | K94: 101649771 | L94: SP | M94: 145435 | N94: 265585 | O94: 3544 | P94: RS | Q94: RS | R94: Finalizado | S94: Finalizada | T94: #N/A | U94: Quinta feira | V94: Quinta feira | W94: =LEN(I94) -> 11 | X94: =IF(W94=14,"CNPJ",IF(W94=12,"CNPJ_INCOMPLETO_2",IF(W94=13,"CNPJ_INCOMPLETO_1",IF(W94=10,"CPF_Incompleto","CPF")))) -> CPF | Y94: =IF(X94="CNPJ_INCOMPLETO_1",("0"&LEFT(I94,1)&"."&MID(I94,2,3)&"."&MID(I94,5,3)&"/"&MID(I94,8,4)&"-"&MID(I94,12,2)),IF(X94="CNPJ_INCOMPLETO_2",("00."&LEFT(I94,3)&"."&MID(I94,4,3)&"/"&MID(I94,7,4)&"-"&MID(I94,11,2)),IF(X94="CNPJ",(LEFT(I94,2)&"."&MID(I94,3,3)&"."&MID(I94,6,3)&"/"&MID(I94,9,4)&"-"&MID(I94,13,2)),IF(X94="CPF_Incompleto",("0"&LEFT(I94,2)&"."&MID(I94,3,3)&"."&MID(I94,6,3)&"-"&MID(I94,9,2)),(LEFT(I94,3)&"."&MID(I94,4,3)&"."&MID(I94,7,3)&"-"&MID(I94,10,2)))))) -> 587.510.500-30 | Z94: =VLOOKUP(Y94,FORNECEDORES!$A$2:$G$9043,3,0) -> VANDERLI DASSOLER | AA94: =VLOOKUP(Y94,FORNECEDORES!$A$2:$G$9041,7,0) -> vanderliegv@gmail.com;
A95: CON:3544 | B95: 4417812013265605 | C95: 45855 | D95: 45862 | E95: SDO | F95: 338.6 | G95: EFETIVADA | H95: VANDERLI DASSOLER | I95: 58751050030 | J95: MKS4A50 | K95: 101649771 | L95: SP | M95: 145435 | N95: 265585 | O95: 3544 | P95: RS | Q95: RS | R95: Finalizado | S95: Finalizada | T95: #N/A | U95: Quinta feira | V95: Quinta feira | W95: =LEN(I95) -> 11 | X95: =IF(W95=14,"CNPJ",IF(W95=12,"CNPJ_INCOMPLETO_2",IF(W95=13,"CNPJ_INCOMPLETO_1",IF(W95=10,"CPF_Incompleto","CPF")))) -> CPF | Y95: =IF(X95="CNPJ_INCOMPLETO_1",("0"&LEFT(I95,1)&"."&MID(I95,2,3)&"."&MID(I95,5,3)&"/"&MID(I95,8,4)&"-"&MID(I95,12,2)),IF(X95="CNPJ_INCOMPLETO_2",("00."&LEFT(I95,3)&"."&MID(I95,4,3)&"/"&MID(I95,7,4)&"-"&MID(I95,11,2)),IF(X95="CNPJ",(LEFT(I95,2)&"."&MID(I95,3,3)&"."&MID(I95,6,3)&"/"&MID(I95,9,4)&"-"&MID(I95,13,2)),IF(X95="CPF_Incompleto",("0"&LEFT(I95,2)&"."&MID(I95,3,3)&"."&MID(I95,6,3)&"-"&MID(I95,9,2)),(LEFT(I95,3)&"."&MID(I95,4,3)&"."&MID(I95,7,3)&"-"&MID(I95,10,2)))))) -> 587.510.500-30 | Z95: =VLOOKUP(Y95,FORNECEDORES!$A$2:$G$9043,3,0) -> VANDERLI DASSOLER | AA95: =VLOOKUP(Y95,FORNECEDORES!$A$2:$G$9041,7,0) -> vanderliegv@gmail.com;
A96: CON:3546 | B96: 4417812015511030 | C96: 45855 | D96: 45855 | E96: ADT | F96: 992.46 | G96: EFETIVADA | H96: Denis Camillo Da Silva | I96: 96685697091 | J96: IQM9933 | K96: 101658065 | L96: SP | M96: 145462 | N96: 265621 | O96: 3546, 3547 | P96: RS | Q96: RS | R96: Finalizado | S96: Finalizada | T96: #N/A | U96: Quinta feira | V96: Quinta feira | W96: =LEN(I96) -> 11 | X96: =IF(W96=14,"CNPJ",IF(W96=12,"CNPJ_INCOMPLETO_2",IF(W96=13,"CNPJ_INCOMPLETO_1",IF(W96=10,"CPF_Incompleto","CPF")))) -> CPF | Y96: =IF(X96="CNPJ_INCOMPLETO_1",("0"&LEFT(I96,1)&"."&MID(I96,2,3)&"."&MID(I96,5,3)&"/"&MID(I96,8,4)&"-"&MID(I96,12,2)),IF(X96="CNPJ_INCOMPLETO_2",("00."&LEFT(I96,3)&"."&MID(I96,4,3)&"/"&MID(I96,7,4)&"-"&MID(I96,11,2)),IF(X96="CNPJ",(LEFT(I96,2)&"."&MID(I96,3,3)&"."&MID(I96,6,3)&"/"&MID(I96,9,4)&"-"&MID(I96,13,2)),IF(X96="CPF_Incompleto",("0"&LEFT(I96,2)&"."&MID(I96,3,3)&"."&MID(I96,6,3)&"-"&MID(I96,9,2)),(LEFT(I96,3)&"."&MID(I96,4,3)&"."&MID(I96,7,3)&"-"&MID(I96,10,2)))))) -> 966.856.970-91 | Z96: =VLOOKUP(Y96,FORNECEDORES!$A$2:$G$9043,3,0) -> DENIS CAMILLO DA SILVA | AA96: =VLOOKUP(Y96,FORNECEDORES!$A$2:$G$9041,7,0) -> deniscamillo29@gmail.com;
A97: CON:3546 | B97: 4417812015511030 | C97: 45855 | D97: 45862 | E97: SDO | F97: 661.64 | G97: EFETIVADA | H97: Denis Camillo Da Silva | I97: 96685697091 | J97: IQM9933 | K97: 101658065 | L97: SP | M97: 145462 | N97: 265621 | O97: 3546, 3547 | P97: RS | Q97: RS | R97: Finalizado | S97: Finalizada | T97: #N/A | U97: Quinta feira | V97: Quinta feira | W97: =LEN(I97) -> 11 | X97: =IF(W97=14,"CNPJ",IF(W97=12,"CNPJ_INCOMPLETO_2",IF(W97=13,"CNPJ_INCOMPLETO_1",IF(W97=10,"CPF_Incompleto","CPF")))) -> CPF | Y97: =IF(X97="CNPJ_INCOMPLETO_1",("0"&LEFT(I97,1)&"."&MID(I97,2,3)&"."&MID(I97,5,3)&"/"&MID(I97,8,4)&"-"&MID(I97,12,2)),IF(X97="CNPJ_INCOMPLETO_2",("00."&LEFT(I97,3)&"."&MID(I97,4,3)&"/"&MID(I97,7,4)&"-"&MID(I97,11,2)),IF(X97="CNPJ",(LEFT(I97,2)&"."&MID(I97,3,3)&"."&MID(I97,6,3)&"/"&MID(I97,9,4)&"-"&MID(I97,13,2)),IF(X97="CPF_Incompleto",("0"&LEFT(I97,2)&"."&MID(I97,3,3)&"."&MID(I97,6,3)&"-"&MID(I97,9,2)),(LEFT(I97,3)&"."&MID(I97,4,3)&"."&MID(I97,7,3)&"-"&MID(I97,10,2)))))) -> 966.856.970-91 | Z97: =VLOOKUP(Y97,FORNECEDORES!$A$2:$G$9043,3,0) -> DENIS CAMILLO DA SILVA | AA97: =VLOOKUP(Y97,FORNECEDORES!$A$2:$G$9041,7,0) -> deniscamillo29@gmail.com;
A98: CON:1687 | B98: 4417812022858440 | C98: 45855 | D98: 45855 | E98: ADT | F98: 507.91 | G98: EFETIVADA | H98: JOSE DAGOBERTO MACHADO | I98: 40573680000 | J98: IKV8F25 | K98: 101659721 | L98: SP | M98: 145453 | N98: 265590 | O98: 1687 | P98: RS | Q98: RS | R98: Finalizado | S98: Finalizada | T98: #N/A | U98: Quinta feira | V98: Quinta feira | W98: =LEN(I98) -> 11 | X98: =IF(W98=14,"CNPJ",IF(W98=12,"CNPJ_INCOMPLETO_2",IF(W98=13,"CNPJ_INCOMPLETO_1",IF(W98=10,"CPF_Incompleto","CPF")))) -> CPF | Y98: =IF(X98="CNPJ_INCOMPLETO_1",("0"&LEFT(I98,1)&"."&MID(I98,2,3)&"."&MID(I98,5,3)&"/"&MID(I98,8,4)&"-"&MID(I98,12,2)),IF(X98="CNPJ_INCOMPLETO_2",("00."&LEFT(I98,3)&"."&MID(I98,4,3)&"/"&MID(I98,7,4)&"-"&MID(I98,11,2)),IF(X98="CNPJ",(LEFT(I98,2)&"."&MID(I98,3,3)&"."&MID(I98,6,3)&"/"&MID(I98,9,4)&"-"&MID(I98,13,2)),IF(X98="CPF_Incompleto",("0"&LEFT(I98,2)&"."&MID(I98,3,3)&"."&MID(I98,6,3)&"-"&MID(I98,9,2)),(LEFT(I98,3)&"."&MID(I98,4,3)&"."&MID(I98,7,3)&"-"&MID(I98,10,2)))))) -> 405.736.800-00 | Z98: =VLOOKUP(Y98,FORNECEDORES!$A$2:$G$9043,3,0) -> JOSÉ DAGOBERTO MACHADO | AA98: =VLOOKUP(Y98,FORNECEDORES!$A$2:$G$9041,7,0) -> jdmdago@gmail.com;
A99: CON:1687 | B99: 4417812022858440 | C99: 45855 | D99: 45862 | E99: SDO | F99: 338.6 | G99: EFETIVADA | H99: JOSE DAGOBERTO MACHADO | I99: 40573680000 | J99: IKV8F25 | K99: 101659721 | L99: SP | M99: 145453 | N99: 265590 | O99: 1687 | P99: RS | Q99: RS | R99: Finalizado | S99: Finalizada | T99: #N/A | U99: Quinta feira | V99: Quinta feira | W99: =LEN(I99) -> 11 | X99: =IF(W99=14,"CNPJ",IF(W99=12,"CNPJ_INCOMPLETO_2",IF(W99=13,"CNPJ_INCOMPLETO_1",IF(W99=10,"CPF_Incompleto","CPF")))) -> CPF | Y99: =IF(X99="CNPJ_INCOMPLETO_1",("0"&LEFT(I99,1)&"."&MID(I99,2,3)&"."&MID(I99,5,3)&"/"&MID(I99,8,4)&"-"&MID(I99,12,2)),IF(X99="CNPJ_INCOMPLETO_2",("00."&LEFT(I99,3)&"."&MID(I99,4,3)&"/"&MID(I99,7,4)&"-"&MID(I99,11,2)),IF(X99="CNPJ",(LEFT(I99,2)&"."&MID(I99,3,3)&"."&MID(I99,6,3)&"/"&MID(I99,9,4)&"-"&MID(I99,13,2)),IF(X99="CPF_Incompleto",("0"&LEFT(I99,2)&"."&MID(I99,3,3)&"."&MID(I99,6,3)&"-"&MID(I99,9,2)),(LEFT(I99,3)&"."&MID(I99,4,3)&"."&MID(I99,7,3)&"-"&MID(I99,10,2)))))) -> 405.736.800-00 | Z99: =VLOOKUP(Y99,FORNECEDORES!$A$2:$G$9043,3,0) -> JOSÉ DAGOBERTO MACHADO | AA99: =VLOOKUP(Y99,FORNECEDORES!$A$2:$G$9041,7,0) -> jdmdago@gmail.com;
A100: CON:3548 | B100: 4417812010875943 | C100: 45860 | D100: 45890 | E100: DES | F100: 1800 | G100: EFETIVADA | H100: ANDRE L.A. ENDRES - ME | I100: 92309194000120 | J100: AFK2804 | K100: 101836835 | L100: SP | M100: 145587 | N100: 266007 | O100: 3548, 3549 | P100: RS | Q100: RS | R100: Finalizado | S100: Finalizada | T100: EFETIVADA | U100: 30 | V100: 45899 | W100: =LEN(I100) -> 14 | X100: =IF(W100=14,"CNPJ",IF(W100=12,"CNPJ_INCOMPLETO_2",IF(W100=13,"CNPJ_INCOMPLETO_1",IF(W100=10,"CPF_Incompleto","CPF")))) -> CNPJ | Y100: =IF(X100="CNPJ_INCOMPLETO_1",("0"&LEFT(I100,1)&"."&MID(I100,2,3)&"."&MID(I100,5,3)&"/"&MID(I100,8,4)&"-"&MID(I100,12,2)),IF(X100="CNPJ_INCOMPLETO_2",("00."&LEFT(I100,3)&"."&MID(I100,4,3)&"/"&MID(I100,7,4)&"-"&MID(I100,11,2)),IF(X100="CNPJ",(LEFT(I100,2)&"."&MID(I100,3,3)&"."&MID(I100,6,3)&"/"&MID(I100,9,4)&"-"&MID(I100,13,2)),IF(X100="CPF_Incompleto",("0"&LEFT(I100,2)&"."&MID(I100,3,3)&"."&MID(I100,6,3)&"-"&MID(I100,9,2)),(LEFT(I100,3)&"."&MID(I100,4,3)&"."&MID(I100,7,3)&"-"&MID(I100,10,2)))))) -> 92.309.194/0001-20 | Z100: =VLOOKUP(Y100,FORNECEDORES!$A$2:$G$9043,3,0) -> ANDRE L.A. ENDRES - ME | AA100: =VLOOKUP(Y100,FORNECEDORES!$A$2:$G$9041,7,0) -> endrestransportes@outlook.com
...

Sheet verificar1
A1: Nome do Favorecido | B1: Documento do Favorecido | C1: Placa do veículo | D1: ID Viagem | E1: Filial | F1: Contrato de Frete | G1: Carga | H1: OBS | M1: Nome do Favorecido | N1: Placa do veículo | O1: Contrato de Frete | P1: Carga | Q1: OBS
A2: EBERTON EDUARDO ALVES | B2: 33924768897 | C2: JSN1D79 | D2: 104029305 | E2: SP | F2: 148828 | G2: 273564 | H2: logistica.onix@gmail.com | M2: EBERTON EDUARDO ALVES | N2: JSN1D79 | O2: 148828 | P2: 273564 | Q2: logistica.onix@gmail.com
A3: EBERTON EDUARDO ALVES | B3: 33924768897 | C3: JSN1D79 | D3: 104029305 | E3: SP | F3: 148828 | G3: 273564 | H3: logistica.onix@gmail.com | M3: EBERTON EDUARDO ALVES | N3: JSN1D79 | O3: 148828 | P3: 273564 | Q3: logistica.onix@gmail.com
A4: LUIS CAIO OLIVEIRA DOS SANTOS | B4: 6786288588 | C4: MLF7B49 | D4: 104069155 | E4: SP | F4: 148768 | G4: 273461 | H4: luiscaio1620@gmail.com; | M4: LUIS CAIO OLIVEIRA DOS SANTOS | N4: MLF7B49 | O4: 148768 | P4: 273461 | Q4: luiscaio1620@gmail.com;
A5: LUIS CAIO OLIVEIRA DOS SANTOS | B5: 6786288588 | C5: MLF7B49 | D5: 104069155 | E5: SP | F5: 148768 | G5: 273461 | H5: luiscaio1620@gmail.com; | M5: LUIS CAIO OLIVEIRA DOS SANTOS | N5: MLF7B49 | O5: 148768 | P5: 273461 | Q5: luiscaio1620@gmail.com;
A6: FAGNER MARQUES LUCAS | B6: 29773789870 | C6: PRQ9B73 | D6: 104069220 | E6: SP | F6: 148899 | G6: 273750 | H6: fag.125k@gmail.com; | M6: FAGNER MARQUES LUCAS | N6: PRQ9B73 | O6: 148899 | P6: 273750 | Q6: fag.125k@gmail.com;
A7: FAGNER MARQUES LUCAS | B7: 29773789870 | C7: PRQ9B73 | D7: 104069220 | E7: SP | F7: 148899 | G7: 273750 | H7: fag.125k@gmail.com; | M7: FAGNER MARQUES LUCAS | N7: PRQ9B73 | O7: 148899 | P7: 273750 | Q7: fag.125k@gmail.com;
A8: Diego Thales Lopes Cançado | B8: 8791702631 | C8: OZH6G24 | D8: 104069384 | E8: SP | F8: 148904 | G8: 273778 | H8: CADASTRADO SEM E-MAIL | M8: Diego Thales Lopes Cançado | N8: OZH6G24 | O8: 148904 | P8: 273778 | Q8: CADASTRADO SEM E-MAIL
A9: Diego Thales Lopes Cançado | B9: 8791702631 | C9: OZH6G24 | D9: 104069384 | E9: SP | F9: 148904 | G9: 273778 | H9: CADASTRADO SEM E-MAIL | M9: Diego Thales Lopes Cançado | N9: OZH6G24 | O9: 148904 | P9: 273778 | Q9: CADASTRADO SEM E-MAIL
M13: Nome do Favorecido | N13: Placa do veículo | O13: Contrato de Frete | P13: Carga | Q13: OBS
M14: EBERTON EDUARDO ALVES | N14: JSN1D79 | O14: 148828 | P14: 273564 | Q14: CADASTRADO SEM E-MAIL
M15: Diego Thales Lopes Cançado | N15: OZH6G24 | O15: 148904 | P15: 273778 | Q15: CADASTRADO SEM E-MAIL

Sheet verificar
B1: REFERENCIA | C1: PRESTADOR
B2: 050.253.025-10 | C2: LEANDRO DE JESUS MENDONCA
B3: 215.407.458-80 | C3: CINTIA ANTUNES NASCIMENTO
B4: 184.250.368-52 | C4: QUEILA DIANE ROMAGNOLI RODRIGUES
B5: 334.143.418-67 | C5: IDALECIO FIRMINO DE OLIVEIRA
B6: 477.928.638-75 | C6: ANDRESSA BISPO RAMOS

Sheet FORNECEDORES
A1: CNPJ | B1: COD_TR | C1: NOME_TRANSPORTADORA | D1: NOME_FANTASIA | E1: RESPONSÁVEL | F1: Tel_Fixo | G1: E-mail | H1: E-mail 2 | I1: MONITOR | J1: Ativa | K1: Analista | L1: Ativar | M1: Logo | N1: UF | O1: Foto | P1: Parceiro | Q1: ENDERECO | R1: MUNICIPIO | S1: CEP | T1: CNPJ | U1: INCRICAO_ESTADUAL | V1: Tipo de Carga | W1: VUC PLATAFORMA | X1: VUC | Y1: LEVE SECO | Z1: LEVE SECO PLATAFORMA | AA1: LEVE REFRIGERADO | AB1: TOCO SECO | AC1: TOCO SECO PLATAFORMA | AD1: TOCO REFRIGERADO | AE1: TRUCK SECO | AF1: TRUCK SECO PLATAFORMA | AG1: TRUCK REFRIGERADA | AH1: CARRETA SECA | AI1: CARRETA SECA PLATAFORMA | AJ1: CARRETA REFRIGERADA | AK1: AC | AL1: AL | AM1: AM | AN1: AP | AO1: BA | AP1: CE | AQ1: DF | AR1: ES | AS1: GO | AT1: MA | AU1: MG | AV1: MS | AW1: MT | AX1: PA | AY1: PB | AZ1: PE | BA1: PI | BB1: PR | BC1: RJ | BD1: RN | BE1: RO | BF1: RR | BG1: RS | BH1: SC | BI1: SE | BJ1: SP | BK1: TO | BL1: Data_Cadastro | BM1: CÓD
A2: 10.948.789/0001-60 | B2: 10948789 | C2: TRANSRIMA TRANSPORTES | D2: TRANSRIMA TRANSPORTES | E2: RICARDO | F2: 49 99928-8382 | G2: ricardo@transrima.com.br; | J2: FALSE | K2: FABIO ALVES CORDEIRO | L2: TRUE | N2: SC | P2: FALSE | Q2: TRAVESSA FAVASSA, 54 - SALA1 - BAIRRO IMPERIAL - CONCORDIA - SC | R2: CONCORDIA | S2: 89709-010 | T2: 10.948.789/0001-60 | U2: 255891210 | W2: FALSE | X2: FALSE | Y2: FALSE | Z2: FALSE | AA2: FALSE | AB2: FALSE | AC2: FALSE | AD2: FALSE | AE2: FALSE | AF2: FALSE | AG2: FALSE | AH2: FALSE | AI2: FALSE | AJ2: FALSE | AK2: FALSE | AL2: FALSE | AM2: FALSE | AN2: FALSE | AO2: FALSE | AP2: FALSE | AQ2: FALSE | AR2: FALSE | AS2: FALSE | AT2: FALSE | AU2: FALSE | AV2: FALSE | AW2: FALSE | AX2: FALSE | AY2: FALSE | AZ2: FALSE | BA2: FALSE | BB2: FALSE | BC2: FALSE | BD2: FALSE | BE2: FALSE | BF2: FALSE | BG2: FALSE | BH2: FALSE | BI2: FALSE | BJ2: FALSE | BK2: FALSE | BL2: 45807.741 | BM2: 1275
A3: 63.073.266/0020-47 | B3: 63073266 | C3: TRANSPORTADORA BOMPREÇO LTDA | D3: BOMPREÇO | E3: PABLO SARMENTO | F3: 11-954567877 | G3: fabio_cordeiro@carrefour.com; | J3: FALSE | K3: FABIO ALVES CORDEIRO | L3: TRUE | N3: SP | P3: FALSE | T3: 63.073.266/0020-47 | U3: 241131272113 | W3: FALSE | X3: FALSE | Y3: FALSE | Z3: FALSE | AA3: FALSE | AB3: FALSE | AC3: FALSE | AD3: FALSE | AE3: FALSE | AF3: FALSE | AG3: FALSE | AH3: FALSE | AI3: FALSE | AJ3: FALSE | AK3: FALSE | AL3: FALSE | AM3: FALSE | AN3: FALSE | AO3: FALSE | AP3: FALSE | AQ3: FALSE | AR3: FALSE | AS3: FALSE | AT3: FALSE | AU3: FALSE | AV3: FALSE | AW3: FALSE | AX3: FALSE | AY3: FALSE | AZ3: FALSE | BA3: FALSE | BB3: FALSE | BC3: FALSE | BD3: FALSE | BE3: FALSE | BF3: FALSE | BG3: FALSE | BH3: FALSE | BI3: FALSE | BJ3: FALSE | BK3: FALSE | BM3: 643
A4: 63.073.266/0004-27 | B4: 63073266000427 | C4: TRANSPORTADORA BOMPREÇO LTDA | D4: BOMPREÇO | E4: PABLO SARMENTO | F4: 11-954567877 | G4: fabio_cordeiro@carrefour.com; luiz_antonio_neris_dos_santos@carrefour.com | H4: NOVO | J4: FALSE | K4: FABIO ALVES CORDEIRO | L4: TRUE | N4: SP | P4: FALSE | Q4: AVENIDA RECIFE, 2 - JARDIM SANTO AFONSO (JARDIM PRESIDENTE DUTRA) - GUARULHOS - | R4: GUARULHOS | S4: 07.271-220 | T4: 63.073.266/0004-27 | U4: 241131272113 | W4: FALSE | X4: FALSE | Y4: FALSE | Z4: FALSE | AA4: FALSE | AB4: FALSE | AC4: FALSE | AD4: FALSE | AE4: FALSE | AF4: FALSE | AG4: FALSE | AH4: FALSE | AI4: FALSE | AJ4: FALSE | AK4: FALSE | AL4: FALSE | AM4: FALSE | AN4: FALSE | AO4: FALSE | AP4: FALSE | AQ4: FALSE | AR4: FALSE | AS4: FALSE | AT4: FALSE | AU4: FALSE | AV4: FALSE | AW4: FALSE | AX4: FALSE | AY4: FALSE | AZ4: FALSE | BA4: FALSE | BB4: FALSE | BC4: FALSE | BD4: FALSE | BE4: FALSE | BF4: FALSE | BG4: FALSE | BH4: FALSE | BI4: FALSE | BJ4: FALSE | BK4: FALSE | BL4: 45830.63 | BM4: 1304
A5: 63.073.266/0011-56 | B5: 63073266001156 | C5: TRANSPORTADORA BOMPREÇO LTDA | D5: BOMPREÇO | E5: PABLO SARMENTO | F5: 11-954567877 | G5: fabio_cordeiro@carrefour.com; luiz_antonio_neris_dos_santos@carrefour.com | H5: NOVO | J5: FALSE | K5: FABIO ALVES CORDEIRO | L5: TRUE | N5: SP | P5: FALSE | Q5: RUA SERGIO JUNGBLUT DIETERICH, 913 - SALAA - SARANDI - PORTO ALEGRE | RS | R5: PORTO ALEGRE | S5: 91060-410 | T5: 63.073.266/0011-56 | W5: FALSE | X5: FALSE | Y5: FALSE | Z5: FALSE | AA5: FALSE | AB5: FALSE | AC5: FALSE | AD5: FALSE | AE5: FALSE | AF5: FALSE | AG5: FALSE | AH5: FALSE | AI5: FALSE | AJ5: FALSE | AK5: FALSE | AL5: FALSE | AM5: FALSE | AN5: FALSE | AO5: FALSE | AP5: FALSE | AQ5: FALSE | AR5: FALSE | AS5: FALSE | AT5: FALSE | AU5: FALSE | AV5: FALSE | AW5: FALSE | AX5: FALSE | AY5: FALSE | AZ5: FALSE | BA5: FALSE | BB5: FALSE | BC5: FALSE | BD5: FALSE | BE5: FALSE | BF5: FALSE | BG5: FALSE | BH5: FALSE | BI5: FALSE | BJ5: FALSE | BK5: FALSE | BL5: 45830.636 | BM5: 1305
A6: 63.073.266/0023-90 | B6: 63073266002390 | C6: TRANSPORTADORA BOMPREÇO LTDA | D6: BOMPREÇO | E6: PABLO SARMENTO | F6: 11-954567877 | G6: fabio_cordeiro@carrefour.com; luiz_antonio_neris_dos_santos@carrefour.com | H6: NOVO | J6: FALSE | K6: FABIO ALVES CORDEIRO | L6: TRUE | N6: SP | P6: FALSE | T6: 63.073.266/0023-90 | U6: 241131272113 | W6: FALSE | X6: FALSE | Y6: FALSE | Z6: FALSE | AA6: FALSE | AB6: FALSE | AC6: FALSE | AD6: FALSE | AE6: FALSE | AF6: FALSE | AG6: FALSE | AH6: FALSE | AI6: FALSE | AJ6: FALSE | AK6: FALSE | AL6: FALSE | AM6: FALSE | AN6: FALSE | AO6: FALSE | AP6: FALSE | AQ6: FALSE | AR6: FALSE | AS6: FALSE | AT6: FALSE | AU6: FALSE | AV6: FALSE | AW6: FALSE | AX6: FALSE | AY6: FALSE | AZ6: FALSE | BA6: FALSE | BB6: FALSE | BC6: FALSE | BD6: FALSE | BE6: FALSE | BF6: FALSE | BG6: FALSE | BH6: FALSE | BI6: FALSE | BJ6: FALSE | BK6: FALSE | BL6: 45708.668 | BM6: 1234
A7: 63.073.266/0024-70 | B7: 6307326600239070 | C7: TRANSPORTADORA BOMPREÇO LTDA | D7: BOMPREÇO | E7: PABLO SARMENTO | F7: 11-954567877 | G7: fabio_cordeiro@carrefour.com; luiz_antonio_neris_dos_santos@carrefour.com | H7: NOVO | J7: FALSE | K7: FABIO ALVES CORDEIRO | L7: TRUE | N7: SP | P7: FALSE | Q7: AVENIDA DOUTOR MAURO LINDEMBERG MONTEIRO, 628 - KM 98 BLOCO A SUPERIOR SALA 1 - BAIRRO SANTA FE - OSASCO - SP | R7: OSASCO | S7: 0628-010 | T7: 63.073.266/0024-70 | U7: 241131272113 | W7: FALSE | X7: FALSE | Y7: FALSE | Z7: FALSE | AA7: FALSE | AB7: FALSE | AC7: FALSE | AD7: FALSE | AE7: FALSE | AF7: FALSE | AG7: FALSE | AH7: FALSE | AI7: FALSE | AJ7: FALSE | AK7: FALSE | AL7: FALSE | AM7: FALSE | AN7: FALSE | AO7: FALSE | AP7: FALSE | AQ7: FALSE | AR7: FALSE | AS7: FALSE | AT7: FALSE | AU7: FALSE | AV7: FALSE | AW7: FALSE | AX7: FALSE | AY7: FALSE | AZ7: FALSE | BA7: FALSE | BB7: FALSE | BC7: FALSE | BD7: FALSE | BE7: FALSE | BF7: FALSE | BG7: FALSE | BH7: FALSE | BI7: FALSE | BJ7: FALSE | BK7: FALSE | BL7: 45807.436 | BM7: 1267
A8: 80.424.914/0003-80 | B8: 80424914 | C8: TRANSPORTES TOZZO LTDA | D8: TRANSPORTES TOZZO LTDA | E8: SOLANGE | F8: 49 8805-9773 | G8: solange.oliveira@transtozzo.com.br; | J8: FALSE | K8: FABIO ALVES CORDEIRO | L8: TRUE | N8: SP | P8: FALSE | Q8: RODOVIA VICE-PREFEITO HERMENEGILDO TONOLLI, 2995 - SALA 01 - Bairro: DESMEMBRAMENTO SANTA CLARA - ITUPEVA - SP | R8: ITUPEVA | S8: 13295-504 | T8: 80.424.914/0003-80 | U8: 388.026.458.117 | W8: FALSE | X8: FALSE | Y8: FALSE | Z8: FALSE | AA8: FALSE | AB8: FALSE | AC8: FALSE | AD8: FALSE | AE8: FALSE | AF8: FALSE | AG8: FALSE | AH8: FALSE | AI8: FALSE | AJ8: FALSE | AK8: FALSE | AL8: FALSE | AM8: FALSE | AN8: FALSE | AO8: FALSE | AP8: FALSE | AQ8: FALSE | AR8: FALSE | AS8: FALSE | AT8: FALSE | AU8: FALSE | AV8: FALSE | AW8: FALSE | AX8: FALSE | AY8: FALSE | AZ8: FALSE | BA8: FALSE | BB8: FALSE | BC8: FALSE | BD8: FALSE | BE8: FALSE | BF8: FALSE | BG8: FALSE | BH8: FALSE | BI8: FALSE | BJ8: FALSE | BK8: FALSE | BL8: 45807.474 | BM8: 1272
A9: 80.424.914/0001-19 | B9: 80424914000119 | C9: TRANSPORTES TOZZO LTDA | D9: TRANSPORTES TOZZO LTDA | E9: SOLANGE | F9: 49 8805-9773 | G9: solange.oliveira@transtozzo.com.br; log5@transtozzo.com.br; | J9: FALSE | K9: FABIO ALVES CORDEIRO | L9: TRUE | N9: SC | P9: FALSE | Q9: ACESSO PLÍNIO ARLINDO DE NES, 4303-D - ACESSO BR 282 - BELVEDERE - CHAPECÓ - SC | R9: CHAPECO | S9: 89810-460 | T9: 80.424.914/0001-19 | U9: 251755738 | W9: FALSE | X9: FALSE | Y9: FALSE | Z9: FALSE | AA9: FALSE | AB9: FALSE | AC9: FALSE | AD9: FALSE | AE9: FALSE | AF9: FALSE | AG9: FALSE | AH9: FALSE | AI9: FALSE | AJ9: FALSE | AK9: FALSE | AL9: FALSE | AM9: FALSE | AN9: FALSE | AO9: FALSE | AP9: FALSE | AQ9: FALSE | AR9: FALSE | AS9: FALSE | AT9: FALSE | AU9: FALSE | AV9: FALSE | AW9: FALSE | AX9: FALSE | AY9: FALSE | AZ9: FALSE | BA9: FALSE | BB9: FALSE | BC9: FALSE | BD9: FALSE | BE9: FALSE | BF9: FALSE | BG9: FALSE | BH9: FALSE | BI9: FALSE | BJ9: FALSE | BK9: FALSE | BL9: 45841.441 | BM9: 1317
A10: 01.599.101/0001-93 | B10: 0159910 | C10: SEQUOIA LOGISTICA E TRANSPORTES S.A | D10: SEQUOIA LOGISTICA E TRANSPORTES S.A | E10: MOACIR - OPER / CLAUDIA -COM | F10: 11-983963646 / 31-99319-4980 | G10: moacir.giovanello@sequoialog.com.br; claudia.msilva@sequoialog.com.br ;nubia.prates@sequoialog.com.br; torre.trafego@sequoialog.com.br; | J10: FALSE | K10: FABIO ALVES CORDEIRO | L10: TRUE | N10: SP | P10: FALSE | Q10: AVENIDA ISALTINO VICTOR DE MORAES, 437 - TERREOMOD. D BLOCO 100 - VILA BONFIM - EMBU DAS ARTES - SP | R10: EMBU DAS ARTES | S10: 06.806-400 | T10: 01.599.101/0001-93 | U10: 298.078.404.118 | W10: FALSE | X10: FALSE | Y10: FALSE | Z10: FALSE | AA10: FALSE | AB10: FALSE | AC10: FALSE | AD10: FALSE | AE10: FALSE | AF10: FALSE | AG10: FALSE | AH10: TRUE | AI10: FALSE | AJ10: FALSE | AK10: FALSE | AL10: FALSE | AM10: FALSE | AN10: FALSE | AO10: FALSE | AP10: FALSE | AQ10: TRUE | AR10: FALSE | AS10: FALSE | AT10: FALSE | AU10: TRUE | AV10: FALSE | AW10: FALSE | AX10: FALSE | AY10: FALSE | AZ10: FALSE | BA10: FALSE | BB10: FALSE | BC10: TRUE | BD10: FALSE | BE10: FALSE | BF10: FALSE | BG10: FALSE | BH10: FALSE | BI10: FALSE | BJ10: TRUE | BK10: FALSE | BM10: 567
A11: 08.158.720/0002-72 | B11: 08158720 | C11: TRANSPORTADORA PEREGRINA LTDA | D11: TRANSPORTADORA PEREGRINA | E11: GABRIEL CECHINEL MACCARI | F11: 48-3467-2700 / 48 99903-0134 | G11: vendas03@transperegrina.com.br; gabriel@transperegrina.com.br; setor.vendas@transperegrina.com.br; olavo@transperegrina.com.br; | J11: FALSE | K11: FABIO ALVES CORDEIRO | L11: TRUE | N11: SP | P11: FALSE | Q11: AV 56, - ALTO DO SANTANA - RIO CLARO - SP - CEP:13504195 | R11: RIO CLARO | S11: 13504195 | T11: 08.158.720/0002-72 | U11: 587294177117 | W11: FALSE | X11: FALSE | Y11: FALSE | Z11: FALSE | AA11: FALSE | AB11: FALSE | AC11: FALSE | AD11: FALSE | AE11: FALSE | AF11: FALSE | AG11: FALSE | AH11: FALSE | AI11: FALSE | AJ11: FALSE | AK11: FALSE | AL11: FALSE | AM11: FALSE | AN11: FALSE | AO11: FALSE | AP11: FALSE | AQ11: FALSE | AR11: FALSE | AS11: FALSE | AT11: FALSE | AU11: FALSE | AV11: FALSE | AW11: FALSE | AX11: FALSE | AY11: FALSE | AZ11: FALSE | BA11: FALSE | BB11: FALSE | BC11: FALSE | BD11: FALSE | BE11: FALSE | BF11: FALSE | BG11: FALSE | BH11: FALSE | BI11: FALSE | BJ11: FALSE | BK11: FALSE | BM11: 677
A12: 60.077.336/0001-84 | B12: 60077336 | C12: JOB TRANSPORTES DE ITATIBA LTDA | D12: B J TRANSPORTES DE ITATIBA LTDA | F12: 11975930568 | H12: ANTT 00121203 | J12: FALSE | K12: FABIO ALVES CORDEIRO | L12: TRUE | N12: SP | P12: FALSE | Q12: AVENIDA ANTONIO NARDI, 777 - | R12: ITATIBA | S12: 13254260 | T12: 60.077.336/0001-84 | U12: 382031050117 | W12: FALSE | X12: FALSE | Y12: FALSE | Z12: FALSE | AA12: FALSE | AB12: FALSE | AC12: FALSE | AD12: FALSE | AE12: FALSE | AF12: FALSE | AG12: FALSE | AH12: FALSE | AI12: FALSE | AJ12: FALSE | AK12: FALSE | AL12: FALSE | AM12: FALSE | AN12: FALSE | AO12: FALSE | AP12: FALSE | AQ12: FALSE | AR12: FALSE | AS12: FALSE | AT12: FALSE | AU12: FALSE | AV12: FALSE | AW12: FALSE | AX12: FALSE | AY12: FALSE | AZ12: FALSE | BA12: FALSE | BB12: FALSE | BC12: FALSE | BD12: FALSE | BE12: FALSE | BF12: FALSE | BG12: FALSE | BH12: FALSE | BI12: FALSE | BJ12: FALSE | BK12: FALSE | BM12: 653
A13: 000059750000210 | B13: 00005975 | C13: TRANSP.REPRES. PEDRI E SCHLINGER LT | E13: ANA GLAUCIA PEDRI | F13: (41) 30420650 - 9979-8343 | G13: agpedri@hotmail.com | J13: TRUE | K13: FABIO ALVES CORDEIRO | L13: TRUE | N13: PR | P13: FALSE | Q13: R TERESA MAGRIN BUSO,68 SITIO CERCADO | R13: CURITIBA | S13: 81900280 | T13: 000059750000210 | U13: 9021826836 | W13: FALSE | X13: FALSE | Y13: FALSE | Z13: FALSE | AA13: FALSE | AB13: FALSE | AC13: FALSE | AD13: FALSE | AE13: FALSE | AF13: FALSE | AG13: FALSE | AH13: FALSE | AI13: FALSE | AJ13: FALSE | AK13: FALSE | AL13: FALSE | AM13: FALSE | AN13: FALSE | AO13: FALSE | AP13: FALSE | AQ13: FALSE | AR13: FALSE | AS13: FALSE | AT13: FALSE | AU13: FALSE | AV13: FALSE | AW13: FALSE | AX13: FALSE | AY13: FALSE | AZ13: FALSE | BA13: FALSE | BB13: FALSE | BC13: FALSE | BD13: FALSE | BE13: FALSE | BF13: FALSE | BG13: FALSE | BH13: FALSE | BI13: FALSE | BJ13: FALSE | BK13: FALSE | BM13: 102
A14: 00.132.104/0001-50 | B14: 00132104 | C14: TATUZAO TRANSPORTES RODOVIARIO LTDA | D14: TATUZAO TRANSPORTES | E14: Edgenes Braz da Silva | F14: (81) 98802-8628 | G14: assistente@tatuzaotransportes.com.br; coordoperacionalpe@tatuzaotransportes.com.br; wal@tatuzaotransportes.com.br; financeiro@tatuzaotransportes.com.br; operacionalpe1@tatuzaotransportes.com.br; contador@tatuzaotransportes.com.br; | J14: FALSE | K14: FABIO ALVES CORDEIRO | L14: TRUE | N14: PE | P14: FALSE | Q14: RUA DR.TAVARES CORREIA, 321 - B. IMBIRIBEIRA - RECIFE - CEP: 51200-130 | R14: RECIFE | S14: 51.200-130 | T14: 00.132.104/0001-50 | W14: FALSE | X14: FALSE | Y14: FALSE | Z14: FALSE | AA14: FALSE | AB14: FALSE | AC14: FALSE | AD14: FALSE | AE14: FALSE | AF14: FALSE | AG14: FALSE | AH14: FALSE | AI14: FALSE | AJ14: FALSE | AK14: FALSE | AL14: FALSE | AM14: FALSE | AN14: FALSE | AO14: FALSE | AP14: FALSE | AQ14: FALSE | AR14: FALSE | AS14: FALSE | AT14: FALSE | AU14: FALSE | AV14: FALSE | AW14: FALSE | AX14: FALSE | AY14: FALSE | AZ14: FALSE | BA14: FALSE | BB14: FALSE | BC14: FALSE | BD14: FALSE | BE14: FALSE | BF14: FALSE | BG14: FALSE | BH14: FALSE | BI14: FALSE | BJ14: FALSE | BK14: FALSE | BM14: 670
A15: 00.132.104/0005-83 | B15: 0013210483 | C15: TATUZAO TRANSPORTES RODOVIARIO LTDA | D15: TATUZAO TRANSPORTES | E15: Edgenes Braz da Silva | F15: (81) 98802-8628 | G15: assistente@tatuzaotransportes.com.br; coordoperacionalpe@tatuzaotransportes.com.br; wal@tatuzaotransportes.com.br; financeiro@tatuzaotransportes.com.br; operacionalpe1@tatuzaotransportes.com.br; contador@tatuzaotransportes.com.br; | J15: FALSE | K15: FABIO ALVES CORDEIRO | L15: TRUE | N15: PE | P15: FALSE | Q15: RUA DR.TAVARES CORREIA, 321 - B. IMBIRIBEIRA - RECIFE - CEP: 51200-130 | R15: RECIFE | S15: 51.200-130 | T15: 00.132.104/0005-83 | W15: FALSE | X15: FALSE | Y15: FALSE | Z15: FALSE | AA15: FALSE | AB15: FALSE | AC15: FALSE | AD15: FALSE | AE15: FALSE | AF15: FALSE | AG15: FALSE | AH15: FALSE | AI15: FALSE | AJ15: FALSE | AK15: FALSE | AL15: FALSE | AM15: FALSE | AN15: FALSE | AO15: FALSE | AP15: FALSE | AQ15: FALSE | AR15: FALSE | AS15: FALSE | AT15: FALSE | AU15: FALSE | AV15: FALSE | AW15: FALSE | AX15: FALSE | AY15: FALSE | AZ15: FALSE | BA15: FALSE | BB15: FALSE | BC15: FALSE | BD15: FALSE | BE15: FALSE | BF15: FALSE | BG15: FALSE | BH15: FALSE | BI15: FALSE | BJ15: FALSE | BK15: FALSE | BL15: 45807.432 | BM15: 1265
A16: 00.175.631/0001-41 | B16: 00175631 | C16: SHELBY TRANSPORTES RODOVIARIO LTDA | D16: SHELBY - TRANSPORTES RODOVIARIO | E16: ATAÍDE | F16: 11976520340 | G16: ataide@rodomilli.com.br | J16: FALSE | K16: FABIO ALVES CORDEIRO | L16: TRUE | N16: SP | P16: FALSE | Q16: AV DO POETA, 640 - LOJA 02 SLJ SLJ 01 - JARDIM JULIETA - SAO PAULO - SP - CEP: 02161160 | R16: SÃO PAULO | S16: 02161160 | T16: 00.175.631/0001-41 | U16: 148.319.550.11 | W16: FALSE | X16: FALSE | Y16: FALSE | Z16: FALSE | AA16: FALSE | AB16: FALSE | AC16: FALSE | AD16: FALSE | AE16: FALSE | AF16: FALSE | AG16: FALSE | AH16: FALSE | AI16: FALSE | AJ16: FALSE | AK16: FALSE | AL16: FALSE | AM16: FALSE | AN16: FALSE | AO16: FALSE | AP16: FALSE | AQ16: FALSE | AR16: FALSE | AS16: FALSE | AT16: FALSE | AU16: FALSE | AV16: FALSE | AW16: FALSE | AX16: FALSE | AY16: FALSE | AZ16: FALSE | BA16: FALSE | BB16: FALSE | BC16: FALSE | BD16: FALSE | BE16: FALSE | BF16: FALSE | BG16: FALSE | BH16: FALSE | BI16: FALSE | BJ16: FALSE | BK16: FALSE | BM16: 676
A17: 00.634.601/0001-56 | B17: 00634601 | C17: A FILHO E N FILHO LTDA | D17: ALTERNATIVA MUDANCAS E TRANSPORTES | E17: JONAS | F17: 4199711435 - | G17: AFILHOTRANSPORTES@GMAIL.COM; | H17: 00.634.601/1000-56 | J17: FALSE | K17: FABIO ALVES CORDEIRO | L17: TRUE | N17: PR | P17: FALSE | Q17: R PADRE FRANCISCO MADEJ, 265 - B. CIC - | R17: CURITIBA | S17: 81280-210 | T17: 00.634.601/0001-56 | U17: 9010436807 | W17: FALSE | X17: FALSE | Y17: FALSE | Z17: FALSE | AA17: FALSE | AB17: FALSE | AC17: FALSE | AD17: FALSE | AE17: FALSE | AF17: FALSE | AG17: FALSE | AH17: FALSE | AI17: FALSE | AJ17: FALSE | AK17: FALSE | AL17: FALSE | AM17: FALSE | AN17: FALSE | AO17: FALSE | AP17: FALSE | AQ17: FALSE | AR17: FALSE | AS17: FALSE | AT17: FALSE | AU17: FALSE | AV17: FALSE | AW17: FALSE | AX17: FALSE | AY17: FALSE | AZ17: FALSE | BA17: FALSE | BB17: FALSE | BC17: FALSE | BD17: FALSE | BE17: FALSE | BF17: FALSE | BG17: FALSE | BH17: FALSE | BI17: FALSE | BJ17: FALSE | BK17: FALSE | BM17: 668
A18: 00.680.933/0003-39 | B18: 00680933 | C18: COOPERATIVA DOS TRANSPORTADORES DO VALE | D18: COOTRAVALE | E18: MAICON | F18: (47) 3404-7000 - 95356-5640 / | G18: contato@cootravale.com.br; maico.alves@cootravale.com.br; marco.machado@cootravale.com.br; | J18: FALSE | K18: FABIO ALVES CORDEIRO | L18: FALSE | N18: SP | P18: FALSE | Q18: RODOVIA JORGE LACERDA, 1135 – ESPINHEIROS, ITAJAÍ – SANTA CATARINA | S18: 88317-100 | T18: 00.680.933/0003-39 | U18: 116.539.730.116 | W18: FALSE | X18: FALSE | Y18: FALSE | Z18: FALSE | AA18: FALSE | AB18: FALSE | AC18: FALSE | AD18: FALSE | AE18: FALSE | AF18: FALSE | AG18: FALSE | AH18: TRUE | AI18: FALSE | AJ18: TRUE | AK18: FALSE | AL18: FALSE | AM18: FALSE | AN18: FALSE | AO18: FALSE | AP18: FALSE | AQ18: FALSE | AR18: FALSE | AS18: FALSE | AT18: FALSE | AU18: FALSE | AV18: FALSE | AW18: FALSE | AX18: FALSE | AY18: FALSE | AZ18: FALSE | BA18: FALSE | BB18: FALSE | BC18: FALSE | BD18: FALSE | BE18: FALSE | BF18: FALSE | BG18: TRUE | BH18: FALSE | BI18: FALSE | BJ18: FALSE | BK18: FALSE | BM18: 559
A19: 00.680.933/0019-04 | B19: 00680933001904 | C19: COOPERATIVA DOS TRANSP DO VALLE | D19: COOTRAVALE | E19: DOUGLAS | F19: (47) 3404-7000 | G19: rivania@cootravale.com.br; eliane@cootravale.com.br; douglas@cootravale.com.br; daiane.goes@cootravale.com.br; | J19: FALSE | K19: FABIO ALVES CORDEIRO | L19: TRUE | N19: CE | P19: FALSE | Q19: RODOVIA BR 116, 5820 - KM 15 SALA 07 -FORTALEZA - CE - CEP:60874-502 | R19: FORTALEZA | S19: 60874-502 | T19: 00.680.933/0019-04 | W19: FALSE | X19: FALSE | Y19: FALSE | Z19: FALSE | AA19: FALSE | AB19: FALSE | AC19: FALSE | AD19: FALSE | AE19: FALSE | AF19: FALSE | AG19: FALSE | AH19: FALSE | AI19: FALSE | AJ19: FALSE | AK19: FALSE | AL19: FALSE | AM19: FALSE | AN19: FALSE | AO19: FALSE | AP19: FALSE | AQ19: FALSE | AR19: FALSE | AS19: FALSE | AT19: FALSE | AU19: FALSE | AV19: FALSE | AW19: FALSE | AX19: FALSE | AY19: FALSE | AZ19: FALSE | BA19: FALSE | BB19: FALSE | BC19: FALSE | BD19: FALSE | BE19: FALSE | BF19: FALSE | BG19: FALSE | BH19: FALSE | BI19: FALSE | BJ19: FALSE | BK19: FALSE | BL19: 45830.702 | BM19: 1311
A20: 00.680.933/0014-91 | B20: 0068093391 | C20: COOPERATIVA DOS TRANSPORTADORES DO VALE | D20: COOTRAVALE | E20: MAICON | F20: (47) 3404-7000 - 95356-5640 / | G20: contato@cootravale.com.br; maico.alves@cootravale.com.br; marco.machado@cootravale.com.br; | J20: FALSE | K20: FABIO ALVES CORDEIRO | L20: FALSE | N20: SP | P20: FALSE | Q20: RODOVIA JORGE LACERDA, 1135 – ESPINHEIROS, ITAJAÍ – SANTA CATARINA | S20: 88317-100 | T20: 00.680.933/0014-91 | U20: 116.539.730.116 | W20: FALSE | X20: FALSE | Y20: FALSE | Z20: FALSE | AA20: FALSE | AB20: FALSE | AC20: FALSE | AD20: FALSE | AE20: FALSE | AF20: FALSE | AG20: FALSE | AH20: TRUE | AI20: FALSE | AJ20: TRUE | AK20: FALSE | AL20: FALSE | AM20: FALSE | AN20: FALSE | AO20: FALSE | AP20: FALSE | AQ20: FALSE | AR20: FALSE | AS20: FALSE | AT20: FALSE | AU20: FALSE | AV20: FALSE | AW20: FALSE | AX20: FALSE | AY20: FALSE | AZ20: FALSE | BA20: FALSE | BB20: FALSE | BC20: FALSE | BD20: FALSE | BE20: FALSE | BF20: FALSE | BG20: TRUE | BH20: FALSE | BI20: FALSE | BJ20: FALSE | BK20: FALSE | BL20: 45807.428 | BM20: 1262
A21: 00.766.315/0001-44 | B21: 00766315 | C21: TRANSPORTES FRAMENTO LTDA | D21: TRANSPORTES FRAMENTO LTDA | E21: DOUGLAS / BARBARA / GEAN BELLEI | F21: 11-96446-0872 / 11-98479-0186 / 49-99991-8461 | G21: gean@transframento.com.br; michel@transframento.com.br; douglas.pereira@transframento.com.br | H21: refrigerado, frigorificado | J21: FALSE | K21: FABIO ALVES CORDEIRO | L21: TRUE | N21: SC | P21: FALSE | Q21: RUA JOÃO GUTEMBERG, 355 D - ENGENHO BRAUN - CHAPECÓ - SC - 89809-350 | R21: CHAPECO | S21: 89809-350 | T21: 00.766.315/0001-44 | U21: 253.154.928 | W21: FALSE | X21: FALSE | Y21: FALSE | Z21: FALSE | AA21: FALSE | AB21: FALSE | AC21: FALSE | AD21: FALSE | AE21: TRUE | AF21: FALSE | AG21: TRUE | AH21: TRUE | AI21: FALSE | AJ21: TRUE | AK21: FALSE | AL21: FALSE | AM21: FALSE | AN21: FALSE | AO21: FALSE | AP21: FALSE | AQ21: FALSE | AR21: FALSE | AS21: FALSE | AT21: FALSE | AU21: FALSE | AV21: FALSE | AW21: FALSE | AX21: FALSE | AY21: FALSE | AZ21: TRUE | BA21: FALSE | BB21: FALSE | BC21: TRUE | BD21: FALSE | BE21: FALSE | BF21: FALSE | BG21: FALSE | BH21: FALSE | BI21: FALSE | BJ21: TRUE | BK21: FALSE | BM21: 587
A22: 00.766.315/0002-25 | B22: 00766315000225 | C22: TRANSPORTES FRAMENTO LTDA | D22: TRANSPORTES FRAMENTO LTDA | E22: GEAN / DOUGLAS | F22: 49-9991-8461 / 11-96446-0872 | G22: gean@transframento.com.br; michel@transframento.com.br; douglas.pereira@transframento.com.br | J22: FALSE | K22: FABIO ALVES CORDEIRO | L22: TRUE | N22: RJ | P22: FALSE | Q22: localizada na Rua Araujo Guimaraes - Chacaras Rio-Petropolis, Duque de Caxias - RJ, 25.230-770 | R22: DUQUE DE CAXIAS | S22: 25230-770 | T22: 00.766.315/0002-25 | W22: FALSE | X22: FALSE | Y22: FALSE | Z22: FALSE | AA22: FALSE | AB22: FALSE | AC22: FALSE | AD22: FALSE | AE22: FALSE | AF22: FALSE | AG22: FALSE | AH22: FALSE | AI22: FALSE | AJ22: FALSE | AK22: FALSE | AL22: FALSE | AM22: FALSE | AN22: FALSE | AO22: FALSE | AP22: FALSE | AQ22: FALSE | AR22: FALSE | AS22: FALSE | AT22: FALSE | AU22: FALSE | AV22: FALSE | AW22: FALSE | AX22: FALSE | AY22: FALSE | AZ22: FALSE | BA22: FALSE | BB22: FALSE | BC22: FALSE | BD22: FALSE | BE22: FALSE | BF22: FALSE | BG22: FALSE | BH22: FALSE | BI22: FALSE | BJ22: FALSE | BK22: FALSE | BL22: 45830.638 | BM22: 1306
A23: 00.853.538/0001-49 | B23: 00853538 | C23: AGT LOG LOGISTICA E CARGAS LTDA | D23: AGT LOG LOGISTICA E CARGAS | E23: WANDERSON | F23: 62-9294-1365 | G23: pe@agtlog.com.br; roberto@agtlog.com.br; comercial@agtlog.com.br; contato@agtlog.com.br; | J23: FALSE | K23: FABIO ALVES CORDEIRO | L23: TRUE | N23: GO | P23: FALSE | Q23: V SECUNDARIA 02 ESQ. VIA PRIMARIA 2, SN - URUACU - GO - CEP:76400-000 | R23: URUACU | S23: 76400-000 | T23: 00.853.538/0001-49 | W23: FALSE | X23: FALSE | Y23: FALSE | Z23: FALSE | AA23: FALSE | AB23: FALSE | AC23: FALSE | AD23: FALSE | AE23: FALSE | AF23: FALSE | AG23: FALSE | AH23: FALSE | AI23: FALSE | AJ23: FALSE | AK23: FALSE | AL23: FALSE | AM23: FALSE | AN23: FALSE | AO23: FALSE | AP23: FALSE | AQ23: FALSE | AR23: FALSE | AS23: FALSE | AT23: FALSE | AU23: FALSE | AV23: FALSE | AW23: FALSE | AX23: FALSE | AY23: FALSE | AZ23: FALSE | BA23: FALSE | BB23: FALSE | BC23: FALSE | BD23: FALSE | BE23: FALSE | BF23: FALSE | BG23: FALSE | BH23: FALSE | BI23: FALSE | BJ23: FALSE | BK23: FALSE | BL23: 45743.712 | BM23: 1251
A24: 00.947.027/0001-96 | B24: 00947027 | C24: TRANSCOL TRANSPORTES E LOGISTICA | D24: TRANSCOL TRANSPORTES E LOGISTICA | E24: RICARDO RISSI | F24: (64) 3621-0234 / 98213-0642 | G24: diretoria@transcolgo.com.br; logistica@ricotransporteselogistica.com.br; diretoria@ricologisticaetransportes.com.br; | H24: direto pelo Carrefour | J24: FALSE | K24: FABIO ALVES CORDEIRO | L24: TRUE | N24: GO | P24: FALSE | Q24: AREA RURAL DE RIO VERDE, S/N - KM 396 A ESQUERDA - RIO VERDE - GO CEP: 75913899 | R24: RIO VERDE | S24: 75913899 | T24: 00.947.027/0001-96 | U24: 103511270 | W24: FALSE | X24: FALSE | Y24: FALSE | Z24: FALSE | AA24: FALSE | AB24: FALSE | AC24: FALSE | AD24: FALSE | AE24: FALSE | AF24: FALSE | AG24: FALSE | AH24: FALSE | AI24: FALSE | AJ24: FALSE | AK24: FALSE | AL24: FALSE | AM24: FALSE | AN24: FALSE | AO24: FALSE | AP24: FALSE | AQ24: FALSE | AR24: FALSE | AS24: FALSE | AT24: FALSE | AU24: FALSE | AV24: FALSE | AW24: FALSE | AX24: FALSE | AY24: FALSE | AZ24: FALSE | BA24: FALSE | BB24: FALSE | BC24: FALSE | BD24: FALSE | BE24: FALSE | BF24: FALSE | BG24: FALSE | BH24: FALSE | BI24: FALSE | BJ24: FALSE | BK24: FALSE | BL24: 45693.675 | BM24: 1208
A25: 010.148.919-65 | B25: 01014891965 | C25: ERISON DE OLIVEIRA | D25: ERISON DE OLIVEIRA | E25: ERISON DE OLIVEIRA | F25: 47 9207-5550 | G25: erisondeoliveiral@gmail.com; | J25: FALSE | K25: FABIO ALVES CORDEIRO | L25: TRUE | N25: SC | P25: FALSE | Q25: BLUMENAU - SC - CEP: 89058010 | R25: BLUMENAU | S25: 89058010 | T25: 010.148.919-65 | W25: FALSE | X25: FALSE | Y25: FALSE | Z25: FALSE | AA25: FALSE | AB25: FALSE | AC25: FALSE | AD25: FALSE | AE25: FALSE | AF25: FALSE | AG25: FALSE | AH25: FALSE | AI25: FALSE | AJ25: FALSE | AK25: FALSE | AL25: FALSE | AM25: FALSE | AN25: FALSE | AO25: FALSE | AP25: FALSE | AQ25: FALSE | AR25: FALSE | AS25: FALSE | AT25: FALSE | AU25: FALSE | AV25: FALSE | AW25: FALSE | AX25: FALSE | AY25: FALSE | AZ25: FALSE | BA25: FALSE | BB25: FALSE | BC25: FALSE | BD25: FALSE | BE25: FALSE | BF25: FALSE | BG25: FALSE | BH25: FALSE | BI25: FALSE | BJ25: FALSE | BK25: FALSE | BL25: 45674.503 | BM25: 1203
A26: 01554759000189 | B26: 01554759 | C26: TRANSPORTADORA & COMERCIO LUNARDI LTDA | D26: TRANSPORTADORA & COMERCIO LUNARDI LTDA | E26: ILÓI LUNARDI | F26: (49) 3353-9900 | G26: faturamento01@transportadoralunardi.com.br; | J26: FALSE | K26: FABIO ALVES CORDEIRO | L26: TRUE | N26: SC | P26: FALSE | R26: XAXIM | T26: 01554759000189 | W26: FALSE | X26: FALSE | Y26: FALSE | Z26: FALSE | AA26: FALSE | AB26: FALSE | AC26: FALSE | AD26: FALSE | AE26: FALSE | AF26: FALSE | AG26: FALSE | AH26: FALSE | AI26: FALSE | AJ26: FALSE | AK26: FALSE | AL26: FALSE | AM26: FALSE | AN26: FALSE | AO26: FALSE | AP26: FALSE | AQ26: FALSE | AR26: FALSE | AS26: FALSE | AT26: FALSE | AU26: FALSE | AV26: FALSE | AW26: FALSE | AX26: FALSE | AY26: FALSE | AZ26: FALSE | BA26: FALSE | BB26: FALSE | BC26: FALSE | BD26: FALSE | BE26: FALSE | BF26: FALSE | BG26: FALSE | BH26: FALSE | BI26: FALSE | BJ26: FALSE | BK26: FALSE | BM26: 613
A27: 01.743.404/0001-38 | B27: 01743404 | C27: FAVORITA TRANSPORTES LTDA | D27: FAVORITA TRANSPORTES LTDA | F27: 11-94773-2804; | G27: rodrigopaglino@favorita.com.br ; | J27: TRUE | K27: FABIO ALVES CORDEIRO | L27: TRUE | N27: SP | P27: FALSE | Q27: V AC JOAO DE GOES, 2285 - JARDIM ALVORADA - JANDIRA - SP -CEP: 06.612-000 | R27: JANDIRA | S27: 06612-000 | T27: 01.743.404/0001-38 | U27: 398146819119 | W27: FALSE | X27: FALSE | Y27: FALSE | Z27: FALSE | AA27: FALSE | AB27: FALSE | AC27: FALSE | AD27: FALSE | AE27: FALSE | AF27: FALSE | AG27: FALSE | AH27: FALSE | AI27: FALSE | AJ27: FALSE | AK27: FALSE | AL27: FALSE | AM27: FALSE | AN27: FALSE | AO27: FALSE | AP27: FALSE | AQ27: FALSE | AR27: FALSE | AS27: FALSE | AT27: FALSE | AU27: FALSE | AV27: FALSE | AW27: FALSE | AX27: FALSE | AY27: FALSE | AZ27: FALSE | BA27: FALSE | BB27: FALSE | BC27: FALSE | BD27: FALSE | BE27: FALSE | BF27: FALSE | BG27: FALSE | BH27: FALSE | BI27: FALSE | BJ27: FALSE | BK27: FALSE | BM27: 328
A28: 01846213000100 | B28: 01846213 | C28: TRANSP.ANTONIO E FILHOS LTDA ME | D28: TAF | E28: ANTONIO AZEVEDO DE SOUZA | F28: 1142072602 | G28: transp.a@uol.com.br; | I28: ALEXANDRE 1*57228 | J28: TRUE | K28: FABIO ALVES CORDEIRO | L28: TRUE | N28: SP | P28: FALSE | Q28: R CAJAMAR,180 | R28: CARAPICUIBA | S28: 6385500 | T28: 01846213000100 | U28: 255.097.578.113 | W28: FALSE | X28: FALSE | Y28: FALSE | Z28: FALSE | AA28: FALSE | AB28: FALSE | AC28: FALSE | AD28: FALSE | AE28: FALSE | AF28: FALSE | AG28: FALSE | AH28: FALSE | AI28: FALSE | AJ28: FALSE | AK28: FALSE | AL28: FALSE | AM28: FALSE | AN28: FALSE | AO28: FALSE | AP28: FALSE | AQ28: FALSE | AR28: FALSE | AS28: FALSE | AT28: FALSE | AU28: FALSE | AV28: FALSE | AW28: FALSE | AX28: FALSE | AY28: FALSE | AZ28: FALSE | BA28: FALSE | BB28: FALSE | BC28: FALSE | BD28: FALSE | BE28: FALSE | BF28: FALSE | BG28: FALSE | BH28: FALSE | BI28: FALSE | BJ28: FALSE | BK28: FALSE | BM28: 31
A29: 01.920.934/0001-04 | B29: 01920934 | C29: RODOVIARIO CRISMARA LTDA | D29: RODOVIARIO CRISMARA | E29: TOMAS | F29: 17 99718-8402 | G29: tomas.guidoti@crismara-plataforma.com.br; | H29: ANTT: 006928265 | J29: FALSE | K29: FABIO ALVES CORDEIRO | L29: TRUE | N29: SP | P29: FALSE | Q29: AVENIDA LUIZ BRAMBATTI, 1304 - Bairro PARQUE INDUSTRIAL III MITUO KAZUME - FERNANDOPOLIS - SP | R29: FERNANDOPOLIS | S29: 15.612-490 | T29: 01.920.934/0001-04 | U29: 304.109.143.110 | W29: FALSE | X29: FALSE | Y29: FALSE | Z29: FALSE | AA29: FALSE | AB29: FALSE | AC29: FALSE | AD29: FALSE | AE29: FALSE | AF29: FALSE | AG29: FALSE | AH29: FALSE | AI29: FALSE | AJ29: FALSE | AK29: FALSE | AL29: FALSE | AM29: FALSE | AN29: FALSE | AO29: FALSE | AP29: FALSE | AQ29: FALSE | AR29: FALSE | AS29: FALSE | AT29: FALSE | AU29: FALSE | AV29: FALSE | AW29: FALSE | AX29: FALSE | AY29: FALSE | AZ29: FALSE | BA29: FALSE | BB29: FALSE | BC29: FALSE | BD29: FALSE | BE29: FALSE | BF29: FALSE | BG29: FALSE | BH29: FALSE | BI29: FALSE | BJ29: FALSE | BK29: FALSE | BL29: 45807.462 | BM29: 1270
A30: 02.149.012/0001-08 | B30: 02149012 | C30: CONCEPT TRANSPORTE DE CARGAS LTDA | D30: CONCEPT | E30: DAIVID LIMA DE FREITAS | F30: (71) 99249-6666 - (71) 3292-1477 | G30: transporte.concept@gmail.com; marcio@holdingcontabilidade.com.br; | H30: ANTT 03421268 | J30: FALSE | K30: FABIO ALVES CORDEIRO | L30: TRUE | N30: BA | P30: FALSE | Q30: R DOS CURSILHISTAS, 53 - EMPRESARIAL - CENTER PIRAJA SALA: 108 - DOM AVELAR - SALVADOR - BA - CEP: 41315-002 | R30: SALVADOR | S30: 41315-002 | T30: 02.149.012/0001-08 | U30: 052922172 | W30: FALSE | X30: FALSE | Y30: FALSE | Z30: FALSE | AA30: FALSE | AB30: FALSE | AC30: FALSE | AD30: FALSE | AE30: FALSE | AF30: FALSE | AG30: FALSE | AH30: FALSE | AI30: FALSE | AJ30: FALSE | AK30: FALSE | AL30: FALSE | AM30: FALSE | AN30: FALSE | AO30: FALSE | AP30: FALSE | AQ30: FALSE | AR30: FALSE | AS30: FALSE | AT30: FALSE | AU30: FALSE | AV30: FALSE | AW30: FALSE | AX30: FALSE | AY30: FALSE | AZ30: FALSE | BA30: FALSE | BB30: FALSE | BC30: FALSE | BD30: FALSE | BE30: FALSE | BF30: FALSE | BG30: FALSE | BH30: FALSE | BI30: FALSE | BJ30: FALSE | BK30: FALSE | BM30: 671
A31: 02.199.242/0001-81 | B31: 02199242 | C31: JCG TRANSPORTES EIRELI | D31: GUEDES TRANSPORTES | E31: JOSE CLAUDIO GUEDES DA SILVA | F31: (71) 99632-6186 | G31: lidiafigueredo@ramosfigueredo.com.br; swellington@transguedes.com.br; brjguedes@transguedes.com.br;jguedes@transguedes.com.br; | J31: FALSE | K31: FABIO ALVES CORDEIRO | L31: TRUE | N31: BA | P31: FALSE | Q31: AV ALIOMAR BALEEIRO, 188 - B GRANJAS RURAIS PRESIDENTE VARGAS - SALVADOR - BA - CEP: 41230-150 | R31: SALVADOR | S31: 41230-150 | T31: 02.199.242/0001-81 | U31: 54534630 | W31: FALSE | X31: FALSE | Y31: FALSE | Z31: FALSE | AA31: FALSE | AB31: FALSE | AC31: FALSE | AD31: FALSE | AE31: FALSE | AF31: FALSE | AG31: FALSE | AH31: FALSE | AI31: FALSE | AJ31: FALSE | AK31: FALSE | AL31: FALSE | AM31: FALSE | AN31: FALSE | AO31: FALSE | AP31: FALSE | AQ31: FALSE | AR31: FALSE | AS31: FALSE | AT31: FALSE | AU31: FALSE | AV31: FALSE | AW31: FALSE | AX31: FALSE | AY31: FALSE | AZ31: FALSE | BA31: FALSE | BB31: FALSE | BC31: FALSE | BD31: FALSE | BE31: FALSE | BF31: FALSE | BG31: FALSE | BH31: FALSE | BI31: FALSE | BJ31: FALSE | BK31: FALSE | BM31: 673
A32: 02.200.990/0001-37 | B32: 02200990 | C32: TRANSPORTES TAVARES LTDA | D32: TRANSPORTES TAVARES | E32: MILTON | F32: (61) 99625-6397 | G32: transportestavares02@gmail.com; | H32: direto pelo Carrefour | J32: FALSE | K32: FABIO ALVES CORDEIRO | L32: TRUE | N32: DF | P32: FALSE | Q32: MODULO 1 S/N LOTE: 08 - CONDOMINIO RESIDENCIAL SANTA MARIA - SANTA MARIA - DF | R32: BRASILIA | S32: 72580-100 | T32: 02.200.990/0001-37 | U32: 754745700121 | W32: FALSE | X32: FALSE | Y32: FALSE | Z32: FALSE | AA32: FALSE | AB32: FALSE | AC32: FALSE | AD32: FALSE | AE32: FALSE | AF32: FALSE | AG32: FALSE | AH32: FALSE | AI32: FALSE | AJ32: FALSE | AK32: FALSE | AL32: FALSE | AM32: FALSE | AN32: FALSE | AO32: FALSE | AP32: FALSE | AQ32: TRUE | AR32: FALSE | AS32: FALSE | AT32: FALSE | AU32: FALSE | AV32: FALSE | AW32: FALSE | AX32: FALSE | AY32: FALSE | AZ32: FALSE | BA32: FALSE | BB32: FALSE | BC32: FALSE | BD32: FALSE | BE32: FALSE | BF32: FALSE | BG32: FALSE | BH32: FALSE | BI32: FALSE | BJ32: FALSE | BK32: FALSE | BM32: 606
A33: 024.814.314-05 | B33: 02481431405 | C33: MARCIO LIRA DE ARAUJO | D33: MARCIO LIRA DE ARAUJO | E33: MARCIO | F33: (81) 98272-4533 | G33: marciolira185@gmail.com; | J33: FALSE | K33: FABIO ALVES CORDEIRO | L33: TRUE | N33: PE | P33: FALSE | Q33: RUA PALMEIRA, 97 - LOTE 92 - JABOATAO DOS GUARARAPES - PE -54000000 | R33: JABOATAO DOS GUARARAPES | S33: 54000000 | T33: 024.814.314-05 | W33: FALSE | X33: FALSE | Y33: FALSE | Z33: FALSE | AA33: FALSE | AB33: FALSE | AC33: FALSE | AD33: FALSE | AE33: FALSE | AF33: FALSE | AG33: FALSE | AH33: FALSE | AI33: FALSE | AJ33: FALSE | AK33: FALSE | AL33: FALSE | AM33: FALSE | AN33: FALSE | AO33: FALSE | AP33: FALSE | AQ33: FALSE | AR33: FALSE | AS33: FALSE | AT33: FALSE | AU33: FALSE | AV33: FALSE | AW33: FALSE | AX33: FALSE | AY33: FALSE | AZ33: FALSE | BA33: FALSE | BB33: FALSE | BC33: FALSE | BD33: FALSE | BE33: FALSE | BF33: FALSE | BG33: FALSE | BH33: FALSE | BI33: FALSE | BJ33: FALSE | BK33: FALSE | BL33: 45670.358 | BM33: 1200
A34: 027.738.854-65 | B34: 02773885465 | C34: WILLIAM FERNANDO BATISTA DA SILVA | D34: WILLIAM FERNANDO BATISTA DA SILVA | E34: WILLIAM FERNANDO BATISTA DA SILVA | F34: (81) 7103-1500 | J34: FALSE | K34: FABIO ALVES CORDEIRO | L34: TRUE | N34: SP | P34: FALSE | Q34: RUA JOAQUIM ANTONIO ALVES, 189 - PARQUE PLANALTO - SÃO PAULO - SP | R34: SÃO PAULO | S34: 04841250 | T34: 027.738.854-65 | W34: FALSE | X34: FALSE | Y34: FALSE | Z34: FALSE | AA34: FALSE | AB34: FALSE | AC34: FALSE | AD34: FALSE | AE34: FALSE | AF34: FALSE | AG34: FALSE | AH34: FALSE | AI34: FALSE | AJ34: FALSE | AK34: FALSE | AL34: FALSE | AM34: FALSE | AN34: FALSE | AO34: FALSE | AP34: FALSE | AQ34: FALSE | AR34: FALSE | AS34: FALSE | AT34: FALSE | AU34: FALSE | AV34: FALSE | AW34: FALSE | AX34: FALSE | AY34: FALSE | AZ34: FALSE | BA34: FALSE | BB34: FALSE | BC34: FALSE | BD34: FALSE | BE34: FALSE | BF34: FALSE | BG34: FALSE | BH34: FALSE | BI34: FALSE | BJ34: FALSE | BK34: FALSE | BL34: 45813.739 | BM34: 1289
A35: 030.532.089-03 | B35: 03053208903 | C35: ALCIDES SELL | D35: ALCIDES SELL | E35: ALCIDES SELL | F35: (47) 99112-9867 | G35: alcidessell@hotmail.com; | J35: FALSE | K35: FABIO ALVES CORDEIRO | L35: TRUE | N35: SC | P35: FALSE | Q35: rua valdemar zink, 138 - CENTRO - BLUMENAU - SC | R35: BLUMENAU | S35: 89063085 | T35: 030.532.089-03 | W35: FALSE | X35: FALSE | Y35: FALSE | Z35: FALSE | AA35: FALSE | AB35: FALSE | AC35: FALSE | AD35: FALSE | AE35: FALSE | AF35: FALSE | AG35: FALSE | AH35: FALSE | AI35: FALSE | AJ35: FALSE | AK35: FALSE | AL35: FALSE | AM35: FALSE | AN35: FALSE | AO35: FALSE | AP35: FALSE | AQ35: FALSE | AR35: FALSE | AS35: FALSE | AT35: FALSE | AU35: FALSE | AV35: FALSE | AW35: FALSE | AX35: FALSE | AY35: FALSE | AZ35: FALSE | BA35: FALSE | BB35: FALSE | BC35: FALSE | BD35: FALSE | BE35: FALSE | BF35: FALSE | BG35: FALSE | BH35: FALSE | BI35: FALSE | BJ35: FALSE | BK35: FALSE | BL35: 45841.477 | BM35: 1322
A36: 032.707.918-52 | B36: 03270791852 | C36: ANTONIO APARECIDO ALVES | D36: ANTONIO APARECIDO ALVES | E36: ANTONIO | F36: (11) 99425-8056 / 11-96300-5208 | G36: logistica.onix@gmail.com; | H36: ANTT: 12792876 - PIS: 12792876 | J36: FALSE | K36: FABIO ALVES CORDEIRO | L36: TRUE | N36: SP | P36: FALSE | Q36: Luiz Rink, S/N - MUTINGA - OSASCO - SP - CEP: 06286000 | R36: OSASCO | S36: 06286000 | T36: 032.707.918-52 | W36: FALSE | X36: FALSE | Y36: FALSE | Z36: FALSE | AA36: FALSE | AB36: FALSE | AC36: FALSE | AD36: FALSE | AE36: FALSE | AF36: FALSE | AG36: FALSE | AH36: FALSE | AI36: FALSE | AJ36: FALSE | AK36: FALSE | AL36: FALSE | AM36: FALSE | AN36: FALSE | AO36: FALSE | AP36: FALSE | AQ36: FALSE | AR36: FALSE | AS36: FALSE | AT36: FALSE | AU36: FALSE | AV36: FALSE | AW36: FALSE | AX36: FALSE | AY36: FALSE | AZ36: FALSE | BA36: FALSE | BB36: FALSE | BC36: FALSE | BD36: FALSE | BE36: FALSE | BF36: FALSE | BG36: FALSE | BH36: FALSE | BI36: FALSE | BJ36: FALSE | BK36: FALSE | BM36: 1061
A37: 03340367000142 | B37: 03340367 | C37: TRANSMAZONI TRANSPORTES DE CARGAS | D37: TRANSMAZONI | E37: EDILSON | F37: 11-4188-6123 | G37: transmazoni@ig.com.br ; | I37: 30*32061 | J37: TRUE | K37: FABIO ALVES CORDEIRO | L37: TRUE | N37: SP | P37: FALSE | Q37: RUA PORTUGAL, 55 | R37: CARAPICUIBA | S37: 6385000 | T37: 03340367000142 | U37: 255.112.577.118 | W37: FALSE | X37: FALSE | Y37: FALSE | Z37: FALSE | AA37: FALSE | AB37: FALSE | AC37: FALSE | AD37: FALSE | AE37: FALSE | AF37: FALSE | AG37: FALSE | AH37: FALSE | AI37: FALSE | AJ37: FALSE | AK37: FALSE | AL37: FALSE | AM37: FALSE | AN37: FALSE | AO37: FALSE | AP37: FALSE | AQ37: FALSE | AR37: FALSE | AS37: FALSE | AT37: FALSE | AU37: FALSE | AV37: FALSE | AW37: FALSE | AX37: FALSE | AY37: FALSE | AZ37: FALSE | BA37: FALSE | BB37: FALSE | BC37: FALSE | BD37: FALSE | BE37: FALSE | BF37: FALSE | BG37: FALSE | BH37: FALSE | BI37: FALSE | BJ37: FALSE | BK37: FALSE | BM37: 71
A38: 03.362.521/0003-49 | B38: 03362521 | C38: CARGO BRASIL LTDA | D38: CARGO BRASIL URGENTE | F38: (47) 3371-0363 / (11) 4498-0694 | J38: FALSE | K38: FABIO ALVES CORDEIRO | L38: TRUE | N38: AM | P38: FALSE | Q38: AV PRESIDENTE KENNEDY, 885 - GALPAO B-4 - BAIRRO DA LIBERDADE - MANAUS - AM | R38: MANAUS | S38: 69074695 | T38: 03.362.521/0003-49 | U38: 053909151 | W38: FALSE | X38: FALSE | Y38: FALSE | Z38: FALSE | AA38: FALSE | AB38: FALSE | AC38: FALSE | AD38: FALSE | AE38: FALSE | AF38: FALSE | AG38: FALSE | AH38: FALSE | AI38: FALSE | AJ38: FALSE | AK38: FALSE | AL38: FALSE | AM38: FALSE | AN38: FALSE | AO38: FALSE | AP38: FALSE | AQ38: FALSE | AR38: FALSE | AS38: FALSE | AT38: FALSE | AU38: FALSE | AV38: FALSE | AW38: FALSE | AX38: FALSE | AY38: FALSE | AZ38: FALSE | BA38: FALSE | BB38: FALSE | BC38: FALSE | BD38: FALSE | BE38: FALSE | BF38: FALSE | BG38: FALSE | BH38: FALSE | BI38: FALSE | BJ38: FALSE | BK38: FALSE | BL38: 45814.496 | BM38: 1297
A39: 035.282.014-44 | B39: 03528201444 | C39: ISAIAS GOMES DA SILVA | D39: ISAIAS GOMES DA SILVA | E39: ISAIAS | F39: 81-981473123 | G39: gomesdasilvaisaias930@gmail.com; | H39: TAC ANTT 057588455 | J39: FALSE | K39: FABIO ALVES CORDEIRO | L39: TRUE | N39: SP | P39: FALSE | Q39: SITIO AGUAS VERMELHAS,50 CASA - AMARAJIRURAL - AMARAJI - SP | R39: AMARAJI | S39: 55515000 | T39: 035.282.014-44 | W39: FALSE | X39: FALSE | Y39: FALSE | Z39: FALSE | AA39: FALSE | AB39: FALSE | AC39: FALSE | AD39: FALSE | AE39: FALSE | AF39: FALSE | AG39: FALSE | AH39: FALSE | AI39: FALSE | AJ39: FALSE | AK39: FALSE | AL39: FALSE | AM39: FALSE | AN39: FALSE | AO39: FALSE | AP39: FALSE | AQ39: FALSE | AR39: FALSE | AS39: FALSE | AT39: FALSE | AU39: FALSE | AV39: FALSE | AW39: FALSE | AX39: FALSE | AY39: FALSE | AZ39: FALSE | BA39: FALSE | BB39: FALSE | BC39: FALSE | BD39: FALSE | BE39: FALSE | BF39: FALSE | BG39: FALSE | BH39: FALSE | BI39: FALSE | BJ39: FALSE | BK39: FALSE | BL39: 45764.584 | BM39: 1256
A40: 03812091000158 | B40: 03812091 | C40: CLARO TRANSPORTES E LOGISTICA LTDA | D40: CLARO TRANSPORTES E LOGISTICA LTDA | E40: PEDRO | F40: 11932990937 | G40: Pedro.Jesus@clarotransportes.com.br; | J40: FALSE | K40: FABIO ALVES CORDEIRO | L40: TRUE | N40: SP | P40: FALSE | Q40: ALAMEDA ARAGUAIA, 3887 - ALPHAVILLE INDUSTRIAL - SP | R40: BARUERI | S40: 06.455-000 | T40: 03812091000158 | U40: 206.172.250.110 | W40: FALSE | X40: FALSE | Y40: FALSE | Z40: FALSE | AA40: FALSE | AB40: FALSE | AC40: FALSE | AD40: FALSE | AE40: FALSE | AF40: FALSE | AG40: FALSE | AH40: TRUE | AI40: FALSE | AJ40: FALSE | AK40: FALSE | AL40: FALSE | AM40: FALSE | AN40: FALSE | AO40: FALSE | AP40: FALSE | AQ40: FALSE | AR40: FALSE | AS40: FALSE | AT40: FALSE | AU40: TRUE | AV40: FALSE | AW40: FALSE | AX40: FALSE | AY40: FALSE | AZ40: FALSE | BA40: FALSE | BB40: FALSE | BC40: FALSE | BD40: FALSE | BE40: FALSE | BF40: FALSE | BG40: FALSE | BH40: FALSE | BI40: FALSE | BJ40: FALSE | BK40: FALSE | BM40: 557
A41: 03.831.403/0011-42 | B41: 03831403 | C41: TRANSMARONI TRANSPORTES BRASIL RODOVIARIOS LTDA | D41: TRANSMARONI | E41: CASAROTTO / JEFFERSON | F41: 11-3837-8842 / 98937-1938 Gean | G41: CASAROTTO@TRANSMARONI.COM.BR; jmendes@transmaroni.com.br; dluiz@transmaroni.com.br; | J41: TRUE | K41: FABIO ALVES CORDEIRO | L41: TRUE | N41: RJ | P41: FALSE | Q41: AVENIDA COELHO DA ROCHA 364 GALPAO2 MOD 204 205 206 2 SALA 9 - CENTRO- BELFORD ROXO | R41: BELFORD ROXO | S41: 26130-130 | T41: 03.831.403/0011-42 | W41: FALSE | X41: FALSE | Y41: FALSE | Z41: FALSE | AA41: FALSE | AB41: FALSE | AC41: FALSE | AD41: FALSE | AE41: FALSE | AF41: FALSE | AG41: FALSE | AH41: FALSE | AI41: FALSE | AJ41: FALSE | AK41: FALSE | AL41: FALSE | AM41: FALSE | AN41: FALSE | AO41: FALSE | AP41: FALSE | AQ41: FALSE | AR41: FALSE | AS41: FALSE | AT41: FALSE | AU41: FALSE | AV41: FALSE | AW41: FALSE | AX41: FALSE | AY41: FALSE | AZ41: FALSE | BA41: FALSE | BB41: FALSE | BC41: FALSE | BD41: FALSE | BE41: FALSE | BF41: FALSE | BG41: FALSE | BH41: FALSE | BI41: FALSE | BJ41: FALSE | BK41: FALSE | BM41: 365
A42: 03.831.403/0001-70 | B42: 03831403000170 | C42: TRANSMARONI TRANSPORTES BRASIL RODOVIARIOS LTDA | D42: TRANSMARONI | E42: CASAROTTO / JEFFERSON | F42: 11-3837-8842 / 98937-1938 Gean | G42: CASAROTTO@TRANSMARONI.COM.BR; jmendes@transmaroni.com.br; dluiz@transmaroni.com.br; | J42: FALSE | K42: FABIO ALVES CORDEIRO | L42: TRUE | N42: RJ | P42: FALSE | Q42: AVENIDA COELHO DA ROCHA 364 GALPAO2 MOD 204 205 206 2 SALA 9 - CENTRO- BELFORD ROXO | R42: BELFORD ROXO | S42: 26130-130 | T42: 03.831.403/0001-70 | W42: FALSE | X42: FALSE | Y42: FALSE | Z42: FALSE | AA42: FALSE | AB42: FALSE | AC42: FALSE | AD42: FALSE | AE42: FALSE | AF42: FALSE | AG42: FALSE | AH42: FALSE | AI42: FALSE | AJ42: FALSE | AK42: FALSE | AL42: FALSE | AM42: FALSE | AN42: FALSE | AO42: FALSE | AP42: FALSE | AQ42: FALSE | AR42: FALSE | AS42: FALSE | AT42: FALSE | AU42: FALSE | AV42: FALSE | AW42: FALSE | AX42: FALSE | AY42: FALSE | AZ42: FALSE | BA42: FALSE | BB42: FALSE | BC42: FALSE | BD42: FALSE | BE42: FALSE | BF42: FALSE | BG42: FALSE | BH42: FALSE | BI42: FALSE | BJ42: FALSE | BK42: FALSE | BL42: 45708.667 | BM42: 1233
A43: 03.831.403/0002-51 | B43: 03831403000251 | C43: TRANSMARONI TRANSPORTES BRASIL RODOVIARIOS LTDA | D43: TRANSMARONI | E43: CASAROTTO / JEFFERSON | F43: 11-3837-8842 / 98937-1938 Gean | G43: CASAROTTO@TRANSMARONI.COM.BR; jmendes@transmaroni.com.br; dluiz@transmaroni.com.br; | J43: FALSE | K43: FABIO ALVES CORDEIRO | L43: TRUE | N43: BA | P43: FALSE | Q43: Rodovia Br 116 SN Km 425 Sala 1 - Novo Horizonte - Feira de Santana BA | R43: Feira de Santana | S43: 44036-331 | T43: 03.831.403/0002-51 | W43: FALSE | X43: FALSE | Y43: FALSE | Z43: FALSE | AA43: FALSE | AB43: FALSE | AC43: FALSE | AD43: FALSE | AE43: FALSE | AF43: FALSE | AG43: FALSE | AH43: FALSE | AI43: FALSE | AJ43: FALSE | AK43: FALSE | AL43: FALSE | AM43: FALSE | AN43: FALSE | AO43: FALSE | AP43: FALSE | AQ43: FALSE | AR43: FALSE | AS43: FALSE | AT43: FALSE | AU43: FALSE | AV43: FALSE | AW43: FALSE | AX43: FALSE | AY43: FALSE | AZ43: FALSE | BA43: FALSE | BB43: FALSE | BC43: FALSE | BD43: FALSE | BE43: FALSE | BF43: FALSE | BG43: FALSE | BH43: FALSE | BI43: FALSE | BJ43: FALSE | BK43: FALSE | BL43: 45830.644 | BM43: 1308
A44: 03.945.518/0001-96 | B44: 03945518 | C44: ELITE EXPRESS LTDA | D44: MWM TRANSPORTES | E44: LEONARDO / WAGNER - PROPRIETARIO | F44: 27-99794-7941 / 99983-9812 | G44: leonardo@mwmtransportes.com; wagner@mwmtransportes.com; | H44: ANTT: 55504244 | J44: FALSE | K44: FABIO ALVES CORDEIRO | L44: TRUE | N44: ES | P44: FALSE | Q44: ROD GOVERNADOR JOSE HENRIQUE SETTE, 68 - GALPAO 02 - B. ALTO LAGE - CARIACICA - ES - CEP: 29151-055 | R44: CARIACICA | S44: 29151-055 | T44: 03.945.518/0001-96 | U44: 03.945.518/0001-96 | V44: Seca | W44: FALSE | X44: FALSE | Y44: FALSE | Z44: FALSE | AA44: FALSE | AB44: FALSE | AC44: FALSE | AD44: FALSE | AE44: FALSE | AF44: FALSE | AG44: FALSE | AH44: TRUE | AI44: FALSE | AJ44: FALSE | AK44: FALSE | AL44: FALSE | AM44: FALSE | AN44: FALSE | AO44: FALSE | AP44: FALSE | AQ44: TRUE | AR44: TRUE | AS44: TRUE | AT44: FALSE | AU44: FALSE | AV44: FALSE | AW44: FALSE | AX44: FALSE | AY44: FALSE | AZ44: FALSE | BA44: FALSE | BB44: FALSE | BC44: FALSE | BD44: FALSE | BE44: FALSE | BF44: FALSE | BG44: FALSE | BH44: FALSE | BI44: FALSE | BJ44: TRUE | BK44: FALSE | BL44: 45483.432 | BM44: 640
A45: 04142031000138 | B45: 04142031 | C45: ENTRE PONTOS EXPRESS LTDA | D45: ENTRE PONTOS EXPRESS LTDA | E45: VICTORIA FIBLA | F45: 11-94932-0985 / 11 93245-0470 | G45: comercial@entrepontos.com.br; bruna.lupianhas@entrepontos.com.br; | J45: FALSE | K45: FABIO ALVES CORDEIRO | L45: TRUE | N45: SP | P45: FALSE | Q45: RUA BERNARDO GUIMARAES, 234 - VILA ANASTACIO - SAO PAULO - SP - CEP 05.092-030 | R45: SÃO PAULO | S45: 05.092-030 | T45: 04142031000138 | U45: 116132287110 | W45: FALSE | X45: FALSE | Y45: FALSE | Z45: FALSE | AA45: FALSE | AB45: FALSE | AC45: FALSE | AD45: FALSE | AE45: FALSE | AF45: FALSE | AG45: FALSE | AH45: FALSE | AI45: FALSE | AJ45: FALSE | AK45: FALSE | AL45: FALSE | AM45: TRUE | AN45: FALSE | AO45: FALSE | AP45: FALSE | AQ45: TRUE | AR45: FALSE | AS45: FALSE | AT45: FALSE | AU45: FALSE | AV45: FALSE | AW45: FALSE | AX45: TRUE | AY45: FALSE | AZ45: FALSE | BA45: FALSE | BB45: FALSE | BC45: FALSE | BD45: FALSE | BE45: FALSE | BF45: FALSE | BG45: FALSE | BH45: FALSE | BI45: FALSE | BJ45: TRUE | BK45: TRUE | BM45: 622
A46: 042.891.185-42 | B46: 04289118542 | C46: CLAUDINEI FERREIRA MOREIRA | D46: CLAUDINEI FERREIRA MOREIRA | E46: CLAUDINEI FERREIRA MOREIRA | F46: (11) 94005-0276 | G46: neynanamoreira@gmail.com; | J46: FALSE | K46: FABIO ALVES CORDEIRO | L46: TRUE | N46: BA | P46: FALSE | Q46: RUA ANALIA PINHEIRO, 0168 - BAIRRO CRUZEIRO - JAGUAQUARA - BA | R46: JAGUAQUARA | S46: 45345000 | T46: 042.891.185-42 | W46: FALSE | X46: FALSE | Y46: FALSE | Z46: FALSE | AA46: FALSE | AB46: FALSE | AC46: FALSE | AD46: FALSE | AE46: FALSE | AF46: FALSE | AG46: FALSE | AH46: FALSE | AI46: FALSE | AJ46: FALSE | AK46: FALSE | AL46: FALSE | AM46: FALSE | AN46: FALSE | AO46: FALSE | AP46: FALSE | AQ46: FALSE | AR46: FALSE | AS46: FALSE | AT46: FALSE | AU46: FALSE | AV46: FALSE | AW46: FALSE | AX46: FALSE | AY46: FALSE | AZ46: FALSE | BA46: FALSE | BB46: FALSE | BC46: FALSE | BD46: FALSE | BE46: FALSE | BF46: FALSE | BG46: FALSE | BH46: FALSE | BI46: FALSE | BJ46: FALSE | BK46: FALSE | BL46: 45813.708 | BM46: 1286
A47: 04509995000171 | B47: 04509995 | C47: TRANS TOUR ENVIAR & RECEBER LTDA | D47: TRANS TOUR ENVIAR & RECEBER LTDA | E47: CAIO FONTES | F47: (11) 3255-5656 / (11) 9475-14046 | J47: FALSE | K47: FABIO ALVES CORDEIRO | L47: TRUE | N47: SP | P47: FALSE | Q47: R AMARO CAVALHEIRO, 28 -PINHEIROS - SÃO PAULO - 05.425-010 | R47: SÃO PAULO | S47: 05.425-010 | T47: 04509995000171 | U47: 117215186112 | V47: Seca | W47: FALSE | X47: FALSE | Y47: FALSE | Z47: FALSE | AA47: FALSE | AB47: FALSE | AC47: FALSE | AD47: FALSE | AE47: FALSE | AF47: FALSE | AG47: FALSE | AH47: FALSE | AI47: FALSE | AJ47: FALSE | AK47: FALSE | AL47: FALSE | AM47: FALSE | AN47: FALSE | AO47: FALSE | AP47: FALSE | AQ47: FALSE | AR47: FALSE | AS47: FALSE | AT47: FALSE | AU47: FALSE | AV47: FALSE | AW47: FALSE | AX47: FALSE | AY47: FALSE | AZ47: FALSE | BA47: FALSE | BB47: FALSE | BC47: FALSE | BD47: FALSE | BE47: FALSE | BF47: FALSE | BG47: FALSE | BH47: FALSE | BI47: FALSE | BJ47: TRUE | BK47: FALSE | BL47: 45455.642 | BM47: 626
A48: 04571045000177 | B48: 04571045 | C48: TOTAL - TRANSPORTES E LOGISTICA LTDA | D48: TOTAL - TRANSPORTES E LOGISTICA LTDA | F48: 31-99637-9196 | J48: FALSE | K48: FABIO ALVES CORDEIRO | L48: TRUE | N48: MG | P48: FALSE | Q48: AVENIDA JUIZ MARCO TULIO, 10990 | R48: BETIM | S48: 32676358 | T48: 04571045000177 | U48: 3131448970083 | W48: FALSE | X48: FALSE | Y48: FALSE | Z48: FALSE | AA48: FALSE | AB48: FALSE | AC48: FALSE | AD48: FALSE | AE48: FALSE | AF48: FALSE | AG48: FALSE | AH48: FALSE | AI48: FALSE | AJ48: FALSE | AK48: FALSE | AL48: FALSE | AM48: FALSE | AN48: FALSE | AO48: FALSE | AP48: FALSE | AQ48: FALSE | AR48: FALSE | AS48: FALSE | AT48: FALSE | AU48: TRUE | AV48: FALSE | AW48: FALSE | AX48: FALSE | AY48: FALSE | AZ48: FALSE | BA48: FALSE | BB48: FALSE | BC48: FALSE | BD48: FALSE | BE48: FALSE | BF48: FALSE | BG48: FALSE | BH48: FALSE | BI48: FALSE | BJ48: TRUE | BK48: FALSE | BM48: 577
A49: 04647323000122 | B49: 04647323 | C49: TRANS-LEKK'S LTDA - ME | D49: TRANS LEKK | E49: EDUARDO | F49: 11-3375-9711 | G49: ELIZAYOGUI@HOTMAIL.COM; | J49: TRUE | K49: FABIO ALVES CORDEIRO | L49: TRUE | N49: SP | P49: FALSE | Q49: AV ENGENHEIRO GEORGE CORBISIER,1141 | R49: SÃO PAULO | S49: 4345001 | T49: 04647323000122 | U49: - | W49: FALSE | X49: FALSE | Y49: FALSE | Z49: FALSE | AA49: FALSE | AB49: FALSE | AC49: FALSE | AD49: FALSE | AE49: FALSE | AF49: FALSE | AG49: FALSE | AH49: FALSE | AI49: FALSE | AJ49: FALSE | AK49: FALSE | AL49: FALSE | AM49: FALSE | AN49: FALSE | AO49: FALSE | AP49: FALSE | AQ49: FALSE | AR49: FALSE | AS49: FALSE | AT49: FALSE | AU49: FALSE | AV49: FALSE | AW49: FALSE | AX49: FALSE | AY49: FALSE | AZ49: FALSE | BA49: FALSE | BB49: FALSE | BC49: FALSE | BD49: FALSE | BE49: FALSE | BF49: FALSE | BG49: FALSE | BH49: FALSE | BI49: FALSE | BJ49: FALSE | BK49: FALSE | BM49: 444
A50: 04.697.636/0001-95 | B50: 04697636 | C50: ROTRANS TRANSPORTES E SERVICOS LTDA | D50: ROTRANS TRANSPORTES E SERVIÇOS LTDA | E50: JOSE ROBERTO PEREIRA DA SILVEIRA | F50: (75) 2102-7903 | G50: logistica@rotrans.com.br; contabilidade@rotrans.com.br; deyse.souza@rotrans.com.br; apoio.gestao@rotrans.com.br; betlei.silveira@rotrans.com.br; julia.silveira@rotrans.com.br; ana.carolina@rotrans.com.br; contabilidade@rotrans.com.br; | J50: FALSE | K50: FABIO ALVES CORDEIRO | L50: TRUE | N50: BA | P50: FALSE | Q50: AV DEPUTADO LUIS EDUARDO MAGALHAES, S/N - FEIRA DE SANTANA - BA - CEP: 44079-002 | R50: FEIRA DE SANTANA - BA | S50: 44079-002 | T50: 04.697.636/0001-95 | W50: FALSE | X50: FALSE | Y50: FALSE | Z50: FALSE | AA50: FALSE | AB50: FALSE | AC50: FALSE | AD50: FALSE | AE50: FALSE | AF50: FALSE | AG50: FALSE | AH50: FALSE | AI50: FALSE | AJ50: FALSE | AK50: FALSE | AL50: FALSE | AM50: FALSE | AN50: FALSE | AO50: FALSE | AP50: FALSE | AQ50: FALSE | AR50: FALSE | AS50: FALSE | AT50: FALSE | AU50: FALSE | AV50: FALSE | AW50: FALSE | AX50: FALSE | AY50: FALSE | AZ50: FALSE | BA50: FALSE | BB50: FALSE | BC50: FALSE | BD50: FALSE | BE50: FALSE | BF50: FALSE | BG50: FALSE | BH50: FALSE | BI50: FALSE | BJ50: FALSE | BK50: FALSE | BM50: 674
A51: 047.536.639-57 | B51: 04753663957 | C51: ELCIO MEISEN | D51: ELCIO MEISEN | E51: ELCIO MEISEN | F51: 47- 99911-0228 | G51: elciomeisen@gmail.com; | J51: FALSE | K51: FABIO ALVES CORDEIRO | L51: TRUE | N51: SC | P51: FALSE | Q51: RUA Jordão Amâncio do Nascimento, 539 - JOINVILLE - SC | R51: JOINVILLE | S51: 89230761 | T51: 047.536.639-57 | W51: FALSE | X51: FALSE | Y51: FALSE | Z51: FALSE | AA51: FALSE | AB51: FALSE | AC51: FALSE | AD51: FALSE | AE51: FALSE | AF51: FALSE | AG51: FALSE | AH51: FALSE | AI51: FALSE | AJ51: FALSE | AK51: FALSE | AL51: FALSE | AM51: FALSE | AN51: FALSE | AO51: FALSE | AP51: FALSE | AQ51: FALSE | AR51: FALSE | AS51: FALSE | AT51: FALSE | AU51: FALSE | AV51: FALSE | AW51: FALSE | AX51: FALSE | AY51: FALSE | AZ51: FALSE | BA51: FALSE | BB51: FALSE | BC51: FALSE | BD51: FALSE | BE51: FALSE | BF51: FALSE | BG51: FALSE | BH51: FALSE | BI51: FALSE | BJ51: FALSE | BK51: FALSE | BL51: 45846.627 | BM51: 1213
A52: 04.948.785/0001-80 | B52: 04948785 | C52: GLOBAL FREIGHT - AGENCIAMENTO DE CARGA LTDA | D52: GLOBAL FREIGHT - AGENCIAMENTO DE CARGA LTDA | E52: Fabiano Reis | F52: (13) 3212-9101 | G52: fabiano@globalfreight.com.br; lima@globalfreight.com.br; | J52: FALSE | K52: FABIO ALVES CORDEIRO | L52: TRUE | N52: SP | P52: FALSE | Q52: R AMADOR BUENO, 333 -ANDAR 13 BLOCO B SALA 1315 - CENTRO - SANTOS - SP - CEP: 11.013-151 | R52: SANTOS | S52: 11.013-151 | T52: 04.948.785/0001-80 | U52: 633593831110 | W52: FALSE | X52: FALSE | Y52: FALSE | Z52: FALSE | AA52: FALSE | AB52: FALSE | AC52: FALSE | AD52: FALSE | AE52: FALSE | AF52: FALSE | AG52: FALSE | AH52: FALSE | AI52: FALSE | AJ52: FALSE | AK52: FALSE | AL52: FALSE | AM52: FALSE | AN52: FALSE | AO52: FALSE | AP52: FALSE | AQ52: FALSE | AR52: FALSE | AS52: FALSE | AT52: FALSE | AU52: FALSE | AV52: FALSE | AW52: FALSE | AX52: FALSE | AY52: FALSE | AZ52: FALSE | BA52: FALSE | BB52: FALSE | BC52: FALSE | BD52: FALSE | BE52: FALSE | BF52: FALSE | BG52: FALSE | BH52: FALSE | BI52: FALSE | BJ52: FALSE | BK52: FALSE | BL52: 45708.476 | BM52: 666
A53: 04.995.902/0001-66 | B53: 04995902 | C53: J.R LIMA PERFIS PLASTICOS E TERCEIRIZACAO DE TRANS | D53: ORIGINAL PLASTICOS E TRANSPORTES | E53: PRISCILA | F53: 11995361236 -1141614536 | G53: originaltransportes@terra.com.br; | J53: FALSE | K53: FABIO ALVES CORDEIRO | L53: TRUE | N53: SP | P53: FALSE | Q53: RUA TUPI, 702 B -VILA SAO SILVESTRE - BARUERI - SP | R53: BARUERI | S53: 06417030 | T53: 04.995.902/0001-66 | U53: 206124672115 | W53: FALSE | X53: FALSE | Y53: FALSE | Z53: FALSE | AA53: FALSE | AB53: FALSE | AC53: FALSE | AD53: FALSE | AE53: FALSE | AF53: FALSE | AG53: FALSE | AH53: FALSE | AI53: FALSE | AJ53: FALSE | AK53: FALSE | AL53: FALSE | AM53: FALSE | AN53: FALSE | AO53: FALSE | AP53: FALSE | AQ53: FALSE | AR53: FALSE | AS53: FALSE | AT53: FALSE | AU53: FALSE | AV53: FALSE | AW53: FALSE | AX53: FALSE | AY53: FALSE | AZ53: FALSE | BA53: FALSE | BB53: FALSE | BC53: FALSE | BD53: FALSE | BE53: FALSE | BF53: FALSE | BG53: FALSE | BH53: FALSE | BI53: FALSE | BJ53: FALSE | BK53: FALSE | BM53: 1288
A54: 050.253.025-10 | B54: 05025302510 | C54: LEANDRO DE JESUS MENDONCA | D54: LEANDRO DE JESUS MENDONCA | E54: LEANDRO DE JESUS MENDONCA | F54: (75) 99153-3273 | J54: FALSE | K54: FABIO ALVES CORDEIRO | L54: TRUE | N54: BA | P54: FALSE | Q54: RUA ANALIA PINHEIRO, 0168 JAGUAQUARA - BA - | R54: JAGUAQUARA | S54: 45345000 | T54: 050.253.025-10 | W54: FALSE | X54: FALSE | Y54: FALSE | Z54: FALSE | AA54: FALSE | AB54: FALSE | AC54: FALSE | AD54: FALSE | AE54: FALSE | AF54: FALSE | AG54: FALSE | AH54: FALSE | AI54: FALSE | AJ54: FALSE | AK54: FALSE | AL54: FALSE | AM54: FALSE | AN54: FALSE | AO54: FALSE | AP54: FALSE | AQ54: FALSE | AR54: FALSE | AS54: FALSE | AT54: FALSE | AU54: FALSE | AV54: FALSE | AW54: FALSE | AX54: FALSE | AY54: FALSE | AZ54: FALSE | BA54: FALSE | BB54: FALSE | BC54: FALSE | BD54: FALSE | BE54: FALSE | BF54: FALSE | BG54: FALSE | BH54: FALSE | BI54: FALSE | BJ54: FALSE | BK54: FALSE | BL54: 45813.723 | BM54: 373
A55: 05.131.086/0001-05 | B55: 05131086 | C55: TRANS-ROBERTO TRANSPORTADORA COMERCIAL LTDA | D55: TRANSPORTES RASTREADOS | E55: ROBERTO | F55: (11) 3932-2002 - 3932-8310 (11) 99164-6128 - 1199264-6128 | G55: transroberto@transportesrastreados.com.br; rosa@transportesrastreados.com.br; patricia@transportesrastreados.com.br;heliane@transportesrastreados.com.br; | J55: TRUE | K55: FABIO ALVES CORDEIRO | L55: TRUE | N55: SP | P55: FALSE | Q55: RUA DA BALSA, 909 - BAIRRO JARDIM ARCADIA - SÃO PAULO - SP - CEP: 02910-000 | R55: SÃO PAULO | S55: 02910-000 | T55: 05.131.086/0001-05 | U55: 116.509.070.114 | W55: FALSE | X55: FALSE | Y55: FALSE | Z55: FALSE | AA55: FALSE | AB55: FALSE | AC55: FALSE | AD55: FALSE | AE55: FALSE | AF55: FALSE | AG55: FALSE | AH55: FALSE | AI55: FALSE | AJ55: FALSE | AK55: FALSE | AL55: FALSE | AM55: FALSE | AN55: FALSE | AO55: FALSE | AP55: FALSE | AQ55: FALSE | AR55: FALSE | AS55: FALSE | AT55: FALSE | AU55: FALSE | AV55: FALSE | AW55: FALSE | AX55: FALSE | AY55: FALSE | AZ55: FALSE | BA55: FALSE | BB55: FALSE | BC55: FALSE | BD55: FALSE | BE55: FALSE | BF55: FALSE | BG55: FALSE | BH55: FALSE | BI55: FALSE | BJ55: FALSE | BK55: FALSE | BM55: 648
A56: 05.151.226/0001-07 | B56: 05151226 | C56: EXPRESSO MINAS FRIOS LTDA | D56: EMF LOGISTICA | F56: 3198415052 | G56: luiz@emflogistica.com.br; | J56: FALSE | K56: FABIO ALVES CORDEIRO | L56: TRUE | N56: MG | P56: FALSE | Q56: AV ENGENHEIRO DARCY NOGUEIRA DO PINHO, 3201 - GALPAO7 - BETIM - MG | R56: BETIM | S56: 32.675-515 | T56: 05.151.226/0001-07 | U56: 672063040086 | W56: FALSE | X56: FALSE | Y56: FALSE | Z56: FALSE | AA56: FALSE | AB56: FALSE | AC56: FALSE | AD56: FALSE | AE56: FALSE | AF56: FALSE | AG56: FALSE | AH56: FALSE | AI56: FALSE | AJ56: FALSE | AK56: FALSE | AL56: FALSE | AM56: FALSE | AN56: FALSE | AO56: FALSE | AP56: FALSE | AQ56: FALSE | AR56: FALSE | AS56: FALSE | AT56: FALSE | AU56: FALSE | AV56: FALSE | AW56: FALSE | AX56: FALSE | AY56: FALSE | AZ56: FALSE | BA56: FALSE | BB56: FALSE | BC56: FALSE | BD56: FALSE | BE56: FALSE | BF56: FALSE | BG56: FALSE | BH56: FALSE | BI56: FALSE | BJ56: FALSE | BK56: FALSE | BM56: 569
A57: 05.220.925/0001-61 | B57: 05220925 | C57: TRANSPORTES TRANSVIDAL S.A | D57: TRANSPORTES TRANSVIDAL | E57: THIAGO MADERS / VITOR | F57: 51-9280-7908 / 9769-5180 | G57: 'Tiago Maders' <lajeado2@transvidal.com.br>; GUILHERME SCHEEREN ME' <lajeado8@transvidal.com.br>; 'Rycael Gregory ' <lajeado@transvidal.com.br>; Evandro Comercial <evandro@transvidal.com.br>;juridico@transvidal.com.br; juridico2@transvidal.com.br; | J57: FALSE | K57: FABIO ALVES CORDEIRO | L57: TRUE | N57: RS | P57: FALSE | Q57: EST BR 153, NUMERO 70 - KM 54 - B. AEROPORTO | R57: ERECHIM | S57: 99708-830 | T57: 05.220.925/0001-61 | U57: 039/0128252 | W57: FALSE | X57: FALSE | Y57: FALSE | Z57: FALSE | AA57: FALSE | AB57: FALSE | AC57: FALSE | AD57: FALSE | AE57: FALSE | AF57: FALSE | AG57: FALSE | AH57: FALSE | AI57: FALSE | AJ57: FALSE | AK57: FALSE | AL57: FALSE | AM57: FALSE | AN57: FALSE | AO57: FALSE | AP57: FALSE | AQ57: FALSE | AR57: FALSE | AS57: FALSE | AT57: FALSE | AU57: FALSE | AV57: FALSE | AW57: FALSE | AX57: FALSE | AY57: FALSE | AZ57: FALSE | BA57: FALSE | BB57: FALSE | BC57: FALSE | BD57: FALSE | BE57: FALSE | BF57: FALSE | BG57: FALSE | BH57: FALSE | BI57: FALSE | BJ57: FALSE | BK57: FALSE | BM57: 274
A58: 05.311.552/0001-34 | B58: 05311552 | C58: TRANSPORTADORA MARQUES ROBERTO LTDA | D58: MARQUES ROBERTO (TMR) | E58: MOACYR ACCORSI JUNIOR/ | F58: 018-9-9133-4578 / 018-9-9771-7098 /18-99151-0115 | G58: claelson@terra.com.br; marquesrober@novolink.com.br;tmrjr@uol.com.br;rafael.accorsi@marquesroberto.com.br; | H58: SUB CONTRATADA TB | J58: TRUE | K58: FABIO ALVES CORDEIRO | L58: TRUE | N58: SP | P58: FALSE | T58: 05.311.552/0001-34 | W58: FALSE | X58: FALSE | Y58: FALSE | Z58: FALSE | AA58: FALSE | AB58: FALSE | AC58: FALSE | AD58: FALSE | AE58: FALSE | AF58: FALSE | AG58: FALSE | AH58: FALSE | AI58: FALSE | AJ58: FALSE | AK58: FALSE | AL58: FALSE | AM58: FALSE | AN58: FALSE | AO58: FALSE | AP58: FALSE | AQ58: FALSE | AR58: FALSE | AS58: FALSE | AT58: FALSE | AU58: FALSE | AV58: TRUE | AW58: FALSE | AX58: FALSE | AY58: FALSE | AZ58: FALSE | BA58: FALSE | BB58: FALSE | BC58: FALSE | BD58: FALSE | BE58: FALSE | BF58: FALSE | BG58: FALSE | BH58: FALSE | BI58: FALSE | BJ58: FALSE | BK58: FALSE | BM58: 634
A59: 053.194.131-06 | B59: 05319413 | C59: THYAGO VALLADARES MACHADO | D59: THYAGO VALLADARES MACHADO | E59: THYAGO | F59: 61-8272-7392 / 61-982727392 | G59: thyagomach@gmail.com; | H59: ANTT: 052938955 SUB CONTRATADO TB | J59: FALSE | K59: FABIO ALVES CORDEIRO | L59: TRUE | N59: GO | P59: TRUE | Q59: 02 HI RUA 26, 14 - B. NÚCLEO HABITACIONAL NOVO GAMA - NOVO GAMA - GO - CEP: 72860026 | R59: NOVO GAMA | S59: 72860026 | T59: 053.194.131-06 | V59: Seca | W59: FALSE | X59: FALSE | Y59: FALSE | Z59: FALSE | AA59: FALSE | AB59: FALSE | AC59: FALSE | AD59: FALSE | AE59: FALSE | AF59: FALSE | AG59: FALSE | AH59: TRUE | AI59: FALSE | AJ59: FALSE | AK59: FALSE | AL59: FALSE | AM59: FALSE | AN59: FALSE | AO59: FALSE | AP59: FALSE | AQ59: TRUE | AR59: FALSE | AS59: TRUE | AT59: FALSE | AU59: FALSE | AV59: FALSE | AW59: FALSE | AX59: FALSE | AY59: FALSE | AZ59: FALSE | BA59: FALSE | BB59: FALSE | BC59: FALSE | BD59: FALSE | BE59: FALSE | BF59: FALSE | BG59: FALSE | BH59: FALSE | BI59: FALSE | BJ59: TRUE | BK59: FALSE | BL59: 45482.494 | BM59: 570
A60: 05.342.379/0001-31 | B60: 05342379 | C60: KM CARGO MULTIMODAL E LOGISTICA LTDA. | D60: KM CARGO | E60: LEANDRO /CRISTIANO | F60: 11-97652-6673 / 11 9 7664 5746 | G60: marco.antonio@kmcargo.com.br ; leandro.roxo@kmcargo.com.br;cgraziotin@kmcargo.com.br; vanessa.paes@kmcargo.com.br;camila.silva@kmcargo.com.br; | J60: FALSE | K60: FABIO ALVES CORDEIRO | L60: TRUE | P60: FALSE | Q60: RUA ESTRELA DO OESTE, 124 - BLOCO C MODULOS C1C2 E C3 - BAIRRO: JARDIM SAO GERALDO | R60: GUARULHOS | S60: 07.140-030 | T60: 05.342.379/0001-31 | U60: 796.176.227.118 | V60: Seca | W60: FALSE | X60: FALSE | Y60: FALSE | Z60: FALSE | AA60: FALSE | AB60: FALSE | AC60: FALSE | AD60: FALSE | AE60: FALSE | AF60: FALSE | AG60: FALSE | AH60: FALSE | AI60: TRUE | AJ60: FALSE | AK60: FALSE | AL60: FALSE | AM60: FALSE | AN60: FALSE | AO60: FALSE | AP60: FALSE | AQ60: FALSE | AR60: FALSE | AS60: FALSE | AT60: FALSE | AU60: FALSE | AV60: FALSE | AW60: FALSE | AX60: FALSE | AY60: FALSE | AZ60: TRUE | BA60: FALSE | BB60: FALSE | BC60: FALSE | BD60: FALSE | BE60: FALSE | BF60: FALSE | BG60: FALSE | BH60: FALSE | BI60: FALSE | BJ60: TRUE | BK60: FALSE | BM60: 1299
A61: 053.595.014-48 | B61: 05359501448 | C61: GLEISON RICHELE DA SILVA RIBEIRO | D61: GLEISON RICHELE DA SILVA RIBEIRO | E61: GLEISON RICHELE DA SILVA RIBEIRO | F61: (81) 98820-8493 | G61: gleisonrichele2@gmail.com; | J61: FALSE | K61: FABIO ALVES CORDEIRO | L61: FALSE | P61: FALSE | Q61: RUA RUI BARBOSA, 268 - VILA RICA - JABOATAO DOS GUARARAPES - PE | R61: JABOATAO DOS GUARARAPES | S61: 54100500 | T61: 053.595.014-48 | W61: FALSE | X61: FALSE | Y61: FALSE | Z61: FALSE | AA61: FALSE | AB61: FALSE | AC61: FALSE | AD61: FALSE | AE61: FALSE | AF61: FALSE | AG61: FALSE | AH61: FALSE | AI61: FALSE | AJ61: FALSE | AK61: FALSE | AL61: FALSE | AM61: FALSE | AN61: FALSE | AO61: FALSE | AP61: FALSE | AQ61: FALSE | AR61: FALSE | AS61: FALSE | AT61: FALSE | AU61: FALSE | AV61: FALSE | AW61: FALSE | AX61: FALSE | AY61: FALSE | AZ61: FALSE | BA61: FALSE | BB61: FALSE | BC61: FALSE | BD61: FALSE | BE61: FALSE | BF61: FALSE | BG61: FALSE | BH61: FALSE | BI61: FALSE | BJ61: FALSE | BK61: FALSE | BL61: 45818.593 | BM61: 1292
A62: 05.454.141/0001-06 | B62: 05454141 | C62: SANDRO PEDROSO BIER | D62: TR SKALONS | E62: SANDRO PEDROSO BIER | F62: (51) 99330-4268 / (51) 99330-4272 | G62: brendaschonarbie@gmail.com; | J62: FALSE | K62: FABIO ALVES CORDEIRO | L62: TRUE | N62: RS | P62: FALSE | Q62: RUA BRASIL, 313 - BAIRRO PREMEM - ESTEIO - RIO GRANDE DO SUL | R62: ESTEIO | S62: 93260-220 | T62: 05.454.141/0001-06 | U62: 043/0129734 | W62: FALSE | X62: FALSE | Y62: FALSE | Z62: FALSE | AA62: FALSE | AB62: FALSE | AC62: FALSE | AD62: FALSE | AE62: FALSE | AF62: FALSE | AG62: FALSE | AH62: FALSE | AI62: FALSE | AJ62: FALSE | AK62: FALSE | AL62: FALSE | AM62: FALSE | AN62: FALSE | AO62: FALSE | AP62: FALSE | AQ62: FALSE | AR62: FALSE | AS62: FALSE | AT62: FALSE | AU62: FALSE | AV62: FALSE | AW62: FALSE | AX62: FALSE | AY62: FALSE | AZ62: FALSE | BA62: FALSE | BB62: FALSE | BC62: FALSE | BD62: FALSE | BE62: FALSE | BF62: FALSE | BG62: FALSE | BH62: FALSE | BI62: FALSE | BJ62: FALSE | BK62: FALSE | BL62: 45814.38 | BM62: 625
A63: 05.594.946/0003-09 | B63: 05594946 | C63: GVM LOGISTICA LTDA | D63: GVM LOGISTICA LTDA | E63: VAGNER / SERGIO / RONILDO | F63: 51-8349-6835 / 4198803-2358 / 41 98730-5451 | G63: felipe.medeiros@gvmbr.com; afc@gvmbr.com; adm@gvmbr.com; gfc@gvmbr.com; | J63: FALSE | K63: FABIO ALVES CORDEIRO | L63: TRUE | N63: SP | P63: FALSE | Q63: DIRETO PELO CARREFOUR | T63: 05.594.946/0003-09 | V63: Seca | W63: FALSE | X63: FALSE | Y63: FALSE | Z63: FALSE | AA63: FALSE | AB63: FALSE | AC63: FALSE | AD63: FALSE | AE63: FALSE | AF63: FALSE | AG63: FALSE | AH63: FALSE | AI63: FALSE | AJ63: FALSE | AK63: FALSE | AL63: FALSE | AM63: FALSE | AN63: FALSE | AO63: FALSE | AP63: FALSE | AQ63: FALSE | AR63: FALSE | AS63: FALSE | AT63: FALSE | AU63: FALSE | AV63: FALSE | AW63: FALSE | AX63: FALSE | AY63: FALSE | AZ63: FALSE | BA63: FALSE | BB63: FALSE | BC63: FALSE | BD63: FALSE | BE63: FALSE | BF63: FALSE | BG63: FALSE | BH63: FALSE | BI63: FALSE | BJ63: FALSE | BK63: FALSE | BL63: 45455.629 | BM63: 1240
A64: 05.594.946/0001-47 | B64: 05594946000147 | C64: GVM LOGISTICA LTDA | D64: GVM LOGISTICA LTDA | E64: VAGNER / SERGIO / RONILDO | F64: 51-8349-6835 / 4198803-2358 / 41 98730-5451 | G64: felipe.medeiros@gvmbr.com; afc@gvmbr.com; adm@gvmbr.com; gfc@gvmbr.com; | H64: ESTE CNPJ INATIVO NO MULTIEMBARCADOR | J64: FALSE | K64: FABIO ALVES CORDEIRO | L64: FALSE | N64: SP | P64: FALSE | Q64: DIRETO PELO CARREFOUR | T64: 05.594.946/0001-47 | V64: Seca | W64: FALSE | X64: FALSE | Y64: FALSE | Z64: FALSE | AA64: FALSE | AB64: FALSE | AC64: FALSE | AD64: FALSE | AE64: FALSE | AF64: FALSE | AG64: FALSE | AH64: FALSE | AI64: FALSE | AJ64: FALSE | AK64: FALSE | AL64: FALSE | AM64: FALSE | AN64: FALSE | AO64: FALSE | AP64: FALSE | AQ64: FALSE | AR64: FALSE | AS64: FALSE | AT64: FALSE | AU64: FALSE | AV64: FALSE | AW64: FALSE | AX64: FALSE | AY64: FALSE | AZ64: FALSE | BA64: FALSE | BB64: FALSE | BC64: FALSE | BD64: FALSE | BE64: FALSE | BF64: FALSE | BG64: FALSE | BH64: FALSE | BI64: FALSE | BJ64: FALSE | BK64: FALSE | BL64: 45708.701 | BM64: 1245
A65: 05.594.946/0009-02 | B65: 05594946000902 | C65: GVM LOGISTICA LTDA | D65: GVM LOGISTICA LTDA | E65: VAGNER / SERGIO / RONILDO | F65: 51-8349-6835 / 4198803-2358 / 41 98730-5451 | G65: felipe.medeiros@gvmbr.com; afc@gvmbr.com; adm@gvmbr.com; gfc@gvmbr.com; | J65: FALSE | K65: FABIO ALVES CORDEIRO | L65: TRUE | N65: PR | P65: FALSE | Q65: DIRETO PELO CARREFOUR | T65: 05.594.946/0009-02 | V65: Seca | W65: FALSE | X65: FALSE | Y65: FALSE | Z65: FALSE | AA65: FALSE | AB65: FALSE | AC65: FALSE | AD65: FALSE | AE65: FALSE | AF65: FALSE | AG65: FALSE | AH65: FALSE | AI65: FALSE | AJ65: FALSE | AK65: FALSE | AL65: FALSE | AM65: FALSE | AN65: FALSE | AO65: FALSE | AP65: FALSE | AQ65: FALSE | AR65: FALSE | AS65: FALSE | AT65: FALSE | AU65: FALSE | AV65: FALSE | AW65: FALSE | AX65: FALSE | AY65: FALSE | AZ65: FALSE | BA65: FALSE | BB65: FALSE | BC65: FALSE | BD65: FALSE | BE65: FALSE | BF65: FALSE | BG65: FALSE | BH65: FALSE | BI65: FALSE | BJ65: FALSE | BK65: FALSE | BL65: 45716.474 | BM65: 649
A66: 05.679.882/0001-87 | B66: 05679882 | C66: F & P TRANSPORTES EIRELI | D66: F & P TRANSPORTES EIRELI | J66: FALSE | K66: FABIO ALVES CORDEIRO | L66: TRUE | N66: MG | P66: FALSE | Q66: R XV DE NOVEMBRO,1040 - ITAQUARA -MG | R66: ITAQUARA | S66: 35488000 | T66: 05.679.882/0001-87 | U66: 001975552.00-0 | W66: FALSE | X66: FALSE | Y66: FALSE | Z66: FALSE | AA66: FALSE | AB66: FALSE | AC66: FALSE | AD66: FALSE | AE66: FALSE | AF66: FALSE | AG66: FALSE | AH66: FALSE | AI66: FALSE | AJ66: FALSE | AK66: FALSE | AL66: FALSE | AM66: FALSE | AN66: FALSE | AO66: FALSE | AP66: FALSE | AQ66: FALSE | AR66: FALSE | AS66: FALSE | AT66: FALSE | AU66: FALSE | AV66: FALSE | AW66: FALSE | AX66: FALSE | AY66: FALSE | AZ66: FALSE | BA66: FALSE | BB66: FALSE | BC66: FALSE | BD66: FALSE | BE66: FALSE | BF66: FALSE | BG66: FALSE | BH66: FALSE | BI66: FALSE | BJ66: FALSE | BK66: FALSE | BM66: 190
A67: 05923435000121 | B67: 05923435 | C67: RODOBRAVO TRANSPORTES E LOGISTICA L | D67: RODOBRAVO | E67: MARIA CRISTINA MACHADO RIBEIRO | F67: 2124716487 | G67: rodobravo@transrodobravo.com.br; | J67: TRUE | K67: FABIO ALVES CORDEIRO | L67: TRUE | N67: RJ | P67: FALSE | Q67: AV BENJAMIN PINTO DIAS,184 | R67: BELFORD ROXO | S67: 26130000 | T67: 05923435000121 | U67: 77.703.160 | W67: FALSE | X67: FALSE | Y67: FALSE | Z67: FALSE | AA67: FALSE | AB67: FALSE | AC67: FALSE | AD67: FALSE | AE67: FALSE | AF67: FALSE | AG67: FALSE | AH67: FALSE | AI67: FALSE | AJ67: FALSE | AK67: FALSE | AL67: FALSE | AM67: FALSE | AN67: FALSE | AO67: FALSE | AP67: FALSE | AQ67: FALSE | AR67: FALSE | AS67: FALSE | AT67: FALSE | AU67: FALSE | AV67: FALSE | AW67: FALSE | AX67: FALSE | AY67: FALSE | AZ67: FALSE | BA67: FALSE | BB67: FALSE | BC67: FALSE | BD67: FALSE | BE67: FALSE | BF67: FALSE | BG67: FALSE | BH67: FALSE | BI67: FALSE | BJ67: FALSE | BK67: FALSE | BM67: 1271
A68: 06.373.063/0001-70 | B68: 06373063 | C68: PRODELOG TRANSPORTES LTDA | D68: PRODELOG TRANSPORTES LTDA | E68: GUILHERME | F68: 11 95765-1725 | G68: guilherme@prodelog.com.br ; ELOIZE@PRODELOG.COM.BR; | H68: ANTT: 010416346 | J68: FALSE | K68: FABIO ALVES CORDEIRO | L68: TRUE | N68: SP | P68: FALSE | Q68: EST MUNICIPAL DO VARJAO, 6250 - CXPST 3502 CEP 13214970 - JARDIM NOVO HORIZONTE - JUNDIAI - SP | R68: JUNDIAI | S68: 13212590 | T68: 06.373.063/0001-70 | U68: 407.484.692.117 | W68: FALSE | X68: FALSE | Y68: FALSE | Z68: FALSE | AA68: FALSE | AB68: FALSE | AC68: FALSE | AD68: FALSE | AE68: FALSE | AF68: FALSE | AG68: FALSE | AH68: FALSE | AI68: FALSE | AJ68: FALSE | AK68: FALSE | AL68: FALSE | AM68: FALSE | AN68: FALSE | AO68: FALSE | AP68: FALSE | AQ68: FALSE | AR68: FALSE | AS68: FALSE | AT68: FALSE | AU68: FALSE | AV68: FALSE | AW68: FALSE | AX68: FALSE | AY68: FALSE | AZ68: FALSE | BA68: FALSE | BB68: FALSE | BC68: FALSE | BD68: FALSE | BE68: FALSE | BF68: FALSE | BG68: FALSE | BH68: FALSE | BI68: FALSE | BJ68: FALSE | BK68: FALSE | BL68: 45807.468 | BM68: 635
A69: 064.779.478-03 | B69: 06477947 | C69: EDGAR ISSAMU KAMEOKA | D69: EDGAR ISSAMU KAMEOKA | E69: EDGAR | F69: 11-990225727 | G69: transportesritaamorim@gmail.com; | H69: ANTT: 011889434 - | J69: FALSE | K69: FABIO ALVES CORDEIRO | L69: TRUE | N69: SP | P69: FALSE | Q69: CORONEL ESDRAS DE OLIVEIRA, 451 - B. PARQUE CASA DE PEDRA - SÃO PAULO - SP CEP: 02351030 | R69: SÃO PAULO | S69: 02351030 | T69: 064.779.478-03 | W69: FALSE | X69: FALSE | Y69: FALSE | Z69: FALSE | AA69: FALSE | AB69: FALSE | AC69: FALSE | AD69: FALSE | AE69: FALSE | AF69: FALSE | AG69: FALSE | AH69: FALSE | AI69: FALSE | AJ69: FALSE | AK69: FALSE | AL69: FALSE | AM69: FALSE | AN69: FALSE | AO69: FALSE | AP69: FALSE | AQ69: FALSE | AR69: FALSE | AS69: FALSE | AT69: FALSE | AU69: FALSE | AV69: FALSE | AW69: FALSE | AX69: FALSE | AY69: FALSE | AZ69: FALSE | BA69: FALSE | BB69: FALSE | BC69: FALSE | BD69: FALSE | BE69: FALSE | BF69: FALSE | BG69: FALSE | BH69: FALSE | BI69: FALSE | BJ69: FALSE | BK69: FALSE | BL69: 45482.603 | BM69: 662
A70: 068.960.258-83 | B70: 06896025883 | C70: GABRIEL VALLE CAMOS | D70: GABRIEL VALLE CAMOS | F70: 1123740734 | J70: FALSE | K70: FABIO ALVES CORDEIRO | L70: TRUE | N70: SP | P70: FALSE | Q70: Coronel Bento Pires., 25 - CENTRO - TATUÍ - SP - CEP: 18270190 | R70: TATUI | S70: 8270190 | T70: 068.960.258-83 | W70: FALSE | X70: FALSE | Y70: FALSE | Z70: FALSE | AA70: FALSE | AB70: FALSE | AC70: FALSE | AD70: FALSE | AE70: FALSE | AF70: FALSE | AG70: FALSE | AH70: FALSE | AI70: FALSE | AJ70: FALSE | AK70: FALSE | AL70: FALSE | AM70: FALSE | AN70: FALSE | AO70: FALSE | AP70: FALSE | AQ70: FALSE | AR70: FALSE | AS70: FALSE | AT70: FALSE | AU70: FALSE | AV70: FALSE | AW70: FALSE | AX70: FALSE | AY70: FALSE | AZ70: FALSE | BA70: FALSE | BB70: FALSE | BC70: FALSE | BD70: FALSE | BE70: FALSE | BF70: FALSE | BG70: FALSE | BH70: FALSE | BI70: FALSE | BJ70: FALSE | BK70: FALSE | BM70: 612
A71: 06.965.514/0001-68 | B71: 06965514 | C71: TRANSPORTADORA GORGONHO LTDA | D71: TRANSPORTADORA GORGONHO LTDA | E71: JOSE ROBERTO DE AZEVEDO | F71: (81) 3378-6192 | G71: diretoria@sistemacontabil.org; george@gorgonho.com.br; alexjose@gorgonho.com.br; roberto@gorgonho.com.br; robertojr@gorgonho.com.br; claudia@gorgonho.com.br; | J71: FALSE | K71: FABIO ALVES CORDEIRO | L71: TRUE | N71: PE | P71: FALSE | Q71: R PALMEIRINA (LOT. ENGENHO GUARARAPES), 149 - JABOATAO DOS GUARARAPES - PE | R71: JABOATAO DOS GUARARAPES | S71: 54.368-230 | T71: 06.965.514/0001-68 | U71: 036163392 | W71: FALSE | X71: FALSE | Y71: FALSE | Z71: FALSE | AA71: FALSE | AB71: FALSE | AC71: FALSE | AD71: FALSE | AE71: FALSE | AF71: FALSE | AG71: FALSE | AH71: FALSE | AI71: FALSE | AJ71: FALSE | AK71: FALSE | AL71: FALSE | AM71: FALSE | AN71: FALSE | AO71: FALSE | AP71: FALSE | AQ71: FALSE | AR71: FALSE | AS71: FALSE | AT71: FALSE | AU71: FALSE | AV71: FALSE | AW71: FALSE | AX71: FALSE | AY71: FALSE | AZ71: FALSE | BA71: FALSE | BB71: FALSE | BC71: FALSE | BD71: FALSE | BE71: FALSE | BF71: FALSE | BG71: FALSE | BH71: FALSE | BI71: FALSE | BJ71: FALSE | BK71: FALSE | BM71: 1220
A72: 07.063.666/0001-38 | B72: 07063666 | C72: VINICIUS GUSTAVO CARBONO MARQUES DA SILVA | D72: VINICIUS GUSTAVO CARBONO MARQUES DA SILVA | E72: DANIELE | F72: (19) 99766-6930 | G72: daniele@vm.log.br; | J72: FALSE | K72: FABIO ALVES CORDEIRO | L72: TRUE | N72: AM | P72: FALSE | Q72: AV TORQUATO TAPAJOS, 7503 - SALA 2 - C LOTE 12 GALPAO2 - TARUMA - MANAUS - AM - CEP: | R72: MANAUS | S72: 69.041-025 | T72: 07.063.666/0001-38 | U72: 54373433 | W72: FALSE | X72: FALSE | Y72: FALSE | Z72: FALSE | AA72: FALSE | AB72: FALSE | AC72: FALSE | AD72: FALSE | AE72: FALSE | AF72: FALSE | AG72: FALSE | AH72: FALSE | AI72: FALSE | AJ72: FALSE | AK72: FALSE | AL72: FALSE | AM72: FALSE | AN72: FALSE | AO72: FALSE | AP72: FALSE | AQ72: FALSE | AR72: FALSE | AS72: FALSE | AT72: FALSE | AU72: FALSE | AV72: FALSE | AW72: FALSE | AX72: FALSE | AY72: FALSE | AZ72: FALSE | BA72: FALSE | BB72: FALSE | BC72: FALSE | BD72: FALSE | BE72: FALSE | BF72: FALSE | BG72: FALSE | BH72: FALSE | BI72: FALSE | BJ72: FALSE | BK72: FALSE | BL72: 45708.522 | BM72: 659
A73: 07.063.949/0002-60 | B73: 07063949 | C73: BARBIERI TRANSPORTES S/A | D73: BARBIERI TRANSPORTES | F73: (49) 9998-78020 | H73: ANTT 07548550 | J73: FALSE | K73: FABIO ALVES CORDEIRO | L73: TRUE | N73: SP | P73: FALSE | Q73: ROD AKZO NOBEL, 433 - LETRA D - ITUPEVA - SP - CEP: 13295-000 | R73: ITUPEVA | S73: 13295-000 | T73: 07.063.949/0002-60 | U73: 388060433110 | W73: FALSE | X73: FALSE | Y73: FALSE | Z73: FALSE | AA73: FALSE | AB73: FALSE | AC73: FALSE | AD73: FALSE | AE73: FALSE | AF73: FALSE | AG73: FALSE | AH73: FALSE | AI73: FALSE | AJ73: FALSE | AK73: FALSE | AL73: FALSE | AM73: FALSE | AN73: FALSE | AO73: FALSE | AP73: FALSE | AQ73: FALSE | AR73: FALSE | AS73: FALSE | AT73: FALSE | AU73: FALSE | AV73: FALSE | AW73: FALSE | AX73: FALSE | AY73: FALSE | AZ73: FALSE | BA73: FALSE | BB73: FALSE | BC73: FALSE | BD73: FALSE | BE73: FALSE | BF73: FALSE | BG73: FALSE | BH73: FALSE | BI73: FALSE | BJ73: FALSE | BK73: FALSE | BM73: 655
A74: 07.104.460/0002-90 | B74: 07104460 | C74: E T N TRANSPORTES RODOVIARIOS DE CARGAS NACIONAL E | D74: ETN | E74: NELCINDO / DANIELA | F74: 5198089631 - 5182341980 - (51) 3032-2834 | G74: etntransportes@etntransportes.com.br; daniela@etntransportes.com.br ; | J74: FALSE | K74: FABIO ALVES CORDEIRO | L74: TRUE | N74: SP | P74: FALSE | Q74: ROD REGIS BITTENCOURT , SN - KM 294 SALA 19 - POTUVERA - | R74: ITAPECERICA DA SERRA | S74: 06.882-700 | T74: 07.104.460/0002-90 | U74: 370149887116 | V74: Seca | W74: FALSE | X74: FALSE | Y74: FALSE | Z74: FALSE | AA74: FALSE | AB74: FALSE | AC74: FALSE | AD74: FALSE | AE74: FALSE | AF74: FALSE | AG74: FALSE | AH74: FALSE | AI74: FALSE | AJ74: FALSE | AK74: FALSE | AL74: FALSE | AM74: FALSE | AN74: FALSE | AO74: TRUE | AP74: FALSE | AQ74: TRUE | AR74: FALSE | AS74: TRUE | AT74: FALSE | AU74: FALSE | AV74: TRUE | AW74: FALSE | AX74: FALSE | AY74: FALSE | AZ74: TRUE | BA74: FALSE | BB74: TRUE | BC74: FALSE | BD74: FALSE | BE74: FALSE | BF74: FALSE | BG74: TRUE | BH74: TRUE | BI74: FALSE | BJ74: FALSE | BK74: FALSE | BM74: 1285
A75: 07.104.460/0001-09 | B75: 0710446009 | C75: E T N TRANSPORTES RODOVIARIOS DE CARGAS NACIONAL E | D75: ETN | E75: NELCINDO / DANIELA | F75: 5198089631 - 5182341980 - (51) 3032-2834 | G75: etntransportes@etntransportes.com.br; daniela@etntransportes.com.br ; | J75: FALSE | K75: FABIO ALVES CORDEIRO | L75: TRUE | N75: SP | P75: FALSE | Q75: RUA MAMORE, 344 - S/207 - B. IGARA - CANOAS - RS | R75: CANOAS | S75: 92410-420 | T75: 07.104.460/0001-09 | U75: 024/0355440 | V75: Seca | W75: FALSE | X75: FALSE | Y75: FALSE | Z75: FALSE | AA75: FALSE | AB75: FALSE | AC75: FALSE | AD75: FALSE | AE75: FALSE | AF75: FALSE | AG75: FALSE | AH75: FALSE | AI75: FALSE | AJ75: FALSE | AK75: FALSE | AL75: FALSE | AM75: FALSE | AN75: FALSE | AO75: TRUE | AP75: FALSE | AQ75: TRUE | AR75: FALSE | AS75: TRUE | AT75: FALSE | AU75: FALSE | AV75: TRUE | AW75: FALSE | AX75: FALSE | AY75: FALSE | AZ75: TRUE | BA75: FALSE | BB75: TRUE | BC75: FALSE | BD75: FALSE | BE75: FALSE | BF75: FALSE | BG75: TRUE | BH75: TRUE | BI75: FALSE | BJ75: FALSE | BK75: FALSE | BL75: 45813.698 | BM75: 576
A76: 07.271.074/0001-01 | B76: 07271074 | C76: DAMACEL TRANSPORTES LTDA | D76: DAMACEL TRANSPORTES LTDA | E76: RAFAEL | F76: 54-98164-0174 | G76: logistica@damacel.com.br; logistica2@damacel.com.br; financeirodamacel@gmail.com; | J76: FALSE | K76: FABIO ALVES CORDEIRO | L76: TRUE | N76: RS | P76: FALSE | Q76: AV JUSCELINO KUBITSCHEK DE OLIVEIRA, 75 - B. MONTE CLARO | R76: VACARIA | S76: 95200-000 | T76: 07.271.074/0001-01 | U76: 154/0096820 | W76: FALSE | X76: FALSE | Y76: FALSE | Z76: FALSE | AA76: FALSE | AB76: FALSE | AC76: FALSE | AD76: FALSE | AE76: FALSE | AF76: FALSE | AG76: FALSE | AH76: TRUE | AI76: FALSE | AJ76: TRUE | AK76: FALSE | AL76: FALSE | AM76: FALSE | AN76: FALSE | AO76: FALSE | AP76: FALSE | AQ76: FALSE | AR76: FALSE | AS76: FALSE | AT76: FALSE | AU76: FALSE | AV76: FALSE | AW76: FALSE | AX76: FALSE | AY76: FALSE | AZ76: TRUE | BA76: FALSE | BB76: FALSE | BC76: FALSE | BD76: FALSE | BE76: FALSE | BF76: FALSE | BG76: TRUE | BH76: FALSE | BI76: FALSE | BJ76: FALSE | BK76: FALSE | BM76: 1226
A77: 07.271.074/0002-92 | B77: 07271074000292 | C77: DAMACEL TRANSPORTES LTDA | D77: DAMACEL TRANSPORTES LTDA | E77: RAFAEL | F77: 54-98164-0174 | G77: logistica@damacel.com.br; logistica2@damacel.com.br; financeirodamacel@gmail.com; | J77: FALSE | K77: FABIO ALVES CORDEIRO | L77: TRUE | N77: RS | P77: FALSE | Q77: AV JUSCELINO KUBITSCHEK DE OLIVEIRA, 75 - B. MONTE CLARO | R77: VACARIA | S77: 95200-000 | T77: 07.271.074/0002-92 | U77: 154/0096820 | W77: FALSE | X77: FALSE | Y77: FALSE | Z77: FALSE | AA77: FALSE | AB77: FALSE | AC77: FALSE | AD77: FALSE | AE77: FALSE | AF77: FALSE | AG77: FALSE | AH77: TRUE | AI77: FALSE | AJ77: TRUE | AK77: FALSE | AL77: FALSE | AM77: FALSE | AN77: FALSE | AO77: FALSE | AP77: FALSE | AQ77: FALSE | AR77: FALSE | AS77: FALSE | AT77: FALSE | AU77: FALSE | AV77: FALSE | AW77: FALSE | AX77: FALSE | AY77: FALSE | AZ77: TRUE | BA77: FALSE | BB77: FALSE | BC77: FALSE | BD77: FALSE | BE77: FALSE | BF77: FALSE | BG77: TRUE | BH77: FALSE | BI77: FALSE | BJ77: FALSE | BK77: FALSE | BL77: 45708.653 | BM77: 445
A78: 073087165000116 | B78: 07308716 | C78: CAPITAL EXP.MUD.E TRANSP.ROD LTDA | D78: CAPITAL EXPRES- | E78: RAFAEL BOTELHO | F78: 11 3936 6969 | G78: rafael@capitaltransportadora.com.br; | I78: ITAMIRAN - 86*20888 | J78: TRUE | K78: FABIO ALVES CORDEIRO | L78: FALSE | P78: FALSE | Q78: AV. SEBASTIÃO HENRIQUES, 433 | R78: SÃO PAULO | S78: 2723050 | T78: 073087165000116 | U78: 114077526110 | W78: FALSE | X78: FALSE | Y78: FALSE | Z78: FALSE | AA78: FALSE | AB78: FALSE | AC78: FALSE | AD78: FALSE | AE78: FALSE | AF78: FALSE | AG78: FALSE | AH78: FALSE | AI78: FALSE | AJ78: FALSE | AK78: FALSE | AL78: FALSE | AM78: FALSE | AN78: FALSE | AO78: FALSE | AP78: FALSE | AQ78: FALSE | AR78: FALSE | AS78: FALSE | AT78: FALSE | AU78: FALSE | AV78: FALSE | AW78: FALSE | AX78: FALSE | AY78: FALSE | AZ78: FALSE | BA78: FALSE | BB78: FALSE | BC78: FALSE | BD78: FALSE | BE78: FALSE | BF78: FALSE | BG78: FALSE | BH78: FALSE | BI78: FALSE | BJ78: FALSE | BK78: FALSE | BM78: 1056
A79: 07.410.172/0001-82 | B79: 07410172 | C79: TRANSDEZIDERIO TRANSPORTES E LOGISTICA EIRELI | D79: TRANSDEZIDERIO TRANSPORTES E LOGISTICA EIRELI | E79: RENAN DA LUZ DEZIDERIO | F79: 11-2279-5423 / 11-94751-2481 | G79: adm@transdeziderio.com; | H79: sub TB | J79: FALSE | K79: FABIO ALVES CORDEIRO | L79: TRUE | N79: SP | P79: TRUE | Q79: RUA JEREMOABO, 473 - PRESIDENTE DUTRA - GUARULHOS - CEP: 07172-140 | R79: GUARULHOS | S79: 07172-140 | T79: 07.410.172/0001-82 | U79: 336766060110 | W79: FALSE | X79: FALSE | Y79: FALSE | Z79: FALSE | AA79: FALSE | AB79: FALSE | AC79: FALSE | AD79: FALSE | AE79: FALSE | AF79: FALSE | AG79: FALSE | AH79: FALSE | AI79: TRUE | AJ79: TRUE | AK79: FALSE | AL79: FALSE | AM79: FALSE | AN79: FALSE | AO79: FALSE | AP79: FALSE | AQ79: FALSE | AR79: FALSE | AS79: FALSE | AT79: FALSE | AU79: TRUE | AV79: FALSE | AW79: FALSE | AX79: FALSE | AY79: FALSE | AZ79: FALSE | BA79: FALSE | BB79: FALSE | BC79: FALSE | BD79: FALSE | BE79: FALSE | BF79: FALSE | BG79: FALSE | BH79: FALSE | BI79: FALSE | BJ79: TRUE | BK79: FALSE | BM79: 556
A80: 07.585.251/0001-24 | B80: 07585251 | C80: MAZZOCHI & MATIELLO TRANSPORTES LTDA | D80: MAZZOCHI | E80: JOÃO | F80: 49-99305050 | G80: cristian@mmlogistic.com.br; administrativo@mmlogistic.com.br; Joao@mmlogistic.com.br; Operacional@mmlogistic.com.br; | H80: RNTRC 043942077 - direto pelo carrefour | J80: FALSE | K80: FABIO ALVES CORDEIRO | L80: TRUE | N80: SC | P80: FALSE | Q80: AVENIDA GIACOMO LUNARDI, 338, SALA 01, XAXIM - SC, 89.825-000 | R80: XAXIM | S80: 89.825-000 | T80: 07.585.251/0001-24 | U80: 255070071 | W80: FALSE | X80: FALSE | Y80: FALSE | Z80: FALSE | AA80: FALSE | AB80: FALSE | AC80: FALSE | AD80: FALSE | AE80: FALSE | AF80: FALSE | AG80: FALSE | AH80: TRUE | AI80: FALSE | AJ80: FALSE | AK80: FALSE | AL80: FALSE | AM80: FALSE | AN80: FALSE | AO80: FALSE | AP80: FALSE | AQ80: FALSE | AR80: FALSE | AS80: FALSE | AT80: FALSE | AU80: FALSE | AV80: FALSE | AW80: FALSE | AX80: FALSE | AY80: FALSE | AZ80: FALSE | BA80: FALSE | BB80: FALSE | BC80: FALSE | BD80: FALSE | BE80: FALSE | BF80: FALSE | BG80: TRUE | BH80: TRUE | BI80: FALSE | BJ80: TRUE | BK80: FALSE | BM80: 239
